Workbook
Name \0: #REF!
Name \A: #REF!
Name \b: #REF!
Name \c: #REF!
Name \D: #REF!
Name \E: #REF!
Name \F: #REF!
Name \G: #REF!
Name \H: #REF!
Name \I: #REF!
Name \J: #REF!
Name \K: #REF!
Name \L: #REF!
Name \m: #REF!
Name \M2: #REF!
Name \N: #REF!
Name \O: #REF!
Name \P: #REF!
Name \paul: #REF!
Name \q: #REF!
Name \R: #REF!
Name \S: #REF!
Name \t: #REF!
Name \U: #REF!
Name \V: #REF!
Name \W: #REF!
Name \X: '[1]טורים 98'!$HJ$146
Name \Y: #REF!
Name \Z: #REF!
Name _: #REF!
Name _?ץד_F?S_עכ.ד_Fע?S_GF: #REF!
Name __: {"'1-TheatreBkgs'!$A$1:$L$102"}
Name ___: {"'1-TheatreBkgs'!$A$1:$L$102"}
Name ____: #REF!
Name _____________________nnd1: #REF!
Name ____________________nnd1: #REF!
Name ____________________RIV1: #REF!
Name ___________________nnd1: #REF!
Name ___________________RIV1: #REF!
Name __________________nnd1: #REF!
Name __________________RIV1: #REF!
Name _________________nnd1: #REF!
Name _________________RIV1: #REF!
Name ________________nnd1: #REF!
Name ________________RIV1: #REF!
Name _______________nnd1: #REF!
Name _______________RIV1: #REF!
Name ______________nnd1: #REF!
Name ______________RIV1: #REF!
Name _____________nnd1: #REF!
Name _____________RIV1: #REF!
Name ____________a1: {"'2ND_QUAR'!$A$1:$P$106"}
Name ____________nnd1: #REF!
Name ____________RIV1: #REF!
Name ___________a1: {"'2ND_QUAR'!$A$1:$P$106"}
Name ___________nnd1: #REF!
Name ___________RIV1: #REF!
Name __________a1: {"'2ND_QUAR'!$A$1:$P$106"}
Name __________nnd1: #REF!
Name __________RIV1: #REF!

Sheet Cover Page

Sheet Customer's Questionnaire
G5: Customer's Questioniere
H6: Name: | I6: GOOGOO DOLLS
G7: Please fill-in the following questionnaire in order to complete the financial model:
G8: 1 | H8: Company's sector | I8: Food-Tech / Ag-Tech
G9: 2 | H9: Upcoming Round | I9: Round C
G10: 3 | H10: Capital Raise Goal | I10: 30000000 | J10: =IF(I10-_xlfn.XLOOKUP(I8&I9,Benchmark_Table!C:C,Benchmark_Table!K:K,0)<0,"Too Low",IF(I10-_xlfn.XLOOKUP(I8&I9,Benchmark_Table!C:C,Benchmark_Table!M:M,0)>0,"Too High",IF(AND(AVERAGE(_xlfn.XLOOKUP(I8&I9,Benchmark_Table!C:C,Benchmark_Table!K:K,0),_xlfn.XLOOKUP(I8&I9,Benchmark_Table!C:C,Benchmark_Table!L:L,0))<I10,AVERAGE(_xlfn.XLOOKUP(I8&I9,Benchmark_Table!C:C,Benchmark_Table!M:M,0),_xlfn.XLOOKUP(I8&I9,Benchmark_Table!C:C,Benchmark_Table!L:L,0))>I10),"Base",IF(AND(_xlfn.XLOOKUP(I8&I9,Benchmark_Table!C:C,Benchmark_Table!L:L,0)>I10,_xlfn.XLOOKUP(I8&I9,Benchmark_Table!C:C,Benchmark_Table!K:K,0)<I10),"Low",IF(_xlfn.XLOOKUP(I8&I9,Benchmark_Table!C:C,Benchmark_Table!K:K,0)-I10=0,"Low",IF(_xlfn.XLOOKUP(I8&I9,Benchmark_Table!C:C,Benchmark_Table!M:M,0)-I10=0,"High","High")))))) -> Too High
G11: 4 | H11: Avg_Years_Since_Founding | I11: 7 | J11: =IF(_xlfn.XLOOKUP(I8&I9,Benchmark_Table!C:C,Benchmark_Table!E:E,0)=I11,"In Benchmark","Not In Benchmark") -> Not In Benchmark
G12: 5 | H12: First Year Financial Model | I12: 2026
G14: 6 | H14: Commercial:
H15: Please define the Customers and Products
G16: 6.a. | H16: Customers: | I16: Type: | J16: Territory
H17: Hungry AF | I17: B2C | J17: US
H18: BULO | I18: Direct | J18: EU
G29: 6.b. | H29: Products: | I29: Revenue Type: | J29: Price: | K29: Cost:
H30: Big MAC | I30: Hardware | J30: 1000 | K30: 500
H31: MCMC | I31: Software / SaaS | J31: 10 | K31: 5
G41: 7 | H41: Lets Scale:
H42: Please specify the Deployment Plan:
H43: Revenue Type | I43: Customer Name | J43: Type | K43: Territory | L43: Product Name | M43: Price | N43: Cost: | O43: ="Q1-"&'Customer''s Questionnaire'!$I$12 -> Q1-2026 | P43: ="Q2-"&'Customer''s Questionnaire'!$I$12 -> Q2-2026 | Q43: ="Q3-"&'Customer''s Questionnaire'!$I$12 -> Q3-2026 | R43: ="Q4-"&'Customer''s Questionnaire'!$I$12 -> Q4-2026 | S43: =I12+1 -> 2027
H44: =_xlfn.XLOOKUP(L44,$H$30:$H$39,$I$30:$I$39,0) -> Hardware | I44: Hungry AF | J44: =_xlfn.XLOOKUP(I44,$H$17:$H$26,$I$17:$I$26,0) -> B2C | K44: =_xlfn.XLOOKUP(I44,$H$17:$H$26,$J$17:$J$26,0) -> US | L44: Big MAC | M44: =_xlfn.XLOOKUP(L44,$H$30:$H$39,$J$30:$J$39,0) -> 1000 | N44: =_xlfn.XLOOKUP(L44,$H$30:$H$39,$K$30:$K$39,0) -> 500 | O44: 10 | P44: 10 | Q44: 10 | R44: 10 | S44: 50
H45: =_xlfn.XLOOKUP(L45,$H$30:$H$39,$I$30:$I$39,0) -> Software / SaaS | I45: BULO | J45: =_xlfn.XLOOKUP(I45,$H$17:$H$26,$I$17:$I$26,0) -> Direct | K45: =_xlfn.XLOOKUP(I45,$H$17:$H$26,$J$17:$J$26,0) -> EU | L45: MCMC | M45: =_xlfn.XLOOKUP(L45,$H$30:$H$39,$J$30:$J$39,0) -> 10 | N45: =_xlfn.XLOOKUP(L45,$H$30:$H$39,$K$30:$K$39,0) -> 5 | O45: 1000 | P45: 1000 | Q45: 1000 | R45: 1000 | S45: 5000
H46: =_xlfn.XLOOKUP(L46,$H$30:$H$39,$I$30:$I$39,0) -> 0 | J46: =_xlfn.XLOOKUP(I46,$H$17:$H$26,$I$17:$I$26,0) -> 0 | K46: =_xlfn.XLOOKUP(I46,$H$17:$H$26,$J$17:$J$26,0) -> 0 | M46: =_xlfn.XLOOKUP(L46,$H$30:$H$39,$J$30:$J$39,0) -> 0 | N46: =_xlfn.XLOOKUP(L46,$H$30:$H$39,$K$30:$K$39,0) -> 0
H47: =_xlfn.XLOOKUP(L47,$H$30:$H$39,$I$30:$I$39,0) -> 0 | J47: =_xlfn.XLOOKUP(I47,$H$17:$H$26,$I$17:$I$26,0) -> 0 | K47: =_xlfn.XLOOKUP(I47,$H$17:$H$26,$J$17:$J$26,0) -> 0 | M47: =_xlfn.XLOOKUP(L47,$H$30:$H$39,$J$30:$J$39,0) -> 0 | N47: =_xlfn.XLOOKUP(L47,$H$30:$H$39,$K$30:$K$39,0) -> 0
H48: =_xlfn.XLOOKUP(L48,$H$30:$H$39,$I$30:$I$39,0) -> 0 | J48: =_xlfn.XLOOKUP(I48,$H$17:$H$26,$I$17:$I$26,0) -> 0 | K48: =_xlfn.XLOOKUP(I48,$H$17:$H$26,$J$17:$J$26,0) -> 0 | M48: =_xlfn.XLOOKUP(L48,$H$30:$H$39,$J$30:$J$39,0) -> 0 | N48: =_xlfn.XLOOKUP(L48,$H$30:$H$39,$K$30:$K$39,0) -> 0
H49: =_xlfn.XLOOKUP(L49,$H$30:$H$39,$I$30:$I$39,0) -> 0 | J49: =_xlfn.XLOOKUP(I49,$H$17:$H$26,$I$17:$I$26,0) -> 0 | K49: =_xlfn.XLOOKUP(I49,$H$17:$H$26,$J$17:$J$26,0) -> 0 | M49: =_xlfn.XLOOKUP(L49,$H$30:$H$39,$J$30:$J$39,0) -> 0 | N49: =_xlfn.XLOOKUP(L49,$H$30:$H$39,$K$30:$K$39,0) -> 0
H50: =_xlfn.XLOOKUP(L50,$H$30:$H$39,$I$30:$I$39,0) -> 0 | J50: =_xlfn.XLOOKUP(I50,$H$17:$H$26,$I$17:$I$26,0) -> 0 | K50: =_xlfn.XLOOKUP(I50,$H$17:$H$26,$J$17:$J$26,0) -> 0 | M50: =_xlfn.XLOOKUP(L50,$H$30:$H$39,$J$30:$J$39,0) -> 0 | N50: =_xlfn.XLOOKUP(L50,$H$30:$H$39,$K$30:$K$39,0) -> 0
H51: =_xlfn.XLOOKUP(L51,$H$30:$H$39,$I$30:$I$39,0) -> 0 | J51: =_xlfn.XLOOKUP(I51,$H$17:$H$26,$I$17:$I$26,0) -> 0 | K51: =_xlfn.XLOOKUP(I51,$H$17:$H$26,$J$17:$J$26,0) -> 0 | M51: =_xlfn.XLOOKUP(L51,$H$30:$H$39,$J$30:$J$39,0) -> 0 | N51: =_xlfn.XLOOKUP(L51,$H$30:$H$39,$K$30:$K$39,0) -> 0
H52: =_xlfn.XLOOKUP(L52,$H$30:$H$39,$I$30:$I$39,0) -> 0 | J52: =_xlfn.XLOOKUP(I52,$H$17:$H$26,$I$17:$I$26,0) -> 0 | K52: =_xlfn.XLOOKUP(I52,$H$17:$H$26,$J$17:$J$26,0) -> 0 | M52: =_xlfn.XLOOKUP(L52,$H$30:$H$39,$J$30:$J$39,0) -> 0 | N52: =_xlfn.XLOOKUP(L52,$H$30:$H$39,$K$30:$K$39,0) -> 0
H53: =_xlfn.XLOOKUP(L53,$H$30:$H$39,$I$30:$I$39,0) -> 0 | J53: =_xlfn.XLOOKUP(I53,$H$17:$H$26,$I$17:$I$26,0) -> 0 | K53: =_xlfn.XLOOKUP(I53,$H$17:$H$26,$J$17:$J$26,0) -> 0 | M53: =_xlfn.XLOOKUP(L53,$H$30:$H$39,$J$30:$J$39,0) -> 0 | N53: =_xlfn.XLOOKUP(L53,$H$30:$H$39,$K$30:$K$39,0) -> 0
H54: =_xlfn.XLOOKUP(L54,$H$30:$H$39,$I$30:$I$39,0) -> 0 | J54: =_xlfn.XLOOKUP(I54,$H$17:$H$26,$I$17:$I$26,0) -> 0 | K54: =_xlfn.XLOOKUP(I54,$H$17:$H$26,$J$17:$J$26,0) -> 0 | M54: =_xlfn.XLOOKUP(L54,$H$30:$H$39,$J$30:$J$39,0) -> 0 | N54: =_xlfn.XLOOKUP(L54,$H$30:$H$39,$K$30:$K$39,0) -> 0
H55: =_xlfn.XLOOKUP(L55,$H$30:$H$39,$I$30:$I$39,0) -> 0 | J55: =_xlfn.XLOOKUP(I55,$H$17:$H$26,$I$17:$I$26,0) -> 0 | K55: =_xlfn.XLOOKUP(I55,$H$17:$H$26,$J$17:$J$26,0) -> 0 | M55: =_xlfn.XLOOKUP(L55,$H$30:$H$39,$J$30:$J$39,0) -> 0 | N55: =_xlfn.XLOOKUP(L55,$H$30:$H$39,$K$30:$K$39,0) -> 0
H56: =_xlfn.XLOOKUP(L56,$H$30:$H$39,$I$30:$I$39,0) -> 0 | J56: =_xlfn.XLOOKUP(I56,$H$17:$H$26,$I$17:$I$26,0) -> 0 | K56: =_xlfn.XLOOKUP(I56,$H$17:$H$26,$J$17:$J$26,0) -> 0 | M56: =_xlfn.XLOOKUP(L56,$H$30:$H$39,$J$30:$J$39,0) -> 0 | N56: =_xlfn.XLOOKUP(L56,$H$30:$H$39,$K$30:$K$39,0) -> 0
H57: =_xlfn.XLOOKUP(L57,$H$30:$H$39,$I$30:$I$39,0) -> 0 | J57: =_xlfn.XLOOKUP(I57,$H$17:$H$26,$I$17:$I$26,0) -> 0 | K57: =_xlfn.XLOOKUP(I57,$H$17:$H$26,$J$17:$J$26,0) -> 0 | M57: =_xlfn.XLOOKUP(L57,$H$30:$H$39,$J$30:$J$39,0) -> 0 | N57: =_xlfn.XLOOKUP(L57,$H$30:$H$39,$K$30:$K$39,0) -> 0
... H63: =_xlfn.XLOOKUP(L63,$H$30:$H$39,$I$30:$I$39,0) -> 0 | J63: =_xlfn.XLOOKUP(I63,$H$17:$H$26,$I$17:$I$26,0) -> 0 | K63: =_xlfn.XLOOKUP(I63,$H$17:$H$26,$J$17:$J$26,0) -> 0 | M63: =_xlfn.XLOOKUP(L63,$H$30:$H$39,$J$30:$J$39,0) -> 0 | N63: =_xlfn.XLOOKUP(L63,$H$30:$H$39,$K$30:$K$39,0) -> 0
H64: Total | O64: =SUM(O44:O63) -> 1010 | P64: =SUM(P44:P63) -> 1010 | Q64: =SUM(Q44:Q63) -> 1010 | R64: =SUM(R44:R63) -> 1010 | S64: =SUM(S44:S63) -> 5050
G66: 8 | H66: Please specify the FTE's (Full-Time-Employment) headcount in the following sections:
H67: P&L Section: | I67: =I12 -> 2026 | J67: =I67+1 -> 2027
H68: COGS | I68: 2 | J68: 3
H69: R&D | I69: 3 | J69: 4
H70: S&M | I70: 4 | J70: 5
H71: G&a | I71: 5 | J71: 6

Sheet Your Company 

Sheet Dashboard
E2: Financial Dashboard
B3: 5-Year revenue, ARR & mix overview
B5: Key metrics — Year 5 (2030)
C7: Total revenue (Yr 5) | F7: Revenue CAGR (Yr1→Yr5) | I7: Software ARR (Yr 5) | L7: Largest customer (Yr 5) | O7: Gross margin (Yr 5)
C8: =G67 -> 194062.5 | F8: =H67 -> 0.24799518 | I8: =G74 -> 194062.5 | L8: =INDEX(B81:B86,MATCH(MAX(G81:G86),G81:G86,0)) -> BULO | O8: ='P&L'!H11 -> 0.5
B63: Supporting data
B65: 1 Total revenue & CAGR | J65: 4 Revenue breakdown — by product
C66: Year 1 (2026) | D66: Year 2 (2027) | E66: Year 3 (2028) | F66: Year 4 (2029) | G66: Year 5 (2030) | H66: CAGR | J66: Product | K66: Year 1 (2026) | L66: Year 2 (2027) | M66: Year 3 (2028) | N66: Year 4 (2029) | O66: Year 5 (2030)
B67: Total Revenue | C67: ='P&L'!D5 -> 80000 | D67: ='P&L'!E5 -> 100000 | E67: ='P&L'!F5 -> 135000 | F67: ='P&L'!G5 -> 168750 | G67: ='P&L'!H5 -> 194062.5 | H67: =IFERROR((G67/C67)^(1/4)-1,0) -> 0.24799518 | J67: =IFERROR(INDEX(_xlfn.ANCHORARRAY($M$115),1),"") -> Big MAC | K67: =IF($J67="",0,SUMIFS(E$116:E$132,$C$116:$C$132,$J67)) -> 40000 | L67: =IF($J67="",0,SUMIFS(F$116:F$132,$C$116:$C$132,$J67)) -> 50000 | M67: =IF($J67="",0,SUMIFS(G$116:G$132,$C$116:$C$132,$J67)) -> 67500 | N67: =IF($J67="",0,SUMIFS(H$116:H$132,$C$116:$C$132,$J67)) -> 84375 | O67: =IF($J67="",0,SUMIFS(I$116:I$132,$C$116:$C$132,$J67)) -> 97031.25 | R67: =TEXT(K67/K$75,"0%") -> 50% | S67: =TEXT(L67/L$75,"0%") -> 50% | T67: =TEXT(M67/M$75,"0%") -> 50% | U67: =TEXT(N67/N$75,"0%") -> 50% | V67: =TEXT(O67/O$75,"0%") -> 50%
B68: CAGR Trajectory | C68: =C67 -> 80000 | D68: =C68*(1+$H$67) -> 99839.615 | E68: =D68*(1+$H$67) -> 124599.36 | F68: =E68*(1+$H$67) -> 155499.4 | G68: =F68*(1+$H$67) -> 194062.5 | J68: =IFERROR(INDEX(_xlfn.ANCHORARRAY($M$115),2),"") -> MCMC | K68: =IF($J68="",0,SUMIFS(E$116:E$132,$C$116:$C$132,$J68)) -> 40000 | L68: =IF($J68="",0,SUMIFS(F$116:F$132,$C$116:$C$132,$J68)) -> 50000 | M68: =IF($J68="",0,SUMIFS(G$116:G$132,$C$116:$C$132,$J68)) -> 67500 | N68: =IF($J68="",0,SUMIFS(H$116:H$132,$C$116:$C$132,$J68)) -> 84375 | O68: =IF($J68="",0,SUMIFS(I$116:I$132,$C$116:$C$132,$J68)) -> 97031.25 | R68: =TEXT(K68/K$75,"0%") -> 50% | S68: =TEXT(L68/L$75,"0%") -> 50% | T68: =TEXT(M68/M$75,"0%") -> 50% | U68: =TEXT(N68/N$75,"0%") -> 50% | V68: =TEXT(O68/O$75,"0%") -> 50%
J69: =IFERROR(INDEX(_xlfn.ANCHORARRAY($M$115),3),"") | K69: =IF($J69="",0,SUMIFS(E$116:E$132,$C$116:$C$132,$J69)) -> 0 | L69: =IF($J69="",0,SUMIFS(F$116:F$132,$C$116:$C$132,$J69)) -> 0 | M69: =IF($J69="",0,SUMIFS(G$116:G$132,$C$116:$C$132,$J69)) -> 0 | N69: =IF($J69="",0,SUMIFS(H$116:H$132,$C$116:$C$132,$J69)) -> 0 | O69: =IF($J69="",0,SUMIFS(I$116:I$132,$C$116:$C$132,$J69)) -> 0 | R69: =TEXT(K69/K$75,"0%") -> 0% | S69: =TEXT(L69/L$75,"0%") -> 0% | T69: =TEXT(M69/M$75,"0%") -> 0% | U69: =TEXT(N69/N$75,"0%") -> 0% | V69: =TEXT(O69/O$75,"0%") -> 0%
J70: =IFERROR(INDEX(_xlfn.ANCHORARRAY($M$115),4),"") | K70: =IF($J70="",0,SUMIFS(E$116:E$132,$C$116:$C$132,$J70)) -> 0 | L70: =IF($J70="",0,SUMIFS(F$116:F$132,$C$116:$C$132,$J70)) -> 0 | M70: =IF($J70="",0,SUMIFS(G$116:G$132,$C$116:$C$132,$J70)) -> 0 | N70: =IF($J70="",0,SUMIFS(H$116:H$132,$C$116:$C$132,$J70)) -> 0 | O70: =IF($J70="",0,SUMIFS(I$116:I$132,$C$116:$C$132,$J70)) -> 0 | R70: =TEXT(K70/K$75,"0%") -> 0% | S70: =TEXT(L70/L$75,"0%") -> 0% | T70: =TEXT(M70/M$75,"0%") -> 0% | U70: =TEXT(N70/N$75,"0%") -> 0% | V70: =TEXT(O70/O$75,"0%") -> 0%
J71: =IFERROR(INDEX(_xlfn.ANCHORARRAY($M$115),5),"") | K71: =IF($J71="",0,SUMIFS(E$116:E$132,$C$116:$C$132,$J71)) -> 0 | L71: =IF($J71="",0,SUMIFS(F$116:F$132,$C$116:$C$132,$J71)) -> 0 | M71: =IF($J71="",0,SUMIFS(G$116:G$132,$C$116:$C$132,$J71)) -> 0 | N71: =IF($J71="",0,SUMIFS(H$116:H$132,$C$116:$C$132,$J71)) -> 0 | O71: =IF($J71="",0,SUMIFS(I$116:I$132,$C$116:$C$132,$J71)) -> 0 | R71: =TEXT(K71/K$75,"0%") -> 0% | S71: =TEXT(L71/L$75,"0%") -> 0% | T71: =TEXT(M71/M$75,"0%") -> 0% | U71: =TEXT(N71/N$75,"0%") -> 0% | V71: =TEXT(O71/O$75,"0%") -> 0%
B72: 2 Software ARR | J72: =IFERROR(INDEX(_xlfn.ANCHORARRAY($M$115),6),"") | K72: =IF($J72="",0,SUMIFS(E$116:E$132,$C$116:$C$132,$J72)) -> 0 | L72: =IF($J72="",0,SUMIFS(F$116:F$132,$C$116:$C$132,$J72)) -> 0 | M72: =IF($J72="",0,SUMIFS(G$116:G$132,$C$116:$C$132,$J72)) -> 0 | N72: =IF($J72="",0,SUMIFS(H$116:H$132,$C$116:$C$132,$J72)) -> 0 | O72: =IF($J72="",0,SUMIFS(I$116:I$132,$C$116:$C$132,$J72)) -> 0 | R72: =TEXT(K72/K$75,"0%") -> 0% | S72: =TEXT(L72/L$75,"0%") -> 0% | T72: =TEXT(M72/M$75,"0%") -> 0% | U72: =TEXT(N72/N$75,"0%") -> 0% | V72: =TEXT(O72/O$75,"0%") -> 0%
C73: Year 1 (2026) | D73: Year 2 (2027) | E73: Year 3 (2028) | F73: Year 4 (2029) | G73: Year 5 (2030) | H73: CAGR | J73: =IFERROR(INDEX(_xlfn.ANCHORARRAY($M$115),7),"") | K73: =IF($J73="",0,SUMIFS(E$116:E$132,$C$116:$C$132,$J73)) -> 0 | L73: =IF($J73="",0,SUMIFS(F$116:F$132,$C$116:$C$132,$J73)) -> 0 | M73: =IF($J73="",0,SUMIFS(G$116:G$132,$C$116:$C$132,$J73)) -> 0 | N73: =IF($J73="",0,SUMIFS(H$116:H$132,$C$116:$C$132,$J73)) -> 0 | O73: =IF($J73="",0,SUMIFS(I$116:I$132,$C$116:$C$132,$J73)) -> 0 | R73: =TEXT(K73/K$75,"0%") -> 0% | S73: =TEXT(L73/L$75,"0%") -> 0% | T73: =TEXT(M73/M$75,"0%") -> 0% | U73: =TEXT(N73/N$75,"0%") -> 0% | V73: =TEXT(O73/O$75,"0%") -> 0%
B74: Software ARR | C74: ='Rev. Build'!J54*4 -> 80000 | D74: ='Rev. Build'!O54*4 -> 100000 | E74: ='Rev. Build'!T54*4 -> 135000 | F74: ='Rev. Build'!Y54*4 -> 168750 | G74: ='Rev. Build'!AD54*4 -> 194062.5 | H74: =IFERROR((G74/C74)^(1/4)-1,0) -> 0.24799518 | J74: =IFERROR(INDEX(_xlfn.ANCHORARRAY($M$115),8),"") | K74: =IF($J74="",0,SUMIFS(E$116:E$132,$C$116:$C$132,$J74)) -> 0 | L74: =IF($J74="",0,SUMIFS(F$116:F$132,$C$116:$C$132,$J74)) -> 0 | M74: =IF($J74="",0,SUMIFS(G$116:G$132,$C$116:$C$132,$J74)) -> 0 | N74: =IF($J74="",0,SUMIFS(H$116:H$132,$C$116:$C$132,$J74)) -> 0 | O74: =IF($J74="",0,SUMIFS(I$116:I$132,$C$116:$C$132,$J74)) -> 0 | R74: =TEXT(K74/K$75,"0%") -> 0% | S74: =TEXT(L74/L$75,"0%") -> 0% | T74: =TEXT(M74/M$75,"0%") -> 0% | U74: =TEXT(N74/N$75,"0%") -> 0% | V74: =TEXT(O74/O$75,"0%") -> 0%
B75: Software CAGR Trajectory | C75: =C74 -> 80000 | D75: =C75*(1+$H$74) -> 99839.615 | E75: =D75*(1+$H$74) -> 124599.36 | F75: =E75*(1+$H$74) -> 155499.4 | G75: =F75*(1+$H$74) -> 194062.5 | J75: Total | K75: =SUM(K67:K74) -> 80000 | L75: =SUM(L67:L74) -> 100000 | M75: =SUM(M67:M74) -> 135000 | N75: =SUM(N67:N74) -> 168750 | O75: =SUM(O67:O74) -> 194062.5
J77: % Contribution
J78: =$J$67 -> Big MAC | K78: =IFERROR(K67/K$75,0) -> 0.5 | L78: =IFERROR(L67/L$75,0) -> 0.5 | M78: =IFERROR(M67/M$75,0) -> 0.5 | N78: =IFERROR(N67/N$75,0) -> 0.5 | O78: =IFERROR(O67/O$75,0) -> 0.5
B79: 3 Revenue breakdown — by customer | J79: =$J$68 -> MCMC | K79: =IFERROR(K68/K$75,0) -> 0.5 | L79: =IFERROR(L68/L$75,0) -> 0.5 | M79: =IFERROR(M68/M$75,0) -> 0.5 | N79: =IFERROR(N68/N$75,0) -> 0.5 | O79: =IFERROR(O68/O$75,0) -> 0.5
B80: Customer | C80: Year 1 (2026) | D80: Year 2 (2027) | E80: Year 3 (2028) | F80: Year 4 (2029) | G80: Year 5 (2030) | J80: =$J$69 | K80: =IFERROR(K69/K$75,0) -> 0 | L80: =IFERROR(L69/L$75,0) -> 0 | M80: =IFERROR(M69/M$75,0) -> 0 | N80: =IFERROR(N69/N$75,0) -> 0 | O80: =IFERROR(O69/O$75,0) -> 0
B81: =IFERROR(INDEX(_xlfn.ANCHORARRAY($L$115),1),"") -> Hungry AF | C81: =IF($B81="",0,SUMIFS(E$116:E$132,$B$116:$B$132,$B81)) -> 40000 | D81: =IF($B81="",0,SUMIFS(F$116:F$132,$B$116:$B$132,$B81)) -> 50000 | E81: =IF($B81="",0,SUMIFS(G$116:G$132,$B$116:$B$132,$B81)) -> 67500 | F81: =IF($B81="",0,SUMIFS(H$116:H$132,$B$116:$B$132,$B81)) -> 84375 | G81: =IF($B81="",0,SUMIFS(I$116:I$132,$B$116:$B$132,$B81)) -> 97031.25 | J81: =$J$70 | K81: =IFERROR(K70/K$75,0) -> 0 | L81: =IFERROR(L70/L$75,0) -> 0 | M81: =IFERROR(M70/M$75,0) -> 0 | N81: =IFERROR(N70/N$75,0) -> 0 | O81: =IFERROR(O70/O$75,0) -> 0 | R81: =TEXT(C81/C$87,"0%") -> 50% | S81: =TEXT(D81/D$87,"0%") -> 50% | T81: =TEXT(E81/E$87,"0%") -> 50% | U81: =TEXT(F81/F$87,"0%") -> 50% | V81: =TEXT(G81/G$87,"0%") -> 50%
B82: =IFERROR(INDEX(_xlfn.ANCHORARRAY($L$115),2),"") -> BULO | C82: =IF($B82="",0,SUMIFS(E$116:E$132,$B$116:$B$132,$B82)) -> 40000 | D82: =IF($B82="",0,SUMIFS(F$116:F$132,$B$116:$B$132,$B82)) -> 50000 | E82: =IF($B82="",0,SUMIFS(G$116:G$132,$B$116:$B$132,$B82)) -> 67500 | F82: =IF($B82="",0,SUMIFS(H$116:H$132,$B$116:$B$132,$B82)) -> 84375 | G82: =IF($B82="",0,SUMIFS(I$116:I$132,$B$116:$B$132,$B82)) -> 97031.25 | J82: =$J$71 | K82: =IFERROR(K71/K$75,0) -> 0 | L82: =IFERROR(L71/L$75,0) -> 0 | M82: =IFERROR(M71/M$75,0) -> 0 | N82: =IFERROR(N71/N$75,0) -> 0 | O82: =IFERROR(O71/O$75,0) -> 0 | R82: =TEXT(C82/C$87,"0%") -> 50% | S82: =TEXT(D82/D$87,"0%") -> 50% | T82: =TEXT(E82/E$87,"0%") -> 50% | U82: =TEXT(F82/F$87,"0%") -> 50% | V82: =TEXT(G82/G$87,"0%") -> 50%
B83: =IFERROR(INDEX(_xlfn.ANCHORARRAY($L$115),3),"") | C83: =IF($B83="",0,SUMIFS(E$116:E$132,$B$116:$B$132,$B83)) -> 0 | D83: =IF($B83="",0,SUMIFS(F$116:F$132,$B$116:$B$132,$B83)) -> 0 | E83: =IF($B83="",0,SUMIFS(G$116:G$132,$B$116:$B$132,$B83)) -> 0 | F83: =IF($B83="",0,SUMIFS(H$116:H$132,$B$116:$B$132,$B83)) -> 0 | G83: =IF($B83="",0,SUMIFS(I$116:I$132,$B$116:$B$132,$B83)) -> 0 | J83: =$J$72 | K83: =IFERROR(K72/K$75,0) -> 0 | L83: =IFERROR(L72/L$75,0) -> 0 | M83: =IFERROR(M72/M$75,0) -> 0 | N83: =IFERROR(N72/N$75,0) -> 0 | O83: =IFERROR(O72/O$75,0) -> 0 | R83: =TEXT(C83/C$87,"0%") -> 0% | S83: =TEXT(D83/D$87,"0%") -> 0% | T83: =TEXT(E83/E$87,"0%") -> 0% | U83: =TEXT(F83/F$87,"0%") -> 0% | V83: =TEXT(G83/G$87,"0%") -> 0%
B84: =IFERROR(INDEX(_xlfn.ANCHORARRAY($L$115),4),"") | C84: =IF($B84="",0,SUMIFS(E$116:E$132,$B$116:$B$132,$B84)) -> 0 | D84: =IF($B84="",0,SUMIFS(F$116:F$132,$B$116:$B$132,$B84)) -> 0 | E84: =IF($B84="",0,SUMIFS(G$116:G$132,$B$116:$B$132,$B84)) -> 0 | F84: =IF($B84="",0,SUMIFS(H$116:H$132,$B$116:$B$132,$B84)) -> 0 | G84: =IF($B84="",0,SUMIFS(I$116:I$132,$B$116:$B$132,$B84)) -> 0 | J84: =$J$73 | K84: =IFERROR(K73/K$75,0) -> 0 | L84: =IFERROR(L73/L$75,0) -> 0 | M84: =IFERROR(M73/M$75,0) -> 0 | N84: =IFERROR(N73/N$75,0) -> 0 | O84: =IFERROR(O73/O$75,0) -> 0 | R84: =TEXT(C84/C$87,"0%") -> 0% | S84: =TEXT(D84/D$87,"0%") -> 0% | T84: =TEXT(E84/E$87,"0%") -> 0% | U84: =TEXT(F84/F$87,"0%") -> 0% | V84: =TEXT(G84/G$87,"0%") -> 0%
B85: =IFERROR(INDEX(_xlfn.ANCHORARRAY($L$115),5),"") | C85: =IF($B85="",0,SUMIFS(E$116:E$132,$B$116:$B$132,$B85)) -> 0 | D85: =IF($B85="",0,SUMIFS(F$116:F$132,$B$116:$B$132,$B85)) -> 0 | E85: =IF($B85="",0,SUMIFS(G$116:G$132,$B$116:$B$132,$B85)) -> 0 | F85: =IF($B85="",0,SUMIFS(H$116:H$132,$B$116:$B$132,$B85)) -> 0 | G85: =IF($B85="",0,SUMIFS(I$116:I$132,$B$116:$B$132,$B85)) -> 0 | J85: =$J$74 | K85: =IFERROR(K74/K$75,0) -> 0 | L85: =IFERROR(L74/L$75,0) -> 0 | M85: =IFERROR(M74/M$75,0) -> 0 | N85: =IFERROR(N74/N$75,0) -> 0 | O85: =IFERROR(O74/O$75,0) -> 0 | R85: =TEXT(C85/C$87,"0%") -> 0% | S85: =TEXT(D85/D$87,"0%") -> 0% | T85: =TEXT(E85/E$87,"0%") -> 0% | U85: =TEXT(F85/F$87,"0%") -> 0% | V85: =TEXT(G85/G$87,"0%") -> 0%
B86: =IFERROR(INDEX(_xlfn.ANCHORARRAY($L$115),6),"") | C86: =IF($B86="",0,SUMIFS(E$116:E$132,$B$116:$B$132,$B86)) -> 0 | D86: =IF($B86="",0,SUMIFS(F$116:F$132,$B$116:$B$132,$B86)) -> 0 | E86: =IF($B86="",0,SUMIFS(G$116:G$132,$B$116:$B$132,$B86)) -> 0 | F86: =IF($B86="",0,SUMIFS(H$116:H$132,$B$116:$B$132,$B86)) -> 0 | G86: =IF($B86="",0,SUMIFS(I$116:I$132,$B$116:$B$132,$B86)) -> 0 | R86: =TEXT(C86/C$87,"0%") -> 0% | S86: =TEXT(D86/D$87,"0%") -> 0% | T86: =TEXT(E86/E$87,"0%") -> 0% | U86: =TEXT(F86/F$87,"0%") -> 0% | V86: =TEXT(G86/G$87,"0%") -> 0%
B87: Total | C87: =SUM(C81:C86) -> 80000 | D87: =SUM(D81:D86) -> 100000 | E87: =SUM(E81:E86) -> 135000 | F87: =SUM(F81:F86) -> 168750 | G87: =SUM(G81:G86) -> 194062.5
J89: 5 Revenue breakdown — by territory
J90: Territory | K90: Year 1 (2026) | L90: Year 2 (2027) | M90: Year 3 (2028) | N90: Year 4 (2029) | O90: Year 5 (2030)
J91: =IFERROR(INDEX(_xlfn.ANCHORARRAY($N$115),1),"") -> US | K91: =IF($J91="",0,SUMIFS(E$116:E$132,$D$116:$D$132,$J91)) -> 40000 | L91: =IF($J91="",0,SUMIFS(F$116:F$132,$D$116:$D$132,$J91)) -> 50000 | M91: =IF($J91="",0,SUMIFS(G$116:G$132,$D$116:$D$132,$J91)) -> 67500 | N91: =IF($J91="",0,SUMIFS(H$116:H$132,$D$116:$D$132,$J91)) -> 84375 | O91: =IF($J91="",0,SUMIFS(I$116:I$132,$D$116:$D$132,$J91)) -> 97031.25 | R91: =TEXT(K91/K$94,"0%") -> 50% | S91: =TEXT(L91/L$94,"0%") -> 50% | T91: =TEXT(M91/M$94,"0%") -> 50% | U91: =TEXT(N91/N$94,"0%") -> 50% | V91: =TEXT(O91/O$94,"0%") -> 50%
J92: =IFERROR(INDEX(_xlfn.ANCHORARRAY($N$115),2),"") -> EU | K92: =IF($J92="",0,SUMIFS(E$116:E$132,$D$116:$D$132,$J92)) -> 40000 | L92: =IF($J92="",0,SUMIFS(F$116:F$132,$D$116:$D$132,$J92)) -> 50000 | M92: =IF($J92="",0,SUMIFS(G$116:G$132,$D$116:$D$132,$J92)) -> 67500 | N92: =IF($J92="",0,SUMIFS(H$116:H$132,$D$116:$D$132,$J92)) -> 84375 | O92: =IF($J92="",0,SUMIFS(I$116:I$132,$D$116:$D$132,$J92)) -> 97031.25 | R92: =TEXT(K92/K$94,"0%") -> 50% | S92: =TEXT(L92/L$94,"0%") -> 50% | T92: =TEXT(M92/M$94,"0%") -> 50% | U92: =TEXT(N92/N$94,"0%") -> 50% | V92: =TEXT(O92/O$94,"0%") -> 50%
J93: =IFERROR(INDEX(_xlfn.ANCHORARRAY($N$115),3),"") | K93: =IF($J93="",0,SUMIFS(E$116:E$132,$D$116:$D$132,$J93)) -> 0 | L93: =IF($J93="",0,SUMIFS(F$116:F$132,$D$116:$D$132,$J93)) -> 0 | M93: =IF($J93="",0,SUMIFS(G$116:G$132,$D$116:$D$132,$J93)) -> 0 | N93: =IF($J93="",0,SUMIFS(H$116:H$132,$D$116:$D$132,$J93)) -> 0 | O93: =IF($J93="",0,SUMIFS(I$116:I$132,$D$116:$D$132,$J93)) -> 0 | R93: =TEXT(K93/K$94,"0%") -> 0% | S93: =TEXT(L93/L$94,"0%") -> 0% | T93: =TEXT(M93/M$94,"0%") -> 0% | U93: =TEXT(N93/N$94,"0%") -> 0% | V93: =TEXT(O93/O$94,"0%") -> 0%
J94: Total | K94: =SUM(K91:K93) -> 80000 | L94: =SUM(L91:L93) -> 100000 | M94: =SUM(M91:M93) -> 135000 | N94: =SUM(N91:N93) -> 168750 | O94: =SUM(O91:O93) -> 194062.5
J96: % Contribution
B97: P&L | J97: =$J$91 -> US | K97: =IFERROR(K91/K$94,0) -> 0.5 | L97: =IFERROR(L91/L$94,0) -> 0.5 | M97: =IFERROR(M91/M$94,0) -> 0.5 | N97: =IFERROR(N91/N$94,0) -> 0.5 | O97: =IFERROR(O91/O$94,0) -> 0.5
B98: ='P&L'!C4 -> 2025 | C98: ='P&L'!D4 -> 2026 | D98: ='P&L'!E4 -> 2027 | E98: ='P&L'!F4 -> 2028 | F98: ='P&L'!G4 -> 2029 | G98: ='P&L'!H4 -> 2030 | J98: =$J$92 -> EU | K98: =IFERROR(K92/K$94,0) -> 0.5 | L98: =IFERROR(L92/L$94,0) -> 0.5 | M98: =IFERROR(M92/M$94,0) -> 0.5 | N98: =IFERROR(N92/N$94,0) -> 0.5 | O98: =IFERROR(O92/O$94,0) -> 0.5
A99: ='P&L'!B5 -> Revenues | B99: ='P&L'!C5 -> 10000 | C99: ='P&L'!D5 -> 80000 | D99: ='P&L'!E5 -> 100000 | E99: ='P&L'!F5 -> 135000 | F99: ='P&L'!G5 -> 168750 | G99: ='P&L'!H5 -> 194062.5 | J99: =$J$93 | K99: =IFERROR(K93/K$94,0) -> 0 | L99: =IFERROR(L93/L$94,0) -> 0 | M99: =IFERROR(M93/M$94,0) -> 0 | N99: =IFERROR(N93/N$94,0) -> 0 | O99: =IFERROR(O93/O$94,0) -> 0
A100: ='P&L'!B8 -> COGS | B100: ='P&L'!C8 -> 5000 | C100: ='P&L'!D8 -> 40000 | D100: ='P&L'!E8 -> 50000 | E100: ='P&L'!F8 -> 67500 | F100: ='P&L'!G8 -> 84375 | G100: ='P&L'!H8 -> 97031.25
A101: ='P&L'!B10 -> Gross Profit | B101: ='P&L'!C10 -> 5000 | C101: ='P&L'!D10 -> 40000 | D101: ='P&L'!E10 -> 50000 | E101: ='P&L'!F10 -> 67500 | F101: ='P&L'!G10 -> 84375 | G101: ='P&L'!H10 -> 97031.25
A102: ='P&L'!B11 -> % Margin | B102: ='P&L'!C11 -> 0.5 | C102: ='P&L'!D11 -> 0.5 | D102: ='P&L'!E11 -> 0.5 | E102: ='P&L'!F11 -> 0.5 | F102: ='P&L'!G11 -> 0.5 | G102: ='P&L'!H11 -> 0.5
A103: ='P&L'!B13 -> S&M | B103: ='P&L'!C13 -> 2000 | C103: ='P&L'!D13 -> 400000 | D103: ='P&L'!E13 -> 500000 | E103: ='P&L'!F13 -> 725000 | F103: ='P&L'!G13 -> 957000 | G103: ='P&L'!H13 -> 1167540
A104: ='P&L'!B15 -> G&A | B104: ='P&L'!C15 -> 0 | C104: ='P&L'!D15 -> 500000 | D104: ='P&L'!E15 -> 600000 | E104: ='P&L'!F15 -> 828000 | F104: ='P&L'!G15 -> 1101240 | G104: ='P&L'!H15 -> 1409587.2
A105: ='P&L'!B17 -> R&D | B105: ='P&L'!C17 -> 0 | C105: ='P&L'!D17 -> 300000 | D105: ='P&L'!E17 -> 400000 | E105: ='P&L'!F17 -> 532000 | F105: ='P&L'!G17 -> 680960 | G105: ='P&L'!H17 -> 817152
A106: ='P&L'!B20 -> Total OPEX | B106: ='P&L'!C20 -> 2000 | C106: ='P&L'!D20 -> 1200000 | D106: ='P&L'!E20 -> 1500000 | E106: ='P&L'!F20 -> 2085000 | F106: ='P&L'!G20 -> 2739200 | G106: ='P&L'!H20 -> 3394279.2
A107: ='P&L'!B21 -> OPEX % | B107: ='P&L'!C21 -> -0.2 | C107: ='P&L'!D21 -> -15 | D107: ='P&L'!E21 -> -15 | E107: ='P&L'!F21 -> -15.444444 | F107: ='P&L'!G21 -> -16.232296 | G107: ='P&L'!H21 -> -17.49065
A108: ='P&L'!B23 -> Adj. EBITDA | B108: ='P&L'!C23 -> 3000 | C108: ='P&L'!D23 -> -1160000 | D108: ='P&L'!E23 -> -1450000 | E108: ='P&L'!F23 -> -2017500 | F108: ='P&L'!G23 -> -2654825 | G108: ='P&L'!H23 -> -3297248
A109: ='P&L'!B24 -> % Margin | B109: ='P&L'!C24 -> 0.3 | C109: ='P&L'!D24 -> -14.5 | D109: ='P&L'!E24 -> -14.5 | E109: ='P&L'!F24 -> -14.944444 | F109: ='P&L'!G24 -> -15.732296 | G109: ='P&L'!H24 -> -16.99065
A114: HELPER — line-item detail (do not edit) | L114: Unique Customers (sorted by 5Y rev. desc) | M114: Unique Products (sorted by 5Y rev. desc) | N114: Unique Territories (sorted by 5Y rev. desc)
B115: Customer | C115: Product | D115: Territory | E115: 2026 | F115: 2027 | G115: 2028 | H115: 2029 | I115: 2030 | J115: Total (5Y) | L115: {=IFERROR(_xlfn.SORTBY(_xlfn.UNIQUE(_xlfn._xlws.FILTER($B$116:$B$132,($B$116:$B$132<>0)*($B$116:$B$132<>""))),SUMIFS($J$116:$J$132,$B$116:$B$132,_xlfn.UNIQUE(_xlfn._xlws.FILTER($B$116:$B$132,($B$116:$B$132<>0)*($B$116:$B$132<>"")))),-1),"")} -> Hungry AF | M115: {=IFERROR(_xlfn.SORTBY(_xlfn.UNIQUE(_xlfn._xlws.FILTER($C$116:$C$132,($C$116:$C$132<>0)*($C$116:$C$132<>""))),SUMIFS($J$116:$J$132,$C$116:$C$132,_xlfn.UNIQUE(_xlfn._xlws.FILTER($C$116:$C$132,($C$116:$C$132<>0)*($C$116:$C$132<>"")))),-1),"")} -> Big MAC | N115: {=IFERROR(_xlfn.SORTBY(_xlfn.UNIQUE(_xlfn._xlws.FILTER($D$116:$D$132,($D$116:$D$132<>0)*($D$116:$D$132<>""))),SUMIFS($J$116:$J$132,$D$116:$D$132,_xlfn.UNIQUE(_xlfn._xlws.FILTER($D$116:$D$132,($D$116:$D$132<>0)*($D$116:$D$132<>"")))),-1),"")} -> US
B116: ='Rev. Build'!B34 -> Hungry AF | C116: ='Rev. Build'!E34 -> Big MAC | D116: ='Rev. Build'!D34 -> US | E116: ='Rev. Build'!K34 -> 40000 | F116: ='Rev. Build'!P34 -> 50000 | G116: ='Rev. Build'!U34 -> 67500 | H116: ='Rev. Build'!Z34 -> 84375 | I116: ='Rev. Build'!AE34 -> 97031.25 | J116: =SUM(E116:I116) -> 338906.25 | L116: BULO | M116: MCMC | N116: EU
B117: ='Rev. Build'!B35 -> BULO | C117: ='Rev. Build'!E35 -> MCMC | D117: ='Rev. Build'!D35 -> EU | E117: ='Rev. Build'!K35 -> 40000 | F117: ='Rev. Build'!P35 -> 50000 | G117: ='Rev. Build'!U35 -> 67500 | H117: ='Rev. Build'!Z35 -> 84375 | I117: ='Rev. Build'!AE35 -> 97031.25 | J117: =SUM(E117:I117) -> 338906.25
B118: ='Rev. Build'!B36 -> 0 | C118: ='Rev. Build'!E36 -> 0 | D118: ='Rev. Build'!D36 -> 0 | E118: ='Rev. Build'!K36 -> 0 | F118: ='Rev. Build'!P36 -> 0 | G118: ='Rev. Build'!U36 -> 0 | H118: ='Rev. Build'!Z36 -> 0 | I118: ='Rev. Build'!AE36 -> 0
B119: ='Rev. Build'!B37 -> 0 | C119: ='Rev. Build'!E37 -> 0 | D119: ='Rev. Build'!D37 -> 0 | E119: ='Rev. Build'!K37 -> 0 | F119: ='Rev. Build'!P37 -> 0 | G119: ='Rev. Build'!U37 -> 0 | H119: ='Rev. Build'!Z37 -> 0 | I119: ='Rev. Build'!AE37 -> 0
B120: ='Rev. Build'!B38 -> 0 | C120: ='Rev. Build'!E38 -> 0 | D120: ='Rev. Build'!D38 -> 0 | E120: ='Rev. Build'!K38 -> 0 | F120: ='Rev. Build'!P38 -> 0 | G120: ='Rev. Build'!U38 -> 0 | H120: ='Rev. Build'!Z38 -> 0 | I120: ='Rev. Build'!AE38 -> 0
B121: ='Rev. Build'!B39 -> 0 | C121: ='Rev. Build'!E39 -> 0 | D121: ='Rev. Build'!D39 -> 0 | E121: ='Rev. Build'!K39 -> 0 | F121: ='Rev. Build'!P39 -> 0 | G121: ='Rev. Build'!U39 -> 0 | H121: ='Rev. Build'!Z39 -> 0 | I121: ='Rev. Build'!AE39 -> 0
B122: ='Rev. Build'!B67 -> 0 | C122: ='Rev. Build'!E67 -> 0 | D122: ='Rev. Build'!D67 -> 0 | E122: ='Rev. Build'!K67 -> 0 | F122: ='Rev. Build'!P67 -> 0 | G122: ='Rev. Build'!U67 -> 0 | H122: ='Rev. Build'!Z67 -> 0 | I122: ='Rev. Build'!AE67 -> 0
B123: ='Rev. Build'!B68 -> 0 | C123: ='Rev. Build'!E68 -> 0 | D123: ='Rev. Build'!D68 -> 0 | E123: ='Rev. Build'!K68 -> 0 | F123: ='Rev. Build'!P68 -> 0 | G123: ='Rev. Build'!U68 -> 0 | H123: ='Rev. Build'!Z68 -> 0 | I123: ='Rev. Build'!AE68 -> 0
B124: ='Rev. Build'!B69 -> 0 | C124: ='Rev. Build'!E69 -> 0 | D124: ='Rev. Build'!D69 -> 0 | E124: ='Rev. Build'!K69 -> 0 | F124: ='Rev. Build'!P69 -> 0 | G124: ='Rev. Build'!U69 -> 0 | H124: ='Rev. Build'!Z69 -> 0 | I124: ='Rev. Build'!AE69 -> 0
B125: ='Rev. Build'!B70 -> 0 | C125: ='Rev. Build'!E70 -> 0 | D125: ='Rev. Build'!D70 -> 0 | E125: ='Rev. Build'!K70 -> 0 | F125: ='Rev. Build'!P70 -> 0 | G125: ='Rev. Build'!U70 -> 0 | H125: ='Rev. Build'!Z70 -> 0 | I125: ='Rev. Build'!AE70 -> 0
B126: ='Rev. Build'!B71 -> 0 | C126: ='Rev. Build'!E71 -> 0 | D126: ='Rev. Build'!D71 -> 0 | E126: ='Rev. Build'!K71 -> 0 | F126: ='Rev. Build'!P71 -> 0 | G126: ='Rev. Build'!U71 -> 0 | H126: ='Rev. Build'!Z71 -> 0 | I126: ='Rev. Build'!AE71 -> 0
B127: ='Rev. Build'!B72 -> 0 | C127: ='Rev. Build'!E72 -> 0 | D127: ='Rev. Build'!D72 -> 0 | E127: ='Rev. Build'!K72 -> 0 | F127: ='Rev. Build'!P72 -> 0 | G127: ='Rev. Build'!U72 -> 0 | H127: ='Rev. Build'!Z72 -> 0 | I127: ='Rev. Build'!AE72 -> 0
B128: ='Rev. Build'!B85 -> 0 | C128: ='Rev. Build'!E85 -> 0 | D128: ='Rev. Build'!D85 -> 0 | E128: ='Rev. Build'!K85 -> 0 | F128: ='Rev. Build'!P85 -> 0 | G128: ='Rev. Build'!U85 -> 0 | H128: ='Rev. Build'!Z85 -> 0 | I128: ='Rev. Build'!AE85 -> 0
B129: ='Rev. Build'!B86 -> 0 | C129: ='Rev. Build'!E86 -> 0 | D129: ='Rev. Build'!D86 -> 0 | E129: ='Rev. Build'!K86 -> 0 | F129: ='Rev. Build'!P86 -> 0 | G129: ='Rev. Build'!U86 -> 0 | H129: ='Rev. Build'!Z86 -> 0 | I129: ='Rev. Build'!AE86 -> 0
B130: ='Rev. Build'!B87 -> 0 | C130: ='Rev. Build'!E87 -> 0 | D130: ='Rev. Build'!D87 -> 0 | E130: ='Rev. Build'!K87 -> 0 | F130: ='Rev. Build'!P87 -> 0 | G130: ='Rev. Build'!U87 -> 0 | H130: ='Rev. Build'!Z87 -> 0 | I130: ='Rev. Build'!AE87 -> 0
B131: ='Rev. Build'!B88 -> 0 | C131: ='Rev. Build'!E88 -> 0 | D131: ='Rev. Build'!D88 -> 0 | E131: ='Rev. Build'!K88 -> 0 | F131: ='Rev. Build'!P88 -> 0 | G131: ='Rev. Build'!U88 -> 0 | H131: ='Rev. Build'!Z88 -> 0 | I131: ='Rev. Build'!AE88 -> 0
B132: ='Rev. Build'!B89 -> 0 | C132: ='Rev. Build'!E89 -> 0 | D132: ='Rev. Build'!D89 -> 0 | E132: ='Rev. Build'!K89 -> 0 | F132: ='Rev. Build'!P89 -> 0 | G132: ='Rev. Build'!U89 -> 0 | H132: ='Rev. Build'!Z89 -> 0 | I132: ='Rev. Build'!AE89 -> 0
A134: Gross Margin % by Revenue Type (helper for GM trend chart)
A135: Type | B135: Year 1 (2026) | C135: Year 2 (2027) | D135: Year 3 (2028) | E135: Year 4 (2029) | F135: Year 5 (2030)
A136: Software / SaaS | B136: =(SUMIF('Rev. Build'!$A$34:$A$53,Dashboard!$A136,'Rev. Build'!K$34:K$53)-SUMIF(COGS!$A$31:$A$50,Dashboard!$A136,COGS!K$31:K$50))/'Rev. Build'!K$54 -> 0.25 | C136: =(SUMIF('Rev. Build'!$A$34:$A$53,Dashboard!$A136,'Rev. Build'!P$34:P$53)-SUMIF(COGS!$A$31:$A$50,Dashboard!$A136,COGS!P$31:P$50))/'Rev. Build'!P$54 -> 0.25 | D136: =(SUMIF('Rev. Build'!$A$34:$A$53,Dashboard!$A136,'Rev. Build'!U$34:U$53)-SUMIF(COGS!$A$31:$A$50,Dashboard!$A136,COGS!U$31:U$50))/'Rev. Build'!U$54 -> 0.25 | E136: =(SUMIF('Rev. Build'!$A$34:$A$53,Dashboard!$A136,'Rev. Build'!Z$34:Z$53)-SUMIF(COGS!$A$31:$A$50,Dashboard!$A136,COGS!Z$31:Z$50))/'Rev. Build'!Z$54 -> 0.25 | F136: =(SUMIF('Rev. Build'!$A$34:$A$53,Dashboard!$A136,'Rev. Build'!AE$34:AE$53)-SUMIF(COGS!$A$31:$A$50,Dashboard!$A136,COGS!AE$31:AE$50))/'Rev. Build'!AE$54 -> 0.25
A137: Hardware | B137: =(SUMIF('Rev. Build'!$A$34:$A$53,Dashboard!$A137,'Rev. Build'!K$34:K$53)-SUMIF(COGS!$A$31:$A$50,Dashboard!$A137,COGS!K$31:K$50))/'Rev. Build'!K$54 -> 0.25 | C137: =(SUMIF('Rev. Build'!$A$34:$A$53,Dashboard!$A137,'Rev. Build'!P$34:P$53)-SUMIF(COGS!$A$31:$A$50,Dashboard!$A137,COGS!P$31:P$50))/'Rev. Build'!P$54 -> 0.25 | D137: =(SUMIF('Rev. Build'!$A$34:$A$53,Dashboard!$A137,'Rev. Build'!U$34:U$53)-SUMIF(COGS!$A$31:$A$50,Dashboard!$A137,COGS!U$31:U$50))/'Rev. Build'!U$54 -> 0.25 | E137: =(SUMIF('Rev. Build'!$A$34:$A$53,Dashboard!$A137,'Rev. Build'!Z$34:Z$53)-SUMIF(COGS!$A$31:$A$50,Dashboard!$A137,COGS!Z$31:Z$50))/'Rev. Build'!Z$54 -> 0.25 | F137: =(SUMIF('Rev. Build'!$A$34:$A$53,Dashboard!$A137,'Rev. Build'!AE$34:AE$53)-SUMIF(COGS!$A$31:$A$50,Dashboard!$A137,COGS!AE$31:AE$50))/'Rev. Build'!AE$54 -> 0.25
A138: Usage-Based Revenue | B138: =(SUMIF('Rev. Build'!$A$34:$A$53,Dashboard!$A138,'Rev. Build'!K$34:K$53)-SUMIF(COGS!$A$31:$A$50,Dashboard!$A138,COGS!K$31:K$50))/'Rev. Build'!K$54 -> 0 | C138: =(SUMIF('Rev. Build'!$A$34:$A$53,Dashboard!$A138,'Rev. Build'!P$34:P$53)-SUMIF(COGS!$A$31:$A$50,Dashboard!$A138,COGS!P$31:P$50))/'Rev. Build'!P$54 -> 0 | D138: =(SUMIF('Rev. Build'!$A$34:$A$53,Dashboard!$A138,'Rev. Build'!U$34:U$53)-SUMIF(COGS!$A$31:$A$50,Dashboard!$A138,COGS!U$31:U$50))/'Rev. Build'!U$54 -> 0 | E138: =(SUMIF('Rev. Build'!$A$34:$A$53,Dashboard!$A138,'Rev. Build'!Z$34:Z$53)-SUMIF(COGS!$A$31:$A$50,Dashboard!$A138,COGS!Z$31:Z$50))/'Rev. Build'!Z$54 -> 0 | F138: =(SUMIF('Rev. Build'!$A$34:$A$53,Dashboard!$A138,'Rev. Build'!AE$34:AE$53)-SUMIF(COGS!$A$31:$A$50,Dashboard!$A138,COGS!AE$31:AE$50))/'Rev. Build'!AE$54 -> 0
A139: Maintenance & Support | B139: =(SUMIF('Rev. Build'!$A$34:$A$53,Dashboard!$A139,'Rev. Build'!K$34:K$53)-SUMIF(COGS!$A$31:$A$50,Dashboard!$A139,COGS!K$31:K$50))/'Rev. Build'!K$54 -> 0 | C139: =(SUMIF('Rev. Build'!$A$34:$A$53,Dashboard!$A139,'Rev. Build'!P$34:P$53)-SUMIF(COGS!$A$31:$A$50,Dashboard!$A139,COGS!P$31:P$50))/'Rev. Build'!P$54 -> 0 | D139: =(SUMIF('Rev. Build'!$A$34:$A$53,Dashboard!$A139,'Rev. Build'!U$34:U$53)-SUMIF(COGS!$A$31:$A$50,Dashboard!$A139,COGS!U$31:U$50))/'Rev. Build'!U$54 -> 0 | E139: =(SUMIF('Rev. Build'!$A$34:$A$53,Dashboard!$A139,'Rev. Build'!Z$34:Z$53)-SUMIF(COGS!$A$31:$A$50,Dashboard!$A139,COGS!Z$31:Z$50))/'Rev. Build'!Z$54 -> 0 | F139: =(SUMIF('Rev. Build'!$A$34:$A$53,Dashboard!$A139,'Rev. Build'!AE$34:AE$53)-SUMIF(COGS!$A$31:$A$50,Dashboard!$A139,COGS!AE$31:AE$50))/'Rev. Build'!AE$54 -> 0
A140: Professional Services / NRE | B140: =(SUMIF('Rev. Build'!$A$34:$A$53,Dashboard!$A140,'Rev. Build'!K$34:K$53)-SUMIF(COGS!$A$31:$A$50,Dashboard!$A140,COGS!K$31:K$50))/'Rev. Build'!K$54 -> 0 | C140: =(SUMIF('Rev. Build'!$A$34:$A$53,Dashboard!$A140,'Rev. Build'!P$34:P$53)-SUMIF(COGS!$A$31:$A$50,Dashboard!$A140,COGS!P$31:P$50))/'Rev. Build'!P$54 -> 0 | D140: =(SUMIF('Rev. Build'!$A$34:$A$53,Dashboard!$A140,'Rev. Build'!U$34:U$53)-SUMIF(COGS!$A$31:$A$50,Dashboard!$A140,COGS!U$31:U$50))/'Rev. Build'!U$54 -> 0 | E140: =(SUMIF('Rev. Build'!$A$34:$A$53,Dashboard!$A140,'Rev. Build'!Z$34:Z$53)-SUMIF(COGS!$A$31:$A$50,Dashboard!$A140,COGS!Z$31:Z$50))/'Rev. Build'!Z$54 -> 0 | F140: =(SUMIF('Rev. Build'!$A$34:$A$53,Dashboard!$A140,'Rev. Build'!AE$34:AE$53)-SUMIF(COGS!$A$31:$A$50,Dashboard!$A140,COGS!AE$31:AE$50))/'Rev. Build'!AE$54 -> 0
A141: POC / Pilot Revenue | B141: =(SUMIF('Rev. Build'!$A$34:$A$53,Dashboard!$A141,'Rev. Build'!K$34:K$53)-SUMIF(COGS!$A$31:$A$50,Dashboard!$A141,COGS!K$31:K$50))/'Rev. Build'!K$54 -> 0 | C141: =(SUMIF('Rev. Build'!$A$34:$A$53,Dashboard!$A141,'Rev. Build'!P$34:P$53)-SUMIF(COGS!$A$31:$A$50,Dashboard!$A141,COGS!P$31:P$50))/'Rev. Build'!P$54 -> 0 | D141: =(SUMIF('Rev. Build'!$A$34:$A$53,Dashboard!$A141,'Rev. Build'!U$34:U$53)-SUMIF(COGS!$A$31:$A$50,Dashboard!$A141,COGS!U$31:U$50))/'Rev. Build'!U$54 -> 0 | E141: =(SUMIF('Rev. Build'!$A$34:$A$53,Dashboard!$A141,'Rev. Build'!Z$34:Z$53)-SUMIF(COGS!$A$31:$A$50,Dashboard!$A141,COGS!Z$31:Z$50))/'Rev. Build'!Z$54 -> 0 | F141: =(SUMIF('Rev. Build'!$A$34:$A$53,Dashboard!$A141,'Rev. Build'!AE$34:AE$53)-SUMIF(COGS!$A$31:$A$50,Dashboard!$A141,COGS!AE$31:AE$50))/'Rev. Build'!AE$54 -> 0
A142: Installation & Training | B142: =(SUMIF('Rev. Build'!$A$34:$A$53,Dashboard!$A142,'Rev. Build'!K$34:K$53)-SUMIF(COGS!$A$31:$A$50,Dashboard!$A142,COGS!K$31:K$50))/'Rev. Build'!K$54 -> 0 | C142: =(SUMIF('Rev. Build'!$A$34:$A$53,Dashboard!$A142,'Rev. Build'!P$34:P$53)-SUMIF(COGS!$A$31:$A$50,Dashboard!$A142,COGS!P$31:P$50))/'Rev. Build'!P$54 -> 0 | D142: =(SUMIF('Rev. Build'!$A$34:$A$53,Dashboard!$A142,'Rev. Build'!U$34:U$53)-SUMIF(COGS!$A$31:$A$50,Dashboard!$A142,COGS!U$31:U$50))/'Rev. Build'!U$54 -> 0 | E142: =(SUMIF('Rev. Build'!$A$34:$A$53,Dashboard!$A142,'Rev. Build'!Z$34:Z$53)-SUMIF(COGS!$A$31:$A$50,Dashboard!$A142,COGS!Z$31:Z$50))/'Rev. Build'!Z$54 -> 0 | F142: =(SUMIF('Rev. Build'!$A$34:$A$53,Dashboard!$A142,'Rev. Build'!AE$34:AE$53)-SUMIF(COGS!$A$31:$A$50,Dashboard!$A142,COGS!AE$31:AE$50))/'Rev. Build'!AE$54 -> 0
A143: Licensing / Royalties | B143: =(SUMIF('Rev. Build'!$A$34:$A$53,Dashboard!$A143,'Rev. Build'!K$34:K$53)-SUMIF(COGS!$A$31:$A$50,Dashboard!$A143,COGS!K$31:K$50))/'Rev. Build'!K$54 -> 0 | C143: =(SUMIF('Rev. Build'!$A$34:$A$53,Dashboard!$A143,'Rev. Build'!P$34:P$53)-SUMIF(COGS!$A$31:$A$50,Dashboard!$A143,COGS!P$31:P$50))/'Rev. Build'!P$54 -> 0 | D143: =(SUMIF('Rev. Build'!$A$34:$A$53,Dashboard!$A143,'Rev. Build'!U$34:U$53)-SUMIF(COGS!$A$31:$A$50,Dashboard!$A143,COGS!U$31:U$50))/'Rev. Build'!U$54 -> 0 | E143: =(SUMIF('Rev. Build'!$A$34:$A$53,Dashboard!$A143,'Rev. Build'!Z$34:Z$53)-SUMIF(COGS!$A$31:$A$50,Dashboard!$A143,COGS!Z$31:Z$50))/'Rev. Build'!Z$54 -> 0 | F143: =(SUMIF('Rev. Build'!$A$34:$A$53,Dashboard!$A143,'Rev. Build'!AE$34:AE$53)-SUMIF(COGS!$A$31:$A$50,Dashboard!$A143,COGS!AE$31:AE$50))/'Rev. Build'!AE$54 -> 0
A144: Revenue Share / Success Fees | B144: =(SUMIF('Rev. Build'!$A$34:$A$53,Dashboard!$A144,'Rev. Build'!K$34:K$53)-SUMIF(COGS!$A$31:$A$50,Dashboard!$A144,COGS!K$31:K$50))/'Rev. Build'!K$54 -> 0 | C144: =(SUMIF('Rev. Build'!$A$34:$A$53,Dashboard!$A144,'Rev. Build'!P$34:P$53)-SUMIF(COGS!$A$31:$A$50,Dashboard!$A144,COGS!P$31:P$50))/'Rev. Build'!P$54 -> 0 | D144: =(SUMIF('Rev. Build'!$A$34:$A$53,Dashboard!$A144,'Rev. Build'!U$34:U$53)-SUMIF(COGS!$A$31:$A$50,Dashboard!$A144,COGS!U$31:U$50))/'Rev. Build'!U$54 -> 0 | E144: =(SUMIF('Rev. Build'!$A$34:$A$53,Dashboard!$A144,'Rev. Build'!Z$34:Z$53)-SUMIF(COGS!$A$31:$A$50,Dashboard!$A144,COGS!Z$31:Z$50))/'Rev. Build'!Z$54 -> 0 | F144: =(SUMIF('Rev. Build'!$A$34:$A$53,Dashboard!$A144,'Rev. Build'!AE$34:AE$53)-SUMIF(COGS!$A$31:$A$50,Dashboard!$A144,COGS!AE$31:AE$50))/'Rev. Build'!AE$54 -> 0
A145: Consumables / Parts / Accessories | B145: =(SUMIF('Rev. Build'!$A$34:$A$53,Dashboard!$A145,'Rev. Build'!K$34:K$53)-SUMIF(COGS!$A$31:$A$50,Dashboard!$A145,COGS!K$31:K$50))/'Rev. Build'!K$54 -> 0 | C145: =(SUMIF('Rev. Build'!$A$34:$A$53,Dashboard!$A145,'Rev. Build'!P$34:P$53)-SUMIF(COGS!$A$31:$A$50,Dashboard!$A145,COGS!P$31:P$50))/'Rev. Build'!P$54 -> 0 | D145: =(SUMIF('Rev. Build'!$A$34:$A$53,Dashboard!$A145,'Rev. Build'!U$34:U$53)-SUMIF(COGS!$A$31:$A$50,Dashboard!$A145,COGS!U$31:U$50))/'Rev. Build'!U$54 -> 0 | E145: =(SUMIF('Rev. Build'!$A$34:$A$53,Dashboard!$A145,'Rev. Build'!Z$34:Z$53)-SUMIF(COGS!$A$31:$A$50,Dashboard!$A145,COGS!Z$31:Z$50))/'Rev. Build'!Z$54 -> 0 | F145: =(SUMIF('Rev. Build'!$A$34:$A$53,Dashboard!$A145,'Rev. Build'!AE$34:AE$53)-SUMIF(COGS!$A$31:$A$50,Dashboard!$A145,COGS!AE$31:AE$50))/'Rev. Build'!AE$54 -> 0
A146: Other | B146: =(SUMIF('Rev. Build'!$A$34:$A$53,Dashboard!$A146,'Rev. Build'!K$34:K$53)-SUMIF(COGS!$A$31:$A$50,Dashboard!$A146,COGS!K$31:K$50))/'Rev. Build'!K$54 -> 0 | C146: =(SUMIF('Rev. Build'!$A$34:$A$53,Dashboard!$A146,'Rev. Build'!P$34:P$53)-SUMIF(COGS!$A$31:$A$50,Dashboard!$A146,COGS!P$31:P$50))/'Rev. Build'!P$54 -> 0 | D146: =(SUMIF('Rev. Build'!$A$34:$A$53,Dashboard!$A146,'Rev. Build'!U$34:U$53)-SUMIF(COGS!$A$31:$A$50,Dashboard!$A146,COGS!U$31:U$50))/'Rev. Build'!U$54 -> 0 | E146: =(SUMIF('Rev. Build'!$A$34:$A$53,Dashboard!$A146,'Rev. Build'!Z$34:Z$53)-SUMIF(COGS!$A$31:$A$50,Dashboard!$A146,COGS!Z$31:Z$50))/'Rev. Build'!Z$54 -> 0 | F146: =(SUMIF('Rev. Build'!$A$34:$A$53,Dashboard!$A146,'Rev. Build'!AE$34:AE$53)-SUMIF(COGS!$A$31:$A$50,Dashboard!$A146,COGS!AE$31:AE$50))/'Rev. Build'!AE$54 -> 0
A147: Weighted Avg | B147: =IFERROR('P&L'!D10/'P&L'!D5,0) -> 0.5 | C147: =IFERROR('P&L'!E10/'P&L'!E5,0) -> 0.5 | D147: =IFERROR('P&L'!F10/'P&L'!F5,0) -> 0.5 | E147: =IFERROR('P&L'!G10/'P&L'!G5,0) -> 0.5 | F147: =IFERROR('P&L'!H10/'P&L'!H5,0) -> 0.5

Sheet Qualitative Assumptions
G1: Qualitative Assumptions:
G2: 1
G3: 2
G4: 3
G5: 4
G6: 5
G7: 6
G8: 7
G9: 8
G10: 9
G11: 10
G12: 11
G13: 12
... G20: 19
G22: Assumptions Metrics | I22: Price Increase | J22: Price Increase | K22: Price Increase | L22: Price Increase
I23: 0.02 | J23: 0 | K23: 0 | L23: 0.02
G24: Unit Sale Price: | H24: 2026 | I24: 2027 | J24: 2028 | K24: 2029 | L24: 2030
G25: Customer A- Product A | H25: 160000 | I25: =H25*(1+I$23) -> 163200 | J25: =I25*(1+J$23) -> 163200 | K25: =J25*(1+K$23) -> 163200 | L25: =K25*(1+L$23) -> 166464
G26: Customer A- Product B | H26: 120000 | I26: =H26*(1+I$23) -> 122400 | J26: =I26*(1+J$23) -> 122400 | K26: =J26*(1+K$23) -> 122400 | L26: =K26*(1+L$23) -> 124848
G27: Customer A- Product C | H27: 100000 | I27: =H27*(1+I$23) -> 102000 | J27: =I27*(1+J$23) -> 102000 | K27: =J27*(1+K$23) -> 102000 | L27: =K27*(1+L$23) -> 104040
G28: Customer B- Product A | H28: 130000 | I28: =H28*(1+I$23) -> 132600 | J28: =I28*(1+J$23) -> 132600 | K28: =J28*(1+K$23) -> 132600 | L28: =K28*(1+L$23) -> 135252
G29: Customer B- Product B | H29: 110000 | I29: =H29*(1+I$23) -> 112200 | J29: =I29*(1+J$23) -> 112200 | K29: =J29*(1+K$23) -> 112200 | L29: =K29*(1+L$23) -> 114444
G30: Customer B- Product C | H30: 90000 | I30: =H30*(1+I$23) -> 91800 | J30: =I30*(1+J$23) -> 91800 | K30: =J30*(1+K$23) -> 91800 | L30: =K30*(1+L$23) -> 93636
G31: Customer C- Product A | H31: 120000 | I31: =H31*(1+I$23) -> 122400 | J31: =I31*(1+J$23) -> 122400 | K31: =J31*(1+K$23) -> 122400 | L31: =K31*(1+L$23) -> 124848
G32: Customer C- Product B | H32: 100000 | I32: =H32*(1+I$23) -> 102000 | J32: =I32*(1+J$23) -> 102000 | K32: =J32*(1+K$23) -> 102000 | L32: =K32*(1+L$23) -> 104040
G33: Customer C- Product C | H33: 85000 | I33: =H33*(1+I$23) -> 86700 | J33: =I33*(1+J$23) -> 86700 | K33: =J33*(1+K$23) -> 86700 | L33: =K33*(1+L$23) -> 88434
I35: Cost Increase | J35: Cost Increase | K35: Cost Increase | L35: Cost Increase
I36: 0.02 | J36: 0 | K36: 0 | L36: 0.02
G37: Unit Cost: | H37: 2026 | I37: 2027 | J37: 2028 | K37: 2029 | L37: 2030
G38: Product A | H38: 87000 | I38: =H38*(1+I$36) -> 88740 | J38: =I38*(1+J$36) -> 88740 | K38: =J38*(1+K$36) -> 88740 | L38: =K38*(1+L$36) -> 90514.8
G39: Product B | H39: 67000 | I39: =H39*(1+I$36) -> 68340 | J39: =I39*(1+J$36) -> 68340 | K39: =J39*(1+K$36) -> 68340 | L39: =K39*(1+L$36) -> 69706.8
G40: Product C | H40: 67000 | I40: =H40*(1+I$36) -> 68340 | J40: =I40*(1+J$36) -> 68340 | K40: =J40*(1+K$36) -> 68340 | L40: =K40*(1+L$36) -> 69706.8

Sheet P&L
C4: 2025 | D4: 2026 | E4: 2027 | F4: 2028 | G4: 2029 | H4: 2030 | I4: CAGR
B5: Revenues | C5: 10000 | D5: ='Rev. Build'!K54 -> 80000 | E5: ='Rev. Build'!P54 -> 100000 | F5: ='Rev. Build'!U54 -> 135000 | G5: ='Rev. Build'!Z54 -> 168750 | H5: ='Rev. Build'!AE54 -> 194062.5 | I5: =(H5/C5)^(1/5)-1 -> 0.8096239
B6: % Growth | D6: =D5/C5-1 -> 7 | E6: =E5/D5-1 -> 0.25 | F6: =F5/E5-1 -> 0.35 | G6: =G5/F5-1 -> 0.25 | H6: =H5/G5-1 -> 0.15
B8: COGS | C8: 5000 | D8: =COGS!K51 -> 40000 | E8: =COGS!P51 -> 50000 | F8: =COGS!U51 -> 67500 | G8: =COGS!Z51 -> 84375 | H8: =COGS!AE51 -> 97031.25
B10: Gross Profit | C10: =C5-C8 -> 5000 | D10: =D5-D8 -> 40000 | E10: =E5-E8 -> 50000 | F10: =F5-F8 -> 67500 | G10: =G5-G8 -> 84375 | H10: =H5-H8 -> 97031.25
B11: % Margin | C11: =C10/C$5 -> 0.5 | D11: =D10/D$5 -> 0.5 | E11: =E10/E$5 -> 0.5 | F11: =F10/F$5 -> 0.5 | G11: =G10/G$5 -> 0.5 | H11: =H10/H$5 -> 0.5
B13: S&M | C13: 2000 | D13: =OPEX!K33 -> 400000 | E13: =OPEX!P33 -> 500000 | F13: =OPEX!U33 -> 725000 | G13: =OPEX!Z33 -> 957000 | H13: =OPEX!AE33 -> 1167540
B14: % Margin | C14: =-C13/C$5 -> -0.2 | D14: =-D13/D$5 -> -5 | E14: =-E13/E$5 -> -5 | F14: =-F13/F$5 -> -5.3703704 | G14: =-G13/G$5 -> -5.6711111 | H14: =-H13/H$5 -> -6.0163092
B15: G&A | D15: =OPEX!K48 -> 500000 | E15: =OPEX!P48 -> 600000 | F15: =OPEX!U48 -> 828000 | G15: =OPEX!Z48 -> 1101240 | H15: =OPEX!AE48 -> 1409587.2
B16: % Margin | C16: =-C15/C$5 -> 0 | D16: =-D15/D$5 -> -6.25 | E16: =-E15/E$5 -> -6 | F16: =-F15/F$5 -> -6.1333333 | G16: =-G15/G$5 -> -6.5258667 | H16: =-H15/H$5 -> -7.2635733
B17: R&D | D17: =OPEX!K18 -> 300000 | E17: =OPEX!P18 -> 400000 | F17: =OPEX!U18 -> 532000 | G17: =OPEX!Z18 -> 680960 | H17: =OPEX!AE18 -> 817152
B18: % Margin | C18: =-C17/C$5 -> 0 | D18: =-D17/D$5 -> -3.75 | E18: =-E17/E$5 -> -4 | F18: =-F17/F$5 -> -3.9407407 | G18: =-G17/G$5 -> -4.0353185 | H18: =-H17/H$5 -> -4.2107671
B20: Total OPEX | C20: =C17+C15+C13 -> 2000 | D20: =D17+D15+D13 -> 1200000 | E20: =E17+E15+E13 -> 1500000 | F20: =F17+F15+F13 -> 2085000 | G20: =G17+G15+G13 -> 2739200 | H20: =H17+H15+H13 -> 3394279.2
B21: OPEX % | C21: =-(C13+C15+C17)/C$5 -> -0.2 | D21: =-(D13+D15+D17)/D$5 -> -15 | E21: =-(E13+E15+E17)/E$5 -> -15 | F21: =-(F13+F15+F17)/F$5 -> -15.444444 | G21: =-(G13+G15+G17)/G$5 -> -16.232296 | H21: =-(H13+H15+H17)/H$5 -> -17.49065
B23: Adj. EBITDA | C23: =C10-C20 -> 3000 | D23: =D10-D20 -> -1160000 | E23: =E10-E20 -> -1450000 | F23: =F10-F20 -> -2017500 | G23: =G10-G20 -> -2654825 | H23: =H10-H20 -> -3297248
B24: % Margin | C24: =C23/C5 -> 0.3 | D24: =D23/D5 -> -14.5 | E24: =E23/E5 -> -14.5 | F24: =F23/F5 -> -14.944444 | G24: =G23/G5 -> -15.732296 | H24: =H23/H5 -> -16.99065
B26: WC rate from rev. | C26: -0.1 | D26: -0.1 | E26: -0.1 | F26: -0.1 | G26: -0.1 | H26: -0.1
B27: WC | C27: =C26*C5 -> -1000
B28: Capex
B29: Financing, net
B30: Tax
B31: Free Cash Flow | C31: =C23+SUM(C27:C30) -> 2000 | D31: =D23+SUM(D27:D30) -> -1160000 | E31: =E23+SUM(E27:E30) -> -1450000 | F31: =F23+SUM(F27:F30) -> -2017500 | G31: =G23+SUM(G27:G30) -> -2654825 | H31: =H23+SUM(H27:H30) -> -3297248

Sheet Rev. Build
A4: ='Customer''s Questionnaire'!H8 -> Company's sector | B4: ='Customer''s Questionnaire'!I8 -> Food-Tech / Ag-Tech
A5: ='Customer''s Questionnaire'!H9 -> Upcoming Round | B5: ='Customer''s Questionnaire'!I9 -> Round C | G5: =B5 -> Round C | L5: =_xlfn.XLOOKUP($B$4&L$6,Benchmark_Table!$F:$F,Benchmark_Table!$B:$B,G$5) -> Series C | Q5: =_xlfn.XLOOKUP($B$4&Q$6,Benchmark_Table!$F:$F,Benchmark_Table!$B:$B,L$5) -> Series C | V5: =_xlfn.XLOOKUP($B$4&V$6,Benchmark_Table!$F:$F,Benchmark_Table!$B:$B,Q$5) -> Series D/E | AA5: =_xlfn.XLOOKUP($B$4&AA$6,Benchmark_Table!$F:$F,Benchmark_Table!$B:$B,V$5) -> Pre-IPO | AF5: =_xlfn.XLOOKUP($B$4&AF$6,Benchmark_Table!$F:$F,Benchmark_Table!$B:$B,AA$5) -> Pre-IPO | AK5: =_xlfn.XLOOKUP($B$4&AK$6,Benchmark_Table!$F:$F,Benchmark_Table!$B:$B,AF$5) -> Pre-IPO | AP5: =_xlfn.XLOOKUP($B$4&AP$6,Benchmark_Table!$F:$F,Benchmark_Table!$B:$B,AK$5) -> Pre-IPO | AU5: =_xlfn.XLOOKUP($B$4&AU$6,Benchmark_Table!$F:$F,Benchmark_Table!$B:$B,AP$5) -> Pre-IPO | AZ5: =_xlfn.XLOOKUP($B$4&AZ$6,Benchmark_Table!$F:$F,Benchmark_Table!$B:$B,AU$5) -> Pre-IPO | BE5: =_xlfn.XLOOKUP($B$4&BE$6,Benchmark_Table!$F:$F,Benchmark_Table!$B:$B,AZ$5) -> Pre-IPO | BJ5: =_xlfn.XLOOKUP($B$4&BJ$6,Benchmark_Table!$F:$F,Benchmark_Table!$B:$B,BE$5) -> Pre-IPO
A6: ='Customer''s Questionnaire'!H11 -> Avg_Years_Since_Founding | B6: ='Customer''s Questionnaire'!I11 -> 7 | G6: =B6 -> 7 | L6: =G6+1 -> 8 | Q6: =L6+1 -> 9 | V6: =Q6+1 -> 10 | AA6: =V6+1 -> 11 | AF6: =AA6+1 -> 12 | AK6: =AF6+1 -> 13 | AP6: =AK6+1 -> 14 | AU6: =AP6+1 -> 15 | AZ6: =AU6+1 -> 16 | BE6: =AZ6+1 -> 17 | BJ6: =BE6+1 -> 18
A7: Growth Benchmark | B7: =IF(OR('Customer''s Questionnaire'!J10="Too Low",'Customer''s Questionnaire'!J10="Low"),Benchmark_Table!AY1,IF(OR('Customer''s Questionnaire'!J10="Too High",'Customer''s Questionnaire'!J10="High"),Benchmark_Table!BA1,Benchmark_Table!AZ1)) -> Revenue_Growth_High | G7: =_xlfn.IFNA(INDEX(Benchmark_Table!$H$2:$BL$136,MATCH('Rev. Build'!$B$4&'Rev. Build'!G$5&G$6,Benchmark_Table!$G$2:$G$136,0),MATCH('Rev. Build'!$B$7,Benchmark_Table!$H$1:$BL$1,0)),0%) -> 0 | L7: =_xlfn.IFNA(INDEX(Benchmark_Table!$H$2:$BL$136,MATCH('Rev. Build'!$B$4&'Rev. Build'!L$5&L$6,Benchmark_Table!$G$2:$G$136,0),MATCH('Rev. Build'!$B$7,Benchmark_Table!$H$1:$BL$1,0)),G$7) -> 0.35 | Q7: =_xlfn.IFNA(INDEX(Benchmark_Table!$H$2:$BL$136,MATCH('Rev. Build'!$B$4&'Rev. Build'!Q$5&Q$6,Benchmark_Table!$G$2:$G$136,0),MATCH('Rev. Build'!$B$7,Benchmark_Table!$H$1:$BL$1,0)),L$7) -> 0.35 | V7: =_xlfn.IFNA(INDEX(Benchmark_Table!$H$2:$BL$136,MATCH('Rev. Build'!$B$4&'Rev. Build'!V$5&V$6,Benchmark_Table!$G$2:$G$136,0),MATCH('Rev. Build'!$B$7,Benchmark_Table!$H$1:$BL$1,0)),Q$7) -> 0.25 | AA7: =_xlfn.IFNA(INDEX(Benchmark_Table!$H$2:$BL$136,MATCH('Rev. Build'!$B$4&'Rev. Build'!AA$5&AA$6,Benchmark_Table!$G$2:$G$136,0),MATCH('Rev. Build'!$B$7,Benchmark_Table!$H$1:$BL$1,0)),V$7) -> 0.15 | AF7: =_xlfn.IFNA(INDEX(Benchmark_Table!$H$2:$BL$136,MATCH('Rev. Build'!$B$4&'Rev. Build'!AF$5&AF$6,Benchmark_Table!$G$2:$G$136,0),MATCH('Rev. Build'!$B$7,Benchmark_Table!$H$1:$BL$1,0)),AA$7) -> 0.15 | AK7: =_xlfn.IFNA(INDEX(Benchmark_Table!$H$2:$BL$136,MATCH('Rev. Build'!$B$4&'Rev. Build'!AK$5&AK$6,Benchmark_Table!$G$2:$G$136,0),MATCH('Rev. Build'!$B$7,Benchmark_Table!$H$1:$BL$1,0)),AF$7) -> 0.15 | AP7: =_xlfn.IFNA(INDEX(Benchmark_Table!$H$2:$BL$136,MATCH('Rev. Build'!$B$4&'Rev. Build'!AP$5&AP$6,Benchmark_Table!$G$2:$G$136,0),MATCH('Rev. Build'!$B$7,Benchmark_Table!$H$1:$BL$1,0)),AK$7) -> 0.15 | AU7: =_xlfn.IFNA(INDEX(Benchmark_Table!$H$2:$BL$136,MATCH('Rev. Build'!$B$4&'Rev. Build'!AU$5&AU$6,Benchmark_Table!$G$2:$G$136,0),MATCH('Rev. Build'!$B$7,Benchmark_Table!$H$1:$BL$1,0)),AP$7) -> 0.15 | AZ7: =_xlfn.IFNA(INDEX(Benchmark_Table!$H$2:$BL$136,MATCH('Rev. Build'!$B$4&'Rev. Build'!AZ$5&AZ$6,Benchmark_Table!$G$2:$G$136,0),MATCH('Rev. Build'!$B$7,Benchmark_Table!$H$1:$BL$1,0)),AU$7) -> 0.15 | BE7: =_xlfn.IFNA(INDEX(Benchmark_Table!$H$2:$BL$136,MATCH('Rev. Build'!$B$4&'Rev. Build'!BE$5&BE$6,Benchmark_Table!$G$2:$G$136,0),MATCH('Rev. Build'!$B$7,Benchmark_Table!$H$1:$BL$1,0)),AZ$7) -> 0.15 | BJ7: =_xlfn.IFNA(INDEX(Benchmark_Table!$H$2:$BL$136,MATCH('Rev. Build'!$B$4&'Rev. Build'!BJ$5&BJ$6,Benchmark_Table!$G$2:$G$136,0),MATCH('Rev. Build'!$B$7,Benchmark_Table!$H$1:$BL$1,0)),BE$7) -> 0.15
A8: Revenue Benchmark | B8: =IF(OR('Customer''s Questionnaire'!J10="Too Low",'Customer''s Questionnaire'!J10="Low"),Benchmark_Table!AI1,IF(OR('Customer''s Questionnaire'!J10="Too High",'Customer''s Questionnaire'!J10="High"),Benchmark_Table!AK1,Benchmark_Table!AJ1)) -> Revenue_High_$ | G8: =_xlfn.IFNA(INDEX(Benchmark_Table!$H$2:$BL$136,MATCH('Rev. Build'!$B$4&'Rev. Build'!G$5&G$6,Benchmark_Table!$G$2:$G$136,0),MATCH($B$8,Benchmark_Table!$H$1:$BL$1,0)),0) -> 0 | L8: =_xlfn.IFNA(INDEX(Benchmark_Table!$H$2:$BL$136,MATCH('Rev. Build'!$B$4&'Rev. Build'!L$5&L$6,Benchmark_Table!$G$2:$G$136,0),MATCH($B$8,Benchmark_Table!$H$1:$BL$1,0)),0) -> 80000000 | Q8: =_xlfn.IFNA(INDEX(Benchmark_Table!$H$2:$BL$136,MATCH('Rev. Build'!$B$4&'Rev. Build'!Q$5&Q$6,Benchmark_Table!$G$2:$G$136,0),MATCH($B$8,Benchmark_Table!$H$1:$BL$1,0)),0) -> 0 | V8: =_xlfn.IFNA(INDEX(Benchmark_Table!$H$2:$BL$136,MATCH('Rev. Build'!$B$4&'Rev. Build'!V$5&V$6,Benchmark_Table!$G$2:$G$136,0),MATCH($B$8,Benchmark_Table!$H$1:$BL$1,0)),0) -> 240000000 | AA8: =_xlfn.IFNA(INDEX(Benchmark_Table!$H$2:$BL$136,MATCH('Rev. Build'!$B$4&'Rev. Build'!AA$5&AA$6,Benchmark_Table!$G$2:$G$136,0),MATCH($B$8,Benchmark_Table!$H$1:$BL$1,0)),0) -> 640000000 | AF8: =_xlfn.IFNA(INDEX(Benchmark_Table!$H$2:$BL$136,MATCH('Rev. Build'!$B$4&'Rev. Build'!AF$5&AF$6,Benchmark_Table!$G$2:$G$136,0),MATCH($B$8,Benchmark_Table!$H$1:$BL$1,0)),0) -> 0 | AK8: =_xlfn.IFNA(INDEX(Benchmark_Table!$H$2:$BL$136,MATCH('Rev. Build'!$B$4&'Rev. Build'!AK$5&AK$6,Benchmark_Table!$G$2:$G$136,0),MATCH($B$8,Benchmark_Table!$H$1:$BL$1,0)),0) -> 0 | AP8: =_xlfn.IFNA(INDEX(Benchmark_Table!$H$2:$BL$136,MATCH('Rev. Build'!$B$4&'Rev. Build'!AP$5&AP$6,Benchmark_Table!$G$2:$G$136,0),MATCH($B$8,Benchmark_Table!$H$1:$BL$1,0)),0) -> 0 | AU8: =_xlfn.IFNA(INDEX(Benchmark_Table!$H$2:$BL$136,MATCH('Rev. Build'!$B$4&'Rev. Build'!AU$5&AU$6,Benchmark_Table!$G$2:$G$136,0),MATCH($B$8,Benchmark_Table!$H$1:$BL$1,0)),0) -> 0 | AZ8: =_xlfn.IFNA(INDEX(Benchmark_Table!$H$2:$BL$136,MATCH('Rev. Build'!$B$4&'Rev. Build'!AZ$5&AZ$6,Benchmark_Table!$G$2:$G$136,0),MATCH($B$8,Benchmark_Table!$H$1:$BL$1,0)),0) -> 0 | BE8: =_xlfn.IFNA(INDEX(Benchmark_Table!$H$2:$BL$136,MATCH('Rev. Build'!$B$4&'Rev. Build'!BE$5&BE$6,Benchmark_Table!$G$2:$G$136,0),MATCH($B$8,Benchmark_Table!$H$1:$BL$1,0)),0) -> 0 | BJ8: =_xlfn.IFNA(INDEX(Benchmark_Table!$H$2:$BL$136,MATCH('Rev. Build'!$B$4&'Rev. Build'!BJ$5&BJ$6,Benchmark_Table!$G$2:$G$136,0),MATCH($B$8,Benchmark_Table!$H$1:$BL$1,0)),0) -> 0
G9: Q. | H9: Q. | I9: Q. | J9: Q. | K9: Q. | L9: Q. | M9: Q. | N9: Q. | O9: Q. | P9: Q. | Q9: Q. | R9: Q. | S9: Q. | T9: Q. | U9: Q. | V9: Q. | W9: Q. | X9: Q. | Y9: Q. | Z9: Q. | AA9: Q. | AB9: Q. | AC9: Q. | AD9: Q. | AE9: Q. | AF9: Q. | AG9: Q. | AH9: Q. | AI9: Q. | AJ9: Q. | AK9: Q. | AL9: Q. | AM9: Q. | AN9: Q. | AO9: Q. | AP9: Q. | AQ9: Q. | AR9: Q. | AS9: Q. | AT9: Q. | AU9: Q. | AV9: Q. | AW9: Q. | AX9: Q. | AY9: Q. | AZ9: Q. | BA9: Q. | BB9: Q. | BC9: Q. | BD9: Q. | BE9: Q. | BF9: Q. | BG9: Q. | BH9: Q. | BI9: Q. | BJ9: Q. | BK9: Q. | BL9: Q. | BM9: Q. | BN9: Q.
A10: Revenue Type | B10: Customer Name | C10: Type | D10: Territory | E10: Product Name | F10: Notes | G10: ="Q1-"&'Customer''s Questionnaire'!$I$12 -> Q1-2026 | H10: ="Q2-"&'Customer''s Questionnaire'!$I$12 -> Q2-2026 | I10: ="Q3-"&'Customer''s Questionnaire'!$I$12 -> Q3-2026 | J10: ="Q4-"&'Customer''s Questionnaire'!$I$12 -> Q4-2026 | K10: ='Customer''s Questionnaire'!$I$12 -> 2026 | L10: ="Q1-"&K$10+1 -> Q1-2027 | M10: ="Q2-"&K$10+1 -> Q2-2027 | N10: ="Q3-"&K$10+1 -> Q3-2027 | O10: ="Q4-"&K$10+1 -> Q4-2027 | P10: =K10+1 -> 2027 | Q10: ="Q1-"&P$10+1 -> Q1-2028 | R10: ="Q2-"&P$10+1 -> Q2-2028 | S10: ="Q3-"&P$10+1 -> Q3-2028 | T10: ="Q4-"&P$10+1 -> Q4-2028 | U10: =P10+1 -> 2028 | V10: ="Q1-"&U$10+1 -> Q1-2029 | W10: ="Q2-"&U$10+1 -> Q2-2029 | X10: ="Q3-"&U$10+1 -> Q3-2029 | Y10: ="Q4-"&U$10+1 -> Q4-2029 | Z10: =U10+1 -> 2029 | AA10: ="Q1-"&Z$10+1 -> Q1-2030 | AB10: ="Q2-"&Z$10+1 -> Q2-2030 | AC10: ="Q3-"&Z$10+1 -> Q3-2030 | AD10: ="Q4-"&Z$10+1 -> Q4-2030 | AE10: =Z10+1 -> 2030 | AF10: ="Q1-"&AE$10+1 -> Q1-2031 | AG10: ="Q2-"&AE$10+1 -> Q2-2031 | AH10: ="Q3-"&AE$10+1 -> Q3-2031 | AI10: ="Q4-"&AE$10+1 -> Q4-2031 | AJ10: =AE10+1 -> 2031 | AK10: ="Q1-"&AJ$10+1 -> Q1-2032 | AL10: ="Q2-"&AJ$10+1 -> Q2-2032 | AM10: ="Q3-"&AJ$10+1 -> Q3-2032 | AN10: ="Q4-"&AJ$10+1 -> Q4-2032 | AO10: =AJ10+1 -> 2032 | AP10: ="Q1-"&AO$10+1 -> Q1-2033 | AQ10: ="Q2-"&AO$10+1 -> Q2-2033 | AR10: ="Q3-"&AO$10+1 -> Q3-2033 | AS10: ="Q4-"&AO$10+1 -> Q4-2033 | AT10: =AO10+1 -> 2033 | AU10: ="Q1-"&AT$10+1 -> Q1-2034 | AV10: ="Q2-"&AT$10+1 -> Q2-2034 | AW10: ="Q3-"&AT$10+1 -> Q3-2034 | AX10: ="Q4-"&AT$10+1 -> Q4-2034 | AY10: =AT10+1 -> 2034 | AZ10: ="Q1-"&AY$10+1 -> Q1-2035 | BA10: ="Q2-"&AY$10+1 -> Q2-2035 | BB10: ="Q3-"&AY$10+1 -> Q3-2035 | BC10: ="Q4-"&AY$10+1 -> Q4-2035 | BD10: =AY10+1 -> 2035 | BE10: ="Q1-"&BD$10+1 -> Q1-2036 | BF10: ="Q2-"&BD$10+1 -> Q2-2036 | BG10: ="Q3-"&BD$10+1 -> Q3-2036 | BH10: ="Q4-"&BD$10+1 -> Q4-2036 | BI10: =BD10+1 -> 2036 | BJ10: ="Q1-"&BI$10+1 -> Q1-2037 | BK10: ="Q2-"&BI$10+1 -> Q2-2037 | BL10: ="Q3-"&BI$10+1 -> Q3-2037 | BM10: ="Q4-"&BI$10+1 -> Q4-2037 | BN10: =BI10+1 -> 2037
A11: ='Customer''s Questionnaire'!H44 -> Hardware | B11: ='Customer''s Questionnaire'!I44 -> Hungry AF | C11: ='Customer''s Questionnaire'!J44 -> B2C | D11: ='Customer''s Questionnaire'!K44 -> US | E11: ='Customer''s Questionnaire'!L44 -> Big MAC | G11: ='Customer''s Questionnaire'!O44 -> 10 | H11: ='Customer''s Questionnaire'!P44 -> 10 | I11: ='Customer''s Questionnaire'!Q44 -> 10 | J11: ='Customer''s Questionnaire'!R44 -> 10 | K11: =SUM(G11:J11) -> 40 | L11: =IFERROR('Customer''s Questionnaire'!$S44/4,"Add if needed") -> 12.5 | M11: =IFERROR('Customer''s Questionnaire'!$S44/4,"Add if needed") -> 12.5 | N11: =IFERROR('Customer''s Questionnaire'!$S44/4,"Add if needed") -> 12.5 | O11: =IFERROR('Customer''s Questionnaire'!$S44/4,"Add if needed") -> 12.5 | P11: =SUM(L11:O11) -> 50 | Q11: =IFERROR($P11/4*(1+$Q$7),0) -> 16.875 | R11: =IFERROR($P11/4*(1+$Q$7),0) -> 16.875 | S11: =IFERROR($P11/4*(1+$Q$7),0) -> 16.875 | T11: =IFERROR($P11/4*(1+$Q$7),0) -> 16.875 | U11: =SUM(Q11:T11) -> 67.5 | V11: =IFERROR($U11/4*(1+$V$7),0) -> 21.09375 | W11: =IFERROR($U11/4*(1+$V$7),0) -> 21.09375 | X11: =IFERROR($U11/4*(1+$V$7),0) -> 21.09375 | Y11: =IFERROR($U11/4*(1+$V$7),0) -> 21.09375 | Z11: =SUM(V11:Y11) -> 84.375 | AA11: =IFERROR($Z11/4*(1+$AA$7),0) -> 24.257812 | AB11: =IFERROR($Z11/4*(1+$AA$7),0) -> 24.257812 | AC11: =IFERROR($Z11/4*(1+$AA$7),0) -> 24.257812 | AD11: =IFERROR($Z11/4*(1+$AA$7),0) -> 24.257812 | AE11: =SUM(AA11:AD11) -> 97.03125 | AF11: =IFERROR($AE11/4*(1+$AF$7),0) -> 27.896484 | AG11: =IFERROR($AE11/4*(1+$AF$7),0) -> 27.896484 | AH11: =IFERROR($AE11/4*(1+$AF$7),0) -> 27.896484 | AI11: =IFERROR($AE11/4*(1+$AF$7),0) -> 27.896484 | AJ11: =SUM(AF11:AI11) -> 111.58594 | AK11: =IFERROR($AJ11/4*(1+$AK$7),0) -> 32.080957 | AL11: =IFERROR($AJ11/4*(1+$AK$7),0) -> 32.080957 | AM11: =IFERROR($AJ11/4*(1+$AK$7),0) -> 32.080957 | AN11: =IFERROR($AJ11/4*(1+$AK$7),0) -> 32.080957 | AO11: =SUM(AK11:AN11) -> 128.32383 | AP11: =IFERROR($AO11/4*(1+$AP$7),0) -> 36.893101 | AQ11: =IFERROR($AO11/4*(1+$AP$7),0) -> 36.893101 | AR11: =IFERROR($AO11/4*(1+$AP$7),0) -> 36.893101 | AS11: =IFERROR($AO11/4*(1+$AP$7),0) -> 36.893101 | AT11: =SUM(AP11:AS11) -> 147.5724 | AU11: =IFERROR($AT11/4*(1+$AU$7),0) -> 42.427066 | AV11: =IFERROR($AT11/4*(1+$AU$7),0) -> 42.427066 | AW11: =IFERROR($AT11/4*(1+$AU$7),0) -> 42.427066 | AX11: =IFERROR($AT11/4*(1+$AU$7),0) -> 42.427066 | AY11: =SUM(AU11:AX11) -> 169.70826 | AZ11: =IFERROR($AY11/4*(1+$AZ$7),0) -> 48.791126 | BA11: =IFERROR($AY11/4*(1+$AZ$7),0) -> 48.791126 | BB11: =IFERROR($AY11/4*(1+$AZ$7),0) -> 48.791126 | BC11: =IFERROR($AY11/4*(1+$AZ$7),0) -> 48.791126 | BD11: =SUM(AZ11:BC11) -> 195.1645 | BE11: =IFERROR($BD11/4*(1+$BE$7),0) -> 56.109794 | BF11: =IFERROR($BD11/4*(1+$BE$7),0) -> 56.109794 | BG11: =IFERROR($BD11/4*(1+$BE$7),0) -> 56.109794 | BH11: =IFERROR($BD11/4*(1+$BE$7),0) -> 56.109794 | BI11: =SUM(BE11:BH11) -> 224.43918 | BJ11: =IFERROR($BI11/4*(1+$BJ$7),0) -> 64.526264 | BK11: =IFERROR($BI11/4*(1+$BJ$7),0) -> 64.526264 | BL11: =IFERROR($BI11/4*(1+$BJ$7),0) -> 64.526264 | BM11: =IFERROR($BI11/4*(1+$BJ$7),0) -> 64.526264 | BN11: =SUM(BJ11:BM11) -> 258.10505
A12: ='Customer''s Questionnaire'!H45 -> Software / SaaS | B12: ='Customer''s Questionnaire'!I45 -> BULO | C12: ='Customer''s Questionnaire'!J45 -> Direct | D12: ='Customer''s Questionnaire'!K45 -> EU | E12: ='Customer''s Questionnaire'!L45 -> MCMC | G12: ='Customer''s Questionnaire'!O45 -> 1000 | H12: ='Customer''s Questionnaire'!P45 -> 1000 | I12: ='Customer''s Questionnaire'!Q45 -> 1000 | J12: ='Customer''s Questionnaire'!R45 -> 1000 | K12: =SUM(G12:J12) -> 4000 | L12: =IFERROR('Customer''s Questionnaire'!$S45/4,"Add if needed") -> 1250 | M12: =IFERROR('Customer''s Questionnaire'!$S45/4,"Add if needed") -> 1250 | N12: =IFERROR('Customer''s Questionnaire'!$S45/4,"Add if needed") -> 1250 | O12: =IFERROR('Customer''s Questionnaire'!$S45/4,"Add if needed") -> 1250 | P12: =SUM(L12:O12) -> 5000 | Q12: =IFERROR($P12/4*(1+$Q$7),0) -> 1687.5 | R12: =IFERROR($P12/4*(1+$Q$7),0) -> 1687.5 | S12: =IFERROR($P12/4*(1+$Q$7),0) -> 1687.5 | T12: =IFERROR($P12/4*(1+$Q$7),0) -> 1687.5 | U12: =SUM(Q12:T12) -> 6750 | V12: =IFERROR($U12/4*(1+$V$7),0) -> 2109.375 | W12: =IFERROR($U12/4*(1+$V$7),0) -> 2109.375 | X12: =IFERROR($U12/4*(1+$V$7),0) -> 2109.375 | Y12: =IFERROR($U12/4*(1+$V$7),0) -> 2109.375 | Z12: =SUM(V12:Y12) -> 8437.5 | AA12: =IFERROR($Z12/4*(1+$AA$7),0) -> 2425.7812 | AB12: =IFERROR($Z12/4*(1+$AA$7),0) -> 2425.7812 | AC12: =IFERROR($Z12/4*(1+$AA$7),0) -> 2425.7812 | AD12: =IFERROR($Z12/4*(1+$AA$7),0) -> 2425.7812 | AE12: =SUM(AA12:AD12) -> 9703.125 | AF12: =IFERROR($AE12/4*(1+$AF$7),0) -> 2789.6484 | AG12: =IFERROR($AE12/4*(1+$AF$7),0) -> 2789.6484 | AH12: =IFERROR($AE12/4*(1+$AF$7),0) -> 2789.6484 | AI12: =IFERROR($AE12/4*(1+$AF$7),0) -> 2789.6484 | AJ12: =SUM(AF12:AI12) -> 11158.594 | AK12: =IFERROR($AJ12/4*(1+$AK$7),0) -> 3208.0957 | AL12: =IFERROR($AJ12/4*(1+$AK$7),0) -> 3208.0957 | AM12: =IFERROR($AJ12/4*(1+$AK$7),0) -> 3208.0957 | AN12: =IFERROR($AJ12/4*(1+$AK$7),0) -> 3208.0957 | AO12: =SUM(AK12:AN12) -> 12832.383 | AP12: =IFERROR($AO12/4*(1+$AP$7),0) -> 3689.3101 | AQ12: =IFERROR($AO12/4*(1+$AP$7),0) -> 3689.3101 | AR12: =IFERROR($AO12/4*(1+$AP$7),0) -> 3689.3101 | AS12: =IFERROR($AO12/4*(1+$AP$7),0) -> 3689.3101 | AT12: =SUM(AP12:AS12) -> 14757.24 | AU12: =IFERROR($AT12/4*(1+$AU$7),0) -> 4242.7066 | AV12: =IFERROR($AT12/4*(1+$AU$7),0) -> 4242.7066 | AW12: =IFERROR($AT12/4*(1+$AU$7),0) -> 4242.7066 | AX12: =IFERROR($AT12/4*(1+$AU$7),0) -> 4242.7066 | AY12: =SUM(AU12:AX12) -> 16970.826 | AZ12: =IFERROR($AY12/4*(1+$AZ$7),0) -> 4879.1126 | BA12: =IFERROR($AY12/4*(1+$AZ$7),0) -> 4879.1126 | BB12: =IFERROR($AY12/4*(1+$AZ$7),0) -> 4879.1126 | BC12: =IFERROR($AY12/4*(1+$AZ$7),0) -> 4879.1126 | BD12: =SUM(AZ12:BC12) -> 19516.45 | BE12: =IFERROR($BD12/4*(1+$BE$7),0) -> 5610.9794 | BF12: =IFERROR($BD12/4*(1+$BE$7),0) -> 5610.9794 | BG12: =IFERROR($BD12/4*(1+$BE$7),0) -> 5610.9794 | BH12: =IFERROR($BD12/4*(1+$BE$7),0) -> 5610.9794 | BI12: =SUM(BE12:BH12) -> 22443.918 | BJ12: =IFERROR($BI12/4*(1+$BJ$7),0) -> 6452.6264 | BK12: =IFERROR($BI12/4*(1+$BJ$7),0) -> 6452.6264 | BL12: =IFERROR($BI12/4*(1+$BJ$7),0) -> 6452.6264 | BM12: =IFERROR($BI12/4*(1+$BJ$7),0) -> 6452.6264 | BN12: =SUM(BJ12:BM12) -> 25810.505
A13: ='Customer''s Questionnaire'!H46 -> 0 | B13: ='Customer''s Questionnaire'!I46 -> 0 | C13: ='Customer''s Questionnaire'!J46 -> 0 | D13: ='Customer''s Questionnaire'!K46 -> 0 | E13: ='Customer''s Questionnaire'!L46 -> 0 | G13: ='Customer''s Questionnaire'!O46 -> 0 | H13: ='Customer''s Questionnaire'!P46 -> 0 | I13: ='Customer''s Questionnaire'!Q46 -> 0 | J13: ='Customer''s Questionnaire'!R46 -> 0 | K13: =SUM(G13:J13) -> 0 | L13: =IFERROR('Customer''s Questionnaire'!$S46/4,"Add if needed") -> 0 | M13: =IFERROR('Customer''s Questionnaire'!$S46/4,"Add if needed") -> 0 | N13: =IFERROR('Customer''s Questionnaire'!$S46/4,"Add if needed") -> 0 | O13: =IFERROR('Customer''s Questionnaire'!$S46/4,"Add if needed") -> 0 | P13: =SUM(L13:O13) -> 0 | Q13: =IFERROR($P13/4*(1+$Q$7),0) -> 0 | R13: =IFERROR($P13/4*(1+$Q$7),0) -> 0 | S13: =IFERROR($P13/4*(1+$Q$7),0) -> 0 | T13: =IFERROR($P13/4*(1+$Q$7),0) -> 0 | U13: =SUM(Q13:T13) -> 0 | V13: =IFERROR($U13/4*(1+$V$7),0) -> 0 | W13: =IFERROR($U13/4*(1+$V$7),0) -> 0 | X13: =IFERROR($U13/4*(1+$V$7),0) -> 0 | Y13: =IFERROR($U13/4*(1+$V$7),0) -> 0 | Z13: =SUM(V13:Y13) -> 0 | AA13: =IFERROR($Z13/4*(1+$AA$7),0) -> 0 | AB13: =IFERROR($Z13/4*(1+$AA$7),0) -> 0 | AC13: =IFERROR($Z13/4*(1+$AA$7),0) -> 0 | AD13: =IFERROR($Z13/4*(1+$AA$7),0) -> 0 | AE13: =SUM(AA13:AD13) -> 0 | AF13: =IFERROR($AE13/4*(1+$AF$7),0) -> 0 | AG13: =IFERROR($AE13/4*(1+$AF$7),0) -> 0 | AH13: =IFERROR($AE13/4*(1+$AF$7),0) -> 0 | AI13: =IFERROR($AE13/4*(1+$AF$7),0) -> 0 | AJ13: =SUM(AF13:AI13) -> 0 | AK13: =IFERROR($AJ13/4*(1+$AK$7),0) -> 0 | AL13: =IFERROR($AJ13/4*(1+$AK$7),0) -> 0 | AM13: =IFERROR($AJ13/4*(1+$AK$7),0) -> 0 | AN13: =IFERROR($AJ13/4*(1+$AK$7),0) -> 0 | AO13: =SUM(AK13:AN13) -> 0 | AP13: =IFERROR($AO13/4*(1+$AP$7),0) -> 0 | AQ13: =IFERROR($AO13/4*(1+$AP$7),0) -> 0 | AR13: =IFERROR($AO13/4*(1+$AP$7),0) -> 0 | AS13: =IFERROR($AO13/4*(1+$AP$7),0) -> 0 | AT13: =SUM(AP13:AS13) -> 0 | AU13: =IFERROR($AT13/4*(1+$AU$7),0) -> 0 | AV13: =IFERROR($AT13/4*(1+$AU$7),0) -> 0 | AW13: =IFERROR($AT13/4*(1+$AU$7),0) -> 0 | AX13: =IFERROR($AT13/4*(1+$AU$7),0) -> 0 | AY13: =SUM(AU13:AX13) -> 0 | AZ13: =IFERROR($AY13/4*(1+$AZ$7),0) -> 0 | BA13: =IFERROR($AY13/4*(1+$AZ$7),0) -> 0 | BB13: =IFERROR($AY13/4*(1+$AZ$7),0) -> 0 | BC13: =IFERROR($AY13/4*(1+$AZ$7),0) -> 0 | BD13: =SUM(AZ13:BC13) -> 0 | BE13: =IFERROR($BD13/4*(1+$BE$7),0) -> 0 | BF13: =IFERROR($BD13/4*(1+$BE$7),0) -> 0 | BG13: =IFERROR($BD13/4*(1+$BE$7),0) -> 0 | BH13: =IFERROR($BD13/4*(1+$BE$7),0) -> 0 | BI13: =SUM(BE13:BH13) -> 0 | BJ13: =IFERROR($BI13/4*(1+$BJ$7),0) -> 0 | BK13: =IFERROR($BI13/4*(1+$BJ$7),0) -> 0 | BL13: =IFERROR($BI13/4*(1+$BJ$7),0) -> 0 | BM13: =IFERROR($BI13/4*(1+$BJ$7),0) -> 0 | BN13: =SUM(BJ13:BM13) -> 0
A14: ='Customer''s Questionnaire'!H47 -> 0 | B14: ='Customer''s Questionnaire'!I47 -> 0 | C14: ='Customer''s Questionnaire'!J47 -> 0 | D14: ='Customer''s Questionnaire'!K47 -> 0 | E14: ='Customer''s Questionnaire'!L47 -> 0 | G14: ='Customer''s Questionnaire'!O47 -> 0 | H14: ='Customer''s Questionnaire'!P47 -> 0 | I14: ='Customer''s Questionnaire'!Q47 -> 0 | J14: ='Customer''s Questionnaire'!R47 -> 0 | K14: =SUM(G14:J14) -> 0 | L14: =IFERROR('Customer''s Questionnaire'!$S47/4,"Add if needed") -> 0 | M14: =IFERROR('Customer''s Questionnaire'!$S47/4,"Add if needed") -> 0 | N14: =IFERROR('Customer''s Questionnaire'!$S47/4,"Add if needed") -> 0 | O14: =IFERROR('Customer''s Questionnaire'!$S47/4,"Add if needed") -> 0 | P14: =SUM(L14:O14) -> 0 | Q14: =IFERROR($P14/4*(1+$Q$7),0) -> 0 | R14: =IFERROR($P14/4*(1+$Q$7),0) -> 0 | S14: =IFERROR($P14/4*(1+$Q$7),0) -> 0 | T14: =IFERROR($P14/4*(1+$Q$7),0) -> 0 | U14: =SUM(Q14:T14) -> 0 | V14: =IFERROR($U14/4*(1+$V$7),0) -> 0 | W14: =IFERROR($U14/4*(1+$V$7),0) -> 0 | X14: =IFERROR($U14/4*(1+$V$7),0) -> 0 | Y14: =IFERROR($U14/4*(1+$V$7),0) -> 0 | Z14: =SUM(V14:Y14) -> 0 | AA14: =IFERROR($Z14/4*(1+$AA$7),0) -> 0 | AB14: =IFERROR($Z14/4*(1+$AA$7),0) -> 0 | AC14: =IFERROR($Z14/4*(1+$AA$7),0) -> 0 | AD14: =IFERROR($Z14/4*(1+$AA$7),0) -> 0 | AE14: =SUM(AA14:AD14) -> 0 | AF14: =IFERROR($AE14/4*(1+$AF$7),0) -> 0 | AG14: =IFERROR($AE14/4*(1+$AF$7),0) -> 0 | AH14: =IFERROR($AE14/4*(1+$AF$7),0) -> 0 | AI14: =IFERROR($AE14/4*(1+$AF$7),0) -> 0 | AJ14: =SUM(AF14:AI14) -> 0 | AK14: =IFERROR($AJ14/4*(1+$AK$7),0) -> 0 | AL14: =IFERROR($AJ14/4*(1+$AK$7),0) -> 0 | AM14: =IFERROR($AJ14/4*(1+$AK$7),0) -> 0 | AN14: =IFERROR($AJ14/4*(1+$AK$7),0) -> 0 | AO14: =SUM(AK14:AN14) -> 0 | AP14: =IFERROR($AO14/4*(1+$AP$7),0) -> 0 | AQ14: =IFERROR($AO14/4*(1+$AP$7),0) -> 0 | AR14: =IFERROR($AO14/4*(1+$AP$7),0) -> 0 | AS14: =IFERROR($AO14/4*(1+$AP$7),0) -> 0 | AT14: =SUM(AP14:AS14) -> 0 | AU14: =IFERROR($AT14/4*(1+$AU$7),0) -> 0 | AV14: =IFERROR($AT14/4*(1+$AU$7),0) -> 0 | AW14: =IFERROR($AT14/4*(1+$AU$7),0) -> 0 | AX14: =IFERROR($AT14/4*(1+$AU$7),0) -> 0 | AY14: =SUM(AU14:AX14) -> 0 | AZ14: =IFERROR($AY14/4*(1+$AZ$7),0) -> 0 | BA14: =IFERROR($AY14/4*(1+$AZ$7),0) -> 0 | BB14: =IFERROR($AY14/4*(1+$AZ$7),0) -> 0 | BC14: =IFERROR($AY14/4*(1+$AZ$7),0) -> 0 | BD14: =SUM(AZ14:BC14) -> 0 | BE14: =IFERROR($BD14/4*(1+$BE$7),0) -> 0 | BF14: =IFERROR($BD14/4*(1+$BE$7),0) -> 0 | BG14: =IFERROR($BD14/4*(1+$BE$7),0) -> 0 | BH14: =IFERROR($BD14/4*(1+$BE$7),0) -> 0 | BI14: =SUM(BE14:BH14) -> 0 | BJ14: =IFERROR($BI14/4*(1+$BJ$7),0) -> 0 | BK14: =IFERROR($BI14/4*(1+$BJ$7),0) -> 0 | BL14: =IFERROR($BI14/4*(1+$BJ$7),0) -> 0 | BM14: =IFERROR($BI14/4*(1+$BJ$7),0) -> 0 | BN14: =SUM(BJ14:BM14) -> 0
A15: ='Customer''s Questionnaire'!H48 -> 0 | B15: ='Customer''s Questionnaire'!I48 -> 0 | C15: ='Customer''s Questionnaire'!J48 -> 0 | D15: ='Customer''s Questionnaire'!K48 -> 0 | E15: ='Customer''s Questionnaire'!L48 -> 0 | G15: ='Customer''s Questionnaire'!O48 -> 0 | H15: ='Customer''s Questionnaire'!P48 -> 0 | I15: ='Customer''s Questionnaire'!Q48 -> 0 | J15: ='Customer''s Questionnaire'!R48 -> 0 | K15: =SUM(G15:J15) -> 0 | L15: =IFERROR('Customer''s Questionnaire'!$S48/4,"Add if needed") -> 0 | M15: =IFERROR('Customer''s Questionnaire'!$S48/4,"Add if needed") -> 0 | N15: =IFERROR('Customer''s Questionnaire'!$S48/4,"Add if needed") -> 0 | O15: =IFERROR('Customer''s Questionnaire'!$S48/4,"Add if needed") -> 0 | P15: =SUM(L15:O15) -> 0 | Q15: =IFERROR($P15/4*(1+$Q$7),0) -> 0 | R15: =IFERROR($P15/4*(1+$Q$7),0) -> 0 | S15: =IFERROR($P15/4*(1+$Q$7),0) -> 0 | T15: =IFERROR($P15/4*(1+$Q$7),0) -> 0 | U15: =SUM(Q15:T15) -> 0 | V15: =IFERROR($U15/4*(1+$V$7),0) -> 0 | W15: =IFERROR($U15/4*(1+$V$7),0) -> 0 | X15: =IFERROR($U15/4*(1+$V$7),0) -> 0 | Y15: =IFERROR($U15/4*(1+$V$7),0) -> 0 | Z15: =SUM(V15:Y15) -> 0 | AA15: =IFERROR($Z15/4*(1+$AA$7),0) -> 0 | AB15: =IFERROR($Z15/4*(1+$AA$7),0) -> 0 | AC15: =IFERROR($Z15/4*(1+$AA$7),0) -> 0 | AD15: =IFERROR($Z15/4*(1+$AA$7),0) -> 0 | AE15: =SUM(AA15:AD15) -> 0 | AF15: =IFERROR($AE15/4*(1+$AF$7),0) -> 0 | AG15: =IFERROR($AE15/4*(1+$AF$7),0) -> 0 | AH15: =IFERROR($AE15/4*(1+$AF$7),0) -> 0 | AI15: =IFERROR($AE15/4*(1+$AF$7),0) -> 0 | AJ15: =SUM(AF15:AI15) -> 0 | AK15: =IFERROR($AJ15/4*(1+$AK$7),0) -> 0 | AL15: =IFERROR($AJ15/4*(1+$AK$7),0) -> 0 | AM15: =IFERROR($AJ15/4*(1+$AK$7),0) -> 0 | AN15: =IFERROR($AJ15/4*(1+$AK$7),0) -> 0 | AO15: =SUM(AK15:AN15) -> 0 | AP15: =IFERROR($AO15/4*(1+$AP$7),0) -> 0 | AQ15: =IFERROR($AO15/4*(1+$AP$7),0) -> 0 | AR15: =IFERROR($AO15/4*(1+$AP$7),0) -> 0 | AS15: =IFERROR($AO15/4*(1+$AP$7),0) -> 0 | AT15: =SUM(AP15:AS15) -> 0 | AU15: =IFERROR($AT15/4*(1+$AU$7),0) -> 0 | AV15: =IFERROR($AT15/4*(1+$AU$7),0) -> 0 | AW15: =IFERROR($AT15/4*(1+$AU$7),0) -> 0 | AX15: =IFERROR($AT15/4*(1+$AU$7),0) -> 0 | AY15: =SUM(AU15:AX15) -> 0 | AZ15: =IFERROR($AY15/4*(1+$AZ$7),0) -> 0 | BA15: =IFERROR($AY15/4*(1+$AZ$7),0) -> 0 | BB15: =IFERROR($AY15/4*(1+$AZ$7),0) -> 0 | BC15: =IFERROR($AY15/4*(1+$AZ$7),0) -> 0 | BD15: =SUM(AZ15:BC15) -> 0 | BE15: =IFERROR($BD15/4*(1+$BE$7),0) -> 0 | BF15: =IFERROR($BD15/4*(1+$BE$7),0) -> 0 | BG15: =IFERROR($BD15/4*(1+$BE$7),0) -> 0 | BH15: =IFERROR($BD15/4*(1+$BE$7),0) -> 0 | BI15: =SUM(BE15:BH15) -> 0 | BJ15: =IFERROR($BI15/4*(1+$BJ$7),0) -> 0 | BK15: =IFERROR($BI15/4*(1+$BJ$7),0) -> 0 | BL15: =IFERROR($BI15/4*(1+$BJ$7),0) -> 0 | BM15: =IFERROR($BI15/4*(1+$BJ$7),0) -> 0 | BN15: =SUM(BJ15:BM15) -> 0
A16: ='Customer''s Questionnaire'!H49 -> 0 | B16: ='Customer''s Questionnaire'!I49 -> 0 | C16: ='Customer''s Questionnaire'!J49 -> 0 | D16: ='Customer''s Questionnaire'!K49 -> 0 | E16: ='Customer''s Questionnaire'!L49 -> 0 | G16: ='Customer''s Questionnaire'!O49 -> 0 | H16: ='Customer''s Questionnaire'!P49 -> 0 | I16: ='Customer''s Questionnaire'!Q49 -> 0 | J16: ='Customer''s Questionnaire'!R49 -> 0 | K16: =SUM(G16:J16) -> 0 | L16: =IFERROR('Customer''s Questionnaire'!$S49/4,"Add if needed") -> 0 | M16: =IFERROR('Customer''s Questionnaire'!$S49/4,"Add if needed") -> 0 | N16: =IFERROR('Customer''s Questionnaire'!$S49/4,"Add if needed") -> 0 | O16: =IFERROR('Customer''s Questionnaire'!$S49/4,"Add if needed") -> 0 | P16: =SUM(L16:O16) -> 0 | Q16: =IFERROR($P16/4*(1+$Q$7),0) -> 0 | R16: =IFERROR($P16/4*(1+$Q$7),0) -> 0 | S16: =IFERROR($P16/4*(1+$Q$7),0) -> 0 | T16: =IFERROR($P16/4*(1+$Q$7),0) -> 0 | U16: =SUM(Q16:T16) -> 0 | V16: =IFERROR($U16/4*(1+$V$7),0) -> 0 | W16: =IFERROR($U16/4*(1+$V$7),0) -> 0 | X16: =IFERROR($U16/4*(1+$V$7),0) -> 0 | Y16: =IFERROR($U16/4*(1+$V$7),0) -> 0 | Z16: =SUM(V16:Y16) -> 0 | AA16: =IFERROR($Z16/4*(1+$AA$7),0) -> 0 | AB16: =IFERROR($Z16/4*(1+$AA$7),0) -> 0 | AC16: =IFERROR($Z16/4*(1+$AA$7),0) -> 0 | AD16: =IFERROR($Z16/4*(1+$AA$7),0) -> 0 | AE16: =SUM(AA16:AD16) -> 0 | AF16: =IFERROR($AE16/4*(1+$AF$7),0) -> 0 | AG16: =IFERROR($AE16/4*(1+$AF$7),0) -> 0 | AH16: =IFERROR($AE16/4*(1+$AF$7),0) -> 0 | AI16: =IFERROR($AE16/4*(1+$AF$7),0) -> 0 | AJ16: =SUM(AF16:AI16) -> 0 | AK16: =IFERROR($AJ16/4*(1+$AK$7),0) -> 0 | AL16: =IFERROR($AJ16/4*(1+$AK$7),0) -> 0 | AM16: =IFERROR($AJ16/4*(1+$AK$7),0) -> 0 | AN16: =IFERROR($AJ16/4*(1+$AK$7),0) -> 0 | AO16: =SUM(AK16:AN16) -> 0 | AP16: =IFERROR($AO16/4*(1+$AP$7),0) -> 0 | AQ16: =IFERROR($AO16/4*(1+$AP$7),0) -> 0 | AR16: =IFERROR($AO16/4*(1+$AP$7),0) -> 0 | AS16: =IFERROR($AO16/4*(1+$AP$7),0) -> 0 | AT16: =SUM(AP16:AS16) -> 0 | AU16: =IFERROR($AT16/4*(1+$AU$7),0) -> 0 | AV16: =IFERROR($AT16/4*(1+$AU$7),0) -> 0 | AW16: =IFERROR($AT16/4*(1+$AU$7),0) -> 0 | AX16: =IFERROR($AT16/4*(1+$AU$7),0) -> 0 | AY16: =SUM(AU16:AX16) -> 0 | AZ16: =IFERROR($AY16/4*(1+$AZ$7),0) -> 0 | BA16: =IFERROR($AY16/4*(1+$AZ$7),0) -> 0 | BB16: =IFERROR($AY16/4*(1+$AZ$7),0) -> 0 | BC16: =IFERROR($AY16/4*(1+$AZ$7),0) -> 0 | BD16: =SUM(AZ16:BC16) -> 0 | BE16: =IFERROR($BD16/4*(1+$BE$7),0) -> 0 | BF16: =IFERROR($BD16/4*(1+$BE$7),0) -> 0 | BG16: =IFERROR($BD16/4*(1+$BE$7),0) -> 0 | BH16: =IFERROR($BD16/4*(1+$BE$7),0) -> 0 | BI16: =SUM(BE16:BH16) -> 0 | BJ16: =IFERROR($BI16/4*(1+$BJ$7),0) -> 0 | BK16: =IFERROR($BI16/4*(1+$BJ$7),0) -> 0 | BL16: =IFERROR($BI16/4*(1+$BJ$7),0) -> 0 | BM16: =IFERROR($BI16/4*(1+$BJ$7),0) -> 0 | BN16: =SUM(BJ16:BM16) -> 0
A17: ='Customer''s Questionnaire'!H50 -> 0 | B17: ='Customer''s Questionnaire'!I50 -> 0 | C17: ='Customer''s Questionnaire'!J50 -> 0 | D17: ='Customer''s Questionnaire'!K50 -> 0 | E17: ='Customer''s Questionnaire'!L50 -> 0 | G17: ='Customer''s Questionnaire'!O50 -> 0 | H17: ='Customer''s Questionnaire'!P50 -> 0 | I17: ='Customer''s Questionnaire'!Q50 -> 0 | J17: ='Customer''s Questionnaire'!R50 -> 0 | K17: =SUM(G17:J17) -> 0 | L17: =IFERROR('Customer''s Questionnaire'!$S50/4,"Add if needed") -> 0 | M17: =IFERROR('Customer''s Questionnaire'!$S50/4,"Add if needed") -> 0 | N17: =IFERROR('Customer''s Questionnaire'!$S50/4,"Add if needed") -> 0 | O17: =IFERROR('Customer''s Questionnaire'!$S50/4,"Add if needed") -> 0 | P17: =SUM(L17:O17) -> 0 | Q17: =IFERROR($P17/4*(1+$Q$7),0) -> 0 | R17: =IFERROR($P17/4*(1+$Q$7),0) -> 0 | S17: =IFERROR($P17/4*(1+$Q$7),0) -> 0 | T17: =IFERROR($P17/4*(1+$Q$7),0) -> 0 | U17: =SUM(Q17:T17) -> 0 | V17: =IFERROR($U17/4*(1+$V$7),0) -> 0 | W17: =IFERROR($U17/4*(1+$V$7),0) -> 0 | X17: =IFERROR($U17/4*(1+$V$7),0) -> 0 | Y17: =IFERROR($U17/4*(1+$V$7),0) -> 0 | Z17: =SUM(V17:Y17) -> 0 | AA17: =IFERROR($Z17/4*(1+$AA$7),0) -> 0 | AB17: =IFERROR($Z17/4*(1+$AA$7),0) -> 0 | AC17: =IFERROR($Z17/4*(1+$AA$7),0) -> 0 | AD17: =IFERROR($Z17/4*(1+$AA$7),0) -> 0 | AE17: =SUM(AA17:AD17) -> 0 | AF17: =IFERROR($AE17/4*(1+$AF$7),0) -> 0 | AG17: =IFERROR($AE17/4*(1+$AF$7),0) -> 0 | AH17: =IFERROR($AE17/4*(1+$AF$7),0) -> 0 | AI17: =IFERROR($AE17/4*(1+$AF$7),0) -> 0 | AJ17: =SUM(AF17:AI17) -> 0 | AK17: =IFERROR($AJ17/4*(1+$AK$7),0) -> 0 | AL17: =IFERROR($AJ17/4*(1+$AK$7),0) -> 0 | AM17: =IFERROR($AJ17/4*(1+$AK$7),0) -> 0 | AN17: =IFERROR($AJ17/4*(1+$AK$7),0) -> 0 | AO17: =SUM(AK17:AN17) -> 0 | AP17: =IFERROR($AO17/4*(1+$AP$7),0) -> 0 | AQ17: =IFERROR($AO17/4*(1+$AP$7),0) -> 0 | AR17: =IFERROR($AO17/4*(1+$AP$7),0) -> 0 | AS17: =IFERROR($AO17/4*(1+$AP$7),0) -> 0 | AT17: =SUM(AP17:AS17) -> 0 | AU17: =IFERROR($AT17/4*(1+$AU$7),0) -> 0 | AV17: =IFERROR($AT17/4*(1+$AU$7),0) -> 0 | AW17: =IFERROR($AT17/4*(1+$AU$7),0) -> 0 | AX17: =IFERROR($AT17/4*(1+$AU$7),0) -> 0 | AY17: =SUM(AU17:AX17) -> 0 | AZ17: =IFERROR($AY17/4*(1+$AZ$7),0) -> 0 | BA17: =IFERROR($AY17/4*(1+$AZ$7),0) -> 0 | BB17: =IFERROR($AY17/4*(1+$AZ$7),0) -> 0 | BC17: =IFERROR($AY17/4*(1+$AZ$7),0) -> 0 | BD17: =SUM(AZ17:BC17) -> 0 | BE17: =IFERROR($BD17/4*(1+$BE$7),0) -> 0 | BF17: =IFERROR($BD17/4*(1+$BE$7),0) -> 0 | BG17: =IFERROR($BD17/4*(1+$BE$7),0) -> 0 | BH17: =IFERROR($BD17/4*(1+$BE$7),0) -> 0 | BI17: =SUM(BE17:BH17) -> 0 | BJ17: =IFERROR($BI17/4*(1+$BJ$7),0) -> 0 | BK17: =IFERROR($BI17/4*(1+$BJ$7),0) -> 0 | BL17: =IFERROR($BI17/4*(1+$BJ$7),0) -> 0 | BM17: =IFERROR($BI17/4*(1+$BJ$7),0) -> 0 | BN17: =SUM(BJ17:BM17) -> 0
A18: ='Customer''s Questionnaire'!H51 -> 0 | B18: ='Customer''s Questionnaire'!I51 -> 0 | C18: ='Customer''s Questionnaire'!J51 -> 0 | D18: ='Customer''s Questionnaire'!K51 -> 0 | E18: ='Customer''s Questionnaire'!L51 -> 0 | G18: ='Customer''s Questionnaire'!O51 -> 0 | H18: ='Customer''s Questionnaire'!P51 -> 0 | I18: ='Customer''s Questionnaire'!Q51 -> 0 | J18: ='Customer''s Questionnaire'!R51 -> 0 | K18: =SUM(G18:J18) -> 0 | L18: =IFERROR('Customer''s Questionnaire'!$S51/4,"Add if needed") -> 0 | M18: =IFERROR('Customer''s Questionnaire'!$S51/4,"Add if needed") -> 0 | N18: =IFERROR('Customer''s Questionnaire'!$S51/4,"Add if needed") -> 0 | O18: =IFERROR('Customer''s Questionnaire'!$S51/4,"Add if needed") -> 0 | P18: =SUM(L18:O18) -> 0 | Q18: =IFERROR($P18/4*(1+$Q$7),0) -> 0 | R18: =IFERROR($P18/4*(1+$Q$7),0) -> 0 | S18: =IFERROR($P18/4*(1+$Q$7),0) -> 0 | T18: =IFERROR($P18/4*(1+$Q$7),0) -> 0 | U18: =SUM(Q18:T18) -> 0 | V18: =IFERROR($U18/4*(1+$V$7),0) -> 0 | W18: =IFERROR($U18/4*(1+$V$7),0) -> 0 | X18: =IFERROR($U18/4*(1+$V$7),0) -> 0 | Y18: =IFERROR($U18/4*(1+$V$7),0) -> 0 | Z18: =SUM(V18:Y18) -> 0 | AA18: =IFERROR($Z18/4*(1+$AA$7),0) -> 0 | AB18: =IFERROR($Z18/4*(1+$AA$7),0) -> 0 | AC18: =IFERROR($Z18/4*(1+$AA$7),0) -> 0 | AD18: =IFERROR($Z18/4*(1+$AA$7),0) -> 0 | AE18: =SUM(AA18:AD18) -> 0 | AF18: =IFERROR($AE18/4*(1+$AF$7),0) -> 0 | AG18: =IFERROR($AE18/4*(1+$AF$7),0) -> 0 | AH18: =IFERROR($AE18/4*(1+$AF$7),0) -> 0 | AI18: =IFERROR($AE18/4*(1+$AF$7),0) -> 0 | AJ18: =SUM(AF18:AI18) -> 0 | AK18: =IFERROR($AJ18/4*(1+$AK$7),0) -> 0 | AL18: =IFERROR($AJ18/4*(1+$AK$7),0) -> 0 | AM18: =IFERROR($AJ18/4*(1+$AK$7),0) -> 0 | AN18: =IFERROR($AJ18/4*(1+$AK$7),0) -> 0 | AO18: =SUM(AK18:AN18) -> 0 | AP18: =IFERROR($AO18/4*(1+$AP$7),0) -> 0 | AQ18: =IFERROR($AO18/4*(1+$AP$7),0) -> 0 | AR18: =IFERROR($AO18/4*(1+$AP$7),0) -> 0 | AS18: =IFERROR($AO18/4*(1+$AP$7),0) -> 0 | AT18: =SUM(AP18:AS18) -> 0 | AU18: =IFERROR($AT18/4*(1+$AU$7),0) -> 0 | AV18: =IFERROR($AT18/4*(1+$AU$7),0) -> 0 | AW18: =IFERROR($AT18/4*(1+$AU$7),0) -> 0 | AX18: =IFERROR($AT18/4*(1+$AU$7),0) -> 0 | AY18: =SUM(AU18:AX18) -> 0 | AZ18: =IFERROR($AY18/4*(1+$AZ$7),0) -> 0 | BA18: =IFERROR($AY18/4*(1+$AZ$7),0) -> 0 | BB18: =IFERROR($AY18/4*(1+$AZ$7),0) -> 0 | BC18: =IFERROR($AY18/4*(1+$AZ$7),0) -> 0 | BD18: =SUM(AZ18:BC18) -> 0 | BE18: =IFERROR($BD18/4*(1+$BE$7),0) -> 0 | BF18: =IFERROR($BD18/4*(1+$BE$7),0) -> 0 | BG18: =IFERROR($BD18/4*(1+$BE$7),0) -> 0 | BH18: =IFERROR($BD18/4*(1+$BE$7),0) -> 0 | BI18: =SUM(BE18:BH18) -> 0 | BJ18: =IFERROR($BI18/4*(1+$BJ$7),0) -> 0 | BK18: =IFERROR($BI18/4*(1+$BJ$7),0) -> 0 | BL18: =IFERROR($BI18/4*(1+$BJ$7),0) -> 0 | BM18: =IFERROR($BI18/4*(1+$BJ$7),0) -> 0 | BN18: =SUM(BJ18:BM18) -> 0
A19: ='Customer''s Questionnaire'!H52 -> 0 | B19: ='Customer''s Questionnaire'!I52 -> 0 | C19: ='Customer''s Questionnaire'!J52 -> 0 | D19: ='Customer''s Questionnaire'!K52 -> 0 | E19: ='Customer''s Questionnaire'!L52 -> 0 | G19: ='Customer''s Questionnaire'!O52 -> 0 | H19: ='Customer''s Questionnaire'!P52 -> 0 | I19: ='Customer''s Questionnaire'!Q52 -> 0 | J19: ='Customer''s Questionnaire'!R52 -> 0 | K19: =SUM(G19:J19) -> 0 | L19: =IFERROR('Customer''s Questionnaire'!$S52/4,"Add if needed") -> 0 | M19: =IFERROR('Customer''s Questionnaire'!$S52/4,"Add if needed") -> 0 | N19: =IFERROR('Customer''s Questionnaire'!$S52/4,"Add if needed") -> 0 | O19: =IFERROR('Customer''s Questionnaire'!$S52/4,"Add if needed") -> 0 | P19: =SUM(L19:O19) -> 0 | Q19: =IFERROR($P19/4*(1+$Q$7),0) -> 0 | R19: =IFERROR($P19/4*(1+$Q$7),0) -> 0 | S19: =IFERROR($P19/4*(1+$Q$7),0) -> 0 | T19: =IFERROR($P19/4*(1+$Q$7),0) -> 0 | U19: =SUM(Q19:T19) -> 0 | V19: =IFERROR($U19/4*(1+$V$7),0) -> 0 | W19: =IFERROR($U19/4*(1+$V$7),0) -> 0 | X19: =IFERROR($U19/4*(1+$V$7),0) -> 0 | Y19: =IFERROR($U19/4*(1+$V$7),0) -> 0 | Z19: =SUM(V19:Y19) -> 0 | AA19: =IFERROR($Z19/4*(1+$AA$7),0) -> 0 | AB19: =IFERROR($Z19/4*(1+$AA$7),0) -> 0 | AC19: =IFERROR($Z19/4*(1+$AA$7),0) -> 0 | AD19: =IFERROR($Z19/4*(1+$AA$7),0) -> 0 | AE19: =SUM(AA19:AD19) -> 0 | AF19: =IFERROR($AE19/4*(1+$AF$7),0) -> 0 | AG19: =IFERROR($AE19/4*(1+$AF$7),0) -> 0 | AH19: =IFERROR($AE19/4*(1+$AF$7),0) -> 0 | AI19: =IFERROR($AE19/4*(1+$AF$7),0) -> 0 | AJ19: =SUM(AF19:AI19) -> 0 | AK19: =IFERROR($AJ19/4*(1+$AK$7),0) -> 0 | AL19: =IFERROR($AJ19/4*(1+$AK$7),0) -> 0 | AM19: =IFERROR($AJ19/4*(1+$AK$7),0) -> 0 | AN19: =IFERROR($AJ19/4*(1+$AK$7),0) -> 0 | AO19: =SUM(AK19:AN19) -> 0 | AP19: =IFERROR($AO19/4*(1+$AP$7),0) -> 0 | AQ19: =IFERROR($AO19/4*(1+$AP$7),0) -> 0 | AR19: =IFERROR($AO19/4*(1+$AP$7),0) -> 0 | AS19: =IFERROR($AO19/4*(1+$AP$7),0) -> 0 | AT19: =SUM(AP19:AS19) -> 0 | AU19: =IFERROR($AT19/4*(1+$AU$7),0) -> 0 | AV19: =IFERROR($AT19/4*(1+$AU$7),0) -> 0 | AW19: =IFERROR($AT19/4*(1+$AU$7),0) -> 0 | AX19: =IFERROR($AT19/4*(1+$AU$7),0) -> 0 | AY19: =SUM(AU19:AX19) -> 0 | AZ19: =IFERROR($AY19/4*(1+$AZ$7),0) -> 0 | BA19: =IFERROR($AY19/4*(1+$AZ$7),0) -> 0 | BB19: =IFERROR($AY19/4*(1+$AZ$7),0) -> 0 | BC19: =IFERROR($AY19/4*(1+$AZ$7),0) -> 0 | BD19: =SUM(AZ19:BC19) -> 0 | BE19: =IFERROR($BD19/4*(1+$BE$7),0) -> 0 | BF19: =IFERROR($BD19/4*(1+$BE$7),0) -> 0 | BG19: =IFERROR($BD19/4*(1+$BE$7),0) -> 0 | BH19: =IFERROR($BD19/4*(1+$BE$7),0) -> 0 | BI19: =SUM(BE19:BH19) -> 0 | BJ19: =IFERROR($BI19/4*(1+$BJ$7),0) -> 0 | BK19: =IFERROR($BI19/4*(1+$BJ$7),0) -> 0 | BL19: =IFERROR($BI19/4*(1+$BJ$7),0) -> 0 | BM19: =IFERROR($BI19/4*(1+$BJ$7),0) -> 0 | BN19: =SUM(BJ19:BM19) -> 0
A20: ='Customer''s Questionnaire'!H53 -> 0 | B20: ='Customer''s Questionnaire'!I53 -> 0 | C20: ='Customer''s Questionnaire'!J53 -> 0 | D20: ='Customer''s Questionnaire'!K53 -> 0 | E20: ='Customer''s Questionnaire'!L53 -> 0 | G20: ='Customer''s Questionnaire'!O53 -> 0 | H20: ='Customer''s Questionnaire'!P53 -> 0 | I20: ='Customer''s Questionnaire'!Q53 -> 0 | J20: ='Customer''s Questionnaire'!R53 -> 0 | K20: =SUM(G20:J20) -> 0 | L20: =IFERROR('Customer''s Questionnaire'!$S53/4,"Add if needed") -> 0 | M20: =IFERROR('Customer''s Questionnaire'!$S53/4,"Add if needed") -> 0 | N20: =IFERROR('Customer''s Questionnaire'!$S53/4,"Add if needed") -> 0 | O20: =IFERROR('Customer''s Questionnaire'!$S53/4,"Add if needed") -> 0 | P20: =SUM(L20:O20) -> 0 | Q20: =IFERROR($P20/4*(1+$Q$7),0) -> 0 | R20: =IFERROR($P20/4*(1+$Q$7),0) -> 0 | S20: =IFERROR($P20/4*(1+$Q$7),0) -> 0 | T20: =IFERROR($P20/4*(1+$Q$7),0) -> 0 | U20: =SUM(Q20:T20) -> 0 | V20: =IFERROR($U20/4*(1+$V$7),0) -> 0 | W20: =IFERROR($U20/4*(1+$V$7),0) -> 0 | X20: =IFERROR($U20/4*(1+$V$7),0) -> 0 | Y20: =IFERROR($U20/4*(1+$V$7),0) -> 0 | Z20: =SUM(V20:Y20) -> 0 | AA20: =IFERROR($Z20/4*(1+$AA$7),0) -> 0 | AB20: =IFERROR($Z20/4*(1+$AA$7),0) -> 0 | AC20: =IFERROR($Z20/4*(1+$AA$7),0) -> 0 | AD20: =IFERROR($Z20/4*(1+$AA$7),0) -> 0 | AE20: =SUM(AA20:AD20) -> 0 | AF20: =IFERROR($AE20/4*(1+$AF$7),0) -> 0 | AG20: =IFERROR($AE20/4*(1+$AF$7),0) -> 0 | AH20: =IFERROR($AE20/4*(1+$AF$7),0) -> 0 | AI20: =IFERROR($AE20/4*(1+$AF$7),0) -> 0 | AJ20: =SUM(AF20:AI20) -> 0 | AK20: =IFERROR($AJ20/4*(1+$AK$7),0) -> 0 | AL20: =IFERROR($AJ20/4*(1+$AK$7),0) -> 0 | AM20: =IFERROR($AJ20/4*(1+$AK$7),0) -> 0 | AN20: =IFERROR($AJ20/4*(1+$AK$7),0) -> 0 | AO20: =SUM(AK20:AN20) -> 0 | AP20: =IFERROR($AO20/4*(1+$AP$7),0) -> 0 | AQ20: =IFERROR($AO20/4*(1+$AP$7),0) -> 0 | AR20: =IFERROR($AO20/4*(1+$AP$7),0) -> 0 | AS20: =IFERROR($AO20/4*(1+$AP$7),0) -> 0 | AT20: =SUM(AP20:AS20) -> 0 | AU20: =IFERROR($AT20/4*(1+$AU$7),0) -> 0 | AV20: =IFERROR($AT20/4*(1+$AU$7),0) -> 0 | AW20: =IFERROR($AT20/4*(1+$AU$7),0) -> 0 | AX20: =IFERROR($AT20/4*(1+$AU$7),0) -> 0 | AY20: =SUM(AU20:AX20) -> 0 | AZ20: =IFERROR($AY20/4*(1+$AZ$7),0) -> 0 | BA20: =IFERROR($AY20/4*(1+$AZ$7),0) -> 0 | BB20: =IFERROR($AY20/4*(1+$AZ$7),0) -> 0 | BC20: =IFERROR($AY20/4*(1+$AZ$7),0) -> 0 | BD20: =SUM(AZ20:BC20) -> 0 | BE20: =IFERROR($BD20/4*(1+$BE$7),0) -> 0 | BF20: =IFERROR($BD20/4*(1+$BE$7),0) -> 0 | BG20: =IFERROR($BD20/4*(1+$BE$7),0) -> 0 | BH20: =IFERROR($BD20/4*(1+$BE$7),0) -> 0 | BI20: =SUM(BE20:BH20) -> 0 | BJ20: =IFERROR($BI20/4*(1+$BJ$7),0) -> 0 | BK20: =IFERROR($BI20/4*(1+$BJ$7),0) -> 0 | BL20: =IFERROR($BI20/4*(1+$BJ$7),0) -> 0 | BM20: =IFERROR($BI20/4*(1+$BJ$7),0) -> 0 | BN20: =SUM(BJ20:BM20) -> 0
A21: ='Customer''s Questionnaire'!H54 -> 0 | B21: ='Customer''s Questionnaire'!I54 -> 0 | C21: ='Customer''s Questionnaire'!J54 -> 0 | D21: ='Customer''s Questionnaire'!K54 -> 0 | E21: ='Customer''s Questionnaire'!L54 -> 0 | G21: ='Customer''s Questionnaire'!O54 -> 0 | H21: ='Customer''s Questionnaire'!P54 -> 0 | I21: ='Customer''s Questionnaire'!Q54 -> 0 | J21: ='Customer''s Questionnaire'!R54 -> 0 | K21: =SUM(G21:J21) -> 0 | L21: =IFERROR('Customer''s Questionnaire'!$S54/4,"Add if needed") -> 0 | M21: =IFERROR('Customer''s Questionnaire'!$S54/4,"Add if needed") -> 0 | N21: =IFERROR('Customer''s Questionnaire'!$S54/4,"Add if needed") -> 0 | O21: =IFERROR('Customer''s Questionnaire'!$S54/4,"Add if needed") -> 0 | P21: =SUM(L21:O21) -> 0 | Q21: =IFERROR($P21/4*(1+$Q$7),0) -> 0 | R21: =IFERROR($P21/4*(1+$Q$7),0) -> 0 | S21: =IFERROR($P21/4*(1+$Q$7),0) -> 0 | T21: =IFERROR($P21/4*(1+$Q$7),0) -> 0 | U21: =SUM(Q21:T21) -> 0 | V21: =IFERROR($U21/4*(1+$V$7),0) -> 0 | W21: =IFERROR($U21/4*(1+$V$7),0) -> 0 | X21: =IFERROR($U21/4*(1+$V$7),0) -> 0 | Y21: =IFERROR($U21/4*(1+$V$7),0) -> 0 | Z21: =SUM(V21:Y21) -> 0 | AA21: =IFERROR($Z21/4*(1+$AA$7),0) -> 0 | AB21: =IFERROR($Z21/4*(1+$AA$7),0) -> 0 | AC21: =IFERROR($Z21/4*(1+$AA$7),0) -> 0 | AD21: =IFERROR($Z21/4*(1+$AA$7),0) -> 0 | AE21: =SUM(AA21:AD21) -> 0 | AF21: =IFERROR($AE21/4*(1+$AF$7),0) -> 0 | AG21: =IFERROR($AE21/4*(1+$AF$7),0) -> 0 | AH21: =IFERROR($AE21/4*(1+$AF$7),0) -> 0 | AI21: =IFERROR($AE21/4*(1+$AF$7),0) -> 0 | AJ21: =SUM(AF21:AI21) -> 0 | AK21: =IFERROR($AJ21/4*(1+$AK$7),0) -> 0 | AL21: =IFERROR($AJ21/4*(1+$AK$7),0) -> 0 | AM21: =IFERROR($AJ21/4*(1+$AK$7),0) -> 0 | AN21: =IFERROR($AJ21/4*(1+$AK$7),0) -> 0 | AO21: =SUM(AK21:AN21) -> 0 | AP21: =IFERROR($AO21/4*(1+$AP$7),0) -> 0 | AQ21: =IFERROR($AO21/4*(1+$AP$7),0) -> 0 | AR21: =IFERROR($AO21/4*(1+$AP$7),0) -> 0 | AS21: =IFERROR($AO21/4*(1+$AP$7),0) -> 0 | AT21: =SUM(AP21:AS21) -> 0 | AU21: =IFERROR($AT21/4*(1+$AU$7),0) -> 0 | AV21: =IFERROR($AT21/4*(1+$AU$7),0) -> 0 | AW21: =IFERROR($AT21/4*(1+$AU$7),0) -> 0 | AX21: =IFERROR($AT21/4*(1+$AU$7),0) -> 0 | AY21: =SUM(AU21:AX21) -> 0 | AZ21: =IFERROR($AY21/4*(1+$AZ$7),0) -> 0 | BA21: =IFERROR($AY21/4*(1+$AZ$7),0) -> 0 | BB21: =IFERROR($AY21/4*(1+$AZ$7),0) -> 0 | BC21: =IFERROR($AY21/4*(1+$AZ$7),0) -> 0 | BD21: =SUM(AZ21:BC21) -> 0 | BE21: =IFERROR($BD21/4*(1+$BE$7),0) -> 0 | BF21: =IFERROR($BD21/4*(1+$BE$7),0) -> 0 | BG21: =IFERROR($BD21/4*(1+$BE$7),0) -> 0 | BH21: =IFERROR($BD21/4*(1+$BE$7),0) -> 0 | BI21: =SUM(BE21:BH21) -> 0 | BJ21: =IFERROR($BI21/4*(1+$BJ$7),0) -> 0 | BK21: =IFERROR($BI21/4*(1+$BJ$7),0) -> 0 | BL21: =IFERROR($BI21/4*(1+$BJ$7),0) -> 0 | BM21: =IFERROR($BI21/4*(1+$BJ$7),0) -> 0 | BN21: =SUM(BJ21:BM21) -> 0
A22: ='Customer''s Questionnaire'!H55 -> 0 | B22: ='Customer''s Questionnaire'!I55 -> 0 | C22: ='Customer''s Questionnaire'!J55 -> 0 | D22: ='Customer''s Questionnaire'!K55 -> 0 | E22: ='Customer''s Questionnaire'!L55 -> 0 | G22: ='Customer''s Questionnaire'!O55 -> 0 | H22: ='Customer''s Questionnaire'!P55 -> 0 | I22: ='Customer''s Questionnaire'!Q55 -> 0 | J22: ='Customer''s Questionnaire'!R55 -> 0 | K22: =SUM(G22:J22) -> 0 | L22: =IFERROR('Customer''s Questionnaire'!$S55/4,"Add if needed") -> 0 | M22: =IFERROR('Customer''s Questionnaire'!$S55/4,"Add if needed") -> 0 | N22: =IFERROR('Customer''s Questionnaire'!$S55/4,"Add if needed") -> 0 | O22: =IFERROR('Customer''s Questionnaire'!$S55/4,"Add if needed") -> 0 | P22: =SUM(L22:O22) -> 0 | Q22: =IFERROR($P22/4*(1+$Q$7),0) -> 0 | R22: =IFERROR($P22/4*(1+$Q$7),0) -> 0 | S22: =IFERROR($P22/4*(1+$Q$7),0) -> 0 | T22: =IFERROR($P22/4*(1+$Q$7),0) -> 0 | U22: =SUM(Q22:T22) -> 0 | V22: =IFERROR($U22/4*(1+$V$7),0) -> 0 | W22: =IFERROR($U22/4*(1+$V$7),0) -> 0 | X22: =IFERROR($U22/4*(1+$V$7),0) -> 0 | Y22: =IFERROR($U22/4*(1+$V$7),0) -> 0 | Z22: =SUM(V22:Y22) -> 0 | AA22: =IFERROR($Z22/4*(1+$AA$7),0) -> 0 | AB22: =IFERROR($Z22/4*(1+$AA$7),0) -> 0 | AC22: =IFERROR($Z22/4*(1+$AA$7),0) -> 0 | AD22: =IFERROR($Z22/4*(1+$AA$7),0) -> 0 | AE22: =SUM(AA22:AD22) -> 0 | AF22: =IFERROR($AE22/4*(1+$AF$7),0) -> 0 | AG22: =IFERROR($AE22/4*(1+$AF$7),0) -> 0 | AH22: =IFERROR($AE22/4*(1+$AF$7),0) -> 0 | AI22: =IFERROR($AE22/4*(1+$AF$7),0) -> 0 | AJ22: =SUM(AF22:AI22) -> 0 | AK22: =IFERROR($AJ22/4*(1+$AK$7),0) -> 0 | AL22: =IFERROR($AJ22/4*(1+$AK$7),0) -> 0 | AM22: =IFERROR($AJ22/4*(1+$AK$7),0) -> 0 | AN22: =IFERROR($AJ22/4*(1+$AK$7),0) -> 0 | AO22: =SUM(AK22:AN22) -> 0 | AP22: =IFERROR($AO22/4*(1+$AP$7),0) -> 0 | AQ22: =IFERROR($AO22/4*(1+$AP$7),0) -> 0 | AR22: =IFERROR($AO22/4*(1+$AP$7),0) -> 0 | AS22: =IFERROR($AO22/4*(1+$AP$7),0) -> 0 | AT22: =SUM(AP22:AS22) -> 0 | AU22: =IFERROR($AT22/4*(1+$AU$7),0) -> 0 | AV22: =IFERROR($AT22/4*(1+$AU$7),0) -> 0 | AW22: =IFERROR($AT22/4*(1+$AU$7),0) -> 0 | AX22: =IFERROR($AT22/4*(1+$AU$7),0) -> 0 | AY22: =SUM(AU22:AX22) -> 0 | AZ22: =IFERROR($AY22/4*(1+$AZ$7),0) -> 0 | BA22: =IFERROR($AY22/4*(1+$AZ$7),0) -> 0 | BB22: =IFERROR($AY22/4*(1+$AZ$7),0) -> 0 | BC22: =IFERROR($AY22/4*(1+$AZ$7),0) -> 0 | BD22: =SUM(AZ22:BC22) -> 0 | BE22: =IFERROR($BD22/4*(1+$BE$7),0) -> 0 | BF22: =IFERROR($BD22/4*(1+$BE$7),0) -> 0 | BG22: =IFERROR($BD22/4*(1+$BE$7),0) -> 0 | BH22: =IFERROR($BD22/4*(1+$BE$7),0) -> 0 | BI22: =SUM(BE22:BH22) -> 0 | BJ22: =IFERROR($BI22/4*(1+$BJ$7),0) -> 0 | BK22: =IFERROR($BI22/4*(1+$BJ$7),0) -> 0 | BL22: =IFERROR($BI22/4*(1+$BJ$7),0) -> 0 | BM22: =IFERROR($BI22/4*(1+$BJ$7),0) -> 0 | BN22: =SUM(BJ22:BM22) -> 0
... A30: ='Customer''s Questionnaire'!H63 -> 0 | B30: ='Customer''s Questionnaire'!I63 -> 0 | C30: ='Customer''s Questionnaire'!J63 -> 0 | D30: ='Customer''s Questionnaire'!K63 -> 0 | E30: ='Customer''s Questionnaire'!L63 -> 0 | G30: ='Customer''s Questionnaire'!O63 -> 0 | H30: ='Customer''s Questionnaire'!P63 -> 0 | I30: ='Customer''s Questionnaire'!Q63 -> 0 | J30: ='Customer''s Questionnaire'!R63 -> 0 | K30: =SUM(G30:J30) -> 0 | L30: =IFERROR('Customer''s Questionnaire'!$S63/4,"Add if needed") -> 0 | M30: =IFERROR('Customer''s Questionnaire'!$S63/4,"Add if needed") -> 0 | N30: =IFERROR('Customer''s Questionnaire'!$S63/4,"Add if needed") -> 0 | O30: =IFERROR('Customer''s Questionnaire'!$S63/4,"Add if needed") -> 0 | P30: =SUM(L30:O30) -> 0 | Q30: =IFERROR($P30/4*(1+$Q$7),0) -> 0 | R30: =IFERROR($P30/4*(1+$Q$7),0) -> 0 | S30: =IFERROR($P30/4*(1+$Q$7),0) -> 0 | T30: =IFERROR($P30/4*(1+$Q$7),0) -> 0 | U30: =SUM(Q30:T30) -> 0 | V30: =IFERROR($U30/4*(1+$V$7),0) -> 0 | W30: =IFERROR($U30/4*(1+$V$7),0) -> 0 | X30: =IFERROR($U30/4*(1+$V$7),0) -> 0 | Y30: =IFERROR($U30/4*(1+$V$7),0) -> 0 | Z30: =SUM(V30:Y30) -> 0 | AA30: =IFERROR($Z30/4*(1+$AA$7),0) -> 0 | AB30: =IFERROR($Z30/4*(1+$AA$7),0) -> 0 | AC30: =IFERROR($Z30/4*(1+$AA$7),0) -> 0 | AD30: =IFERROR($Z30/4*(1+$AA$7),0) -> 0 | AE30: =SUM(AA30:AD30) -> 0 | AF30: =IFERROR($AE30/4*(1+$AF$7),0) -> 0 | AG30: =IFERROR($AE30/4*(1+$AF$7),0) -> 0 | AH30: =IFERROR($AE30/4*(1+$AF$7),0) -> 0 | AI30: =IFERROR($AE30/4*(1+$AF$7),0) -> 0 | AJ30: =SUM(AF30:AI30) -> 0 | AK30: =IFERROR($AJ30/4*(1+$AK$7),0) -> 0 | AL30: =IFERROR($AJ30/4*(1+$AK$7),0) -> 0 | AM30: =IFERROR($AJ30/4*(1+$AK$7),0) -> 0 | AN30: =IFERROR($AJ30/4*(1+$AK$7),0) -> 0 | AO30: =SUM(AK30:AN30) -> 0 | AP30: =IFERROR($AO30/4*(1+$AP$7),0) -> 0 | AQ30: =IFERROR($AO30/4*(1+$AP$7),0) -> 0 | AR30: =IFERROR($AO30/4*(1+$AP$7),0) -> 0 | AS30: =IFERROR($AO30/4*(1+$AP$7),0) -> 0 | AT30: =SUM(AP30:AS30) -> 0 | AU30: =IFERROR($AT30/4*(1+$AU$7),0) -> 0 | AV30: =IFERROR($AT30/4*(1+$AU$7),0) -> 0 | AW30: =IFERROR($AT30/4*(1+$AU$7),0) -> 0 | AX30: =IFERROR($AT30/4*(1+$AU$7),0) -> 0 | AY30: =SUM(AU30:AX30) -> 0 | AZ30: =IFERROR($AY30/4*(1+$AZ$7),0) -> 0 | BA30: =IFERROR($AY30/4*(1+$AZ$7),0) -> 0 | BB30: =IFERROR($AY30/4*(1+$AZ$7),0) -> 0 | BC30: =IFERROR($AY30/4*(1+$AZ$7),0) -> 0 | BD30: =SUM(AZ30:BC30) -> 0 | BE30: =IFERROR($BD30/4*(1+$BE$7),0) -> 0 | BF30: =IFERROR($BD30/4*(1+$BE$7),0) -> 0 | BG30: =IFERROR($BD30/4*(1+$BE$7),0) -> 0 | BH30: =IFERROR($BD30/4*(1+$BE$7),0) -> 0 | BI30: =SUM(BE30:BH30) -> 0 | BJ30: =IFERROR($BI30/4*(1+$BJ$7),0) -> 0 | BK30: =IFERROR($BI30/4*(1+$BJ$7),0) -> 0 | BL30: =IFERROR($BI30/4*(1+$BJ$7),0) -> 0 | BM30: =IFERROR($BI30/4*(1+$BJ$7),0) -> 0 | BN30: =SUM(BJ30:BM30) -> 0
A31: Total | B31: Total | E31: Total | G31: =SUM(G11:G30) -> 1010 | H31: =SUM(H11:H30) -> 1010 | I31: =SUM(I11:I30) -> 1010 | J31: =SUM(J11:J30) -> 1010 | K31: =SUM(K11:K30) -> 4040 | L31: =SUM(L11:L30) -> 1262.5 | M31: =SUM(M11:M30) -> 1262.5 | N31: =SUM(N11:N30) -> 1262.5 | ... BN31: =SUM(BN11:BN30) -> 26068.61
G32: Rev. | H32: Rev. | I32: Rev. | J32: Rev. | L32: Rev. | M32: Rev. | N32: Rev. | O32: Rev. | Q32: Rev. | R32: Rev. | S32: Rev. | T32: Rev. | V32: Rev. | W32: Rev. | X32: Rev. | Y32: Rev. | AA32: Rev. | AB32: Rev. | AC32: Rev. | AD32: Rev. | AF32: Rev. | AG32: Rev. | AH32: Rev. | AI32: Rev. | AK32: Rev. | AL32: Rev. | AM32: Rev. | AN32: Rev. | AP32: Rev. | AQ32: Rev. | AR32: Rev. | AS32: Rev. | AU32: Rev. | AV32: Rev. | AW32: Rev. | AX32: Rev. | AZ32: Rev. | BA32: Rev. | BB32: Rev. | BC32: Rev. | BE32: Rev. | BF32: Rev. | BG32: Rev. | BH32: Rev. | BJ32: Rev. | BK32: Rev. | BL32: Rev. | BM32: Rev.
A33: =A10 -> Revenue Type | B33: =B10 -> Customer Name | C33: =C10 -> Type | D33: =D10 -> Territory | E33: =E10 -> Product Name | F33: Price | G33: =G10 -> Q1-2026 | H33: =H10 -> Q2-2026 | I33: =I10 -> Q3-2026 | J33: =J10 -> Q4-2026 | K33: =K10 -> 2026 | L33: =L10 -> Q1-2027 | M33: =M10 -> Q2-2027 | N33: =N10 -> Q3-2027 | ... BN33: =BN10 -> 2037
A34: =A11 -> Hardware | B34: =B11 -> Hungry AF | C34: =C11 -> B2C | D34: =D11 -> US | E34: =E11 -> Big MAC | F34: ='Customer''s Questionnaire'!M44 -> 1000 | G34: =IFERROR(G11*$F34,0) -> 10000 | H34: =IFERROR(H11*$F34,0) -> 10000 | I34: =IFERROR(I11*$F34,0) -> 10000 | J34: =IFERROR(J11*$F34,0) -> 10000 | K34: =SUM(G34:J34) -> 40000 | L34: =IFERROR(L11*$F34,0) -> 12500 | M34: =IFERROR(M11*$F34,0) -> 12500 | N34: =IFERROR(N11*$F34,0) -> 12500 | O34: =IFERROR(O11*$F34,0) -> 12500 | P34: =SUM(L34:O34) -> 50000 | Q34: =IFERROR(Q11*$F34,0) -> 16875 | R34: =IFERROR(R11*$F34,0) -> 16875 | S34: =IFERROR(S11*$F34,0) -> 16875 | T34: =IFERROR(T11*$F34,0) -> 16875 | U34: =SUM(Q34:T34) -> 67500 | V34: =IFERROR(V11*$F34,0) -> 21093.75 | W34: =IFERROR(W11*$F34,0) -> 21093.75 | X34: =IFERROR(X11*$F34,0) -> 21093.75 | Y34: =IFERROR(Y11*$F34,0) -> 21093.75 | Z34: =SUM(V34:Y34) -> 84375 | AA34: =IFERROR(AA11*$F34,0) -> 24257.812 | AB34: =IFERROR(AB11*$F34,0) -> 24257.812 | AC34: =IFERROR(AC11*$F34,0) -> 24257.812 | AD34: =IFERROR(AD11*$F34,0) -> 24257.812 | AE34: =SUM(AA34:AD34) -> 97031.25 | AF34: =IFERROR(AF11*$F34,0) -> 27896.484 | AG34: =IFERROR(AG11*$F34,0) -> 27896.484 | AH34: =IFERROR(AH11*$F34,0) -> 27896.484 | AI34: =IFERROR(AI11*$F34,0) -> 27896.484 | AJ34: =SUM(AF34:AI34) -> 111585.94 | AK34: =IFERROR(AK11*$F34,0) -> 32080.957 | AL34: =IFERROR(AL11*$F34,0) -> 32080.957 | AM34: =IFERROR(AM11*$F34,0) -> 32080.957 | AN34: =IFERROR(AN11*$F34,0) -> 32080.957 | AO34: =SUM(AK34:AN34) -> 128323.83 | AP34: =IFERROR(AP11*$F34,0) -> 36893.101 | AQ34: =IFERROR(AQ11*$F34,0) -> 36893.101 | AR34: =IFERROR(AR11*$F34,0) -> 36893.101 | AS34: =IFERROR(AS11*$F34,0) -> 36893.101 | AT34: =SUM(AP34:AS34) -> 147572.4 | AU34: =IFERROR(AU11*$F34,0) -> 42427.066 | AV34: =IFERROR(AV11*$F34,0) -> 42427.066 | AW34: =IFERROR(AW11*$F34,0) -> 42427.066 | AX34: =IFERROR(AX11*$F34,0) -> 42427.066 | AY34: =SUM(AU34:AX34) -> 169708.26 | AZ34: =IFERROR(AZ11*$F34,0) -> 48791.126 | BA34: =IFERROR(BA11*$F34,0) -> 48791.126 | BB34: =IFERROR(BB11*$F34,0) -> 48791.126 | BC34: =IFERROR(BC11*$F34,0) -> 48791.126 | BD34: =SUM(AZ34:BC34) -> 195164.5 | BE34: =IFERROR(BE11*$F34,0) -> 56109.794 | BF34: =IFERROR(BF11*$F34,0) -> 56109.794 | BG34: =IFERROR(BG11*$F34,0) -> 56109.794 | BH34: =IFERROR(BH11*$F34,0) -> 56109.794 | BI34: =SUM(BE34:BH34) -> 224439.18 | BJ34: =IFERROR(BJ11*$F34,0) -> 64526.264 | BK34: =IFERROR(BK11*$F34,0) -> 64526.264 | BL34: =IFERROR(BL11*$F34,0) -> 64526.264 | BM34: =IFERROR(BM11*$F34,0) -> 64526.264 | BN34: =SUM(BJ34:BM34) -> 258105.05
A35: =A12 -> Software / SaaS | B35: =B12 -> BULO | C35: =C12 -> Direct | D35: =D12 -> EU | E35: =E12 -> MCMC | F35: ='Customer''s Questionnaire'!M45 -> 10 | G35: =IFERROR(G12*$F35,0) -> 10000 | H35: =IFERROR(H12*$F35,0) -> 10000 | I35: =IFERROR(I12*$F35,0) -> 10000 | J35: =IFERROR(J12*$F35,0) -> 10000 | K35: =SUM(G35:J35) -> 40000 | L35: =IFERROR(L12*$F35,0) -> 12500 | M35: =IFERROR(M12*$F35,0) -> 12500 | N35: =IFERROR(N12*$F35,0) -> 12500 | O35: =IFERROR(O12*$F35,0) -> 12500 | P35: =SUM(L35:O35) -> 50000 | Q35: =IFERROR(Q12*$F35,0) -> 16875 | R35: =IFERROR(R12*$F35,0) -> 16875 | S35: =IFERROR(S12*$F35,0) -> 16875 | T35: =IFERROR(T12*$F35,0) -> 16875 | U35: =SUM(Q35:T35) -> 67500 | V35: =IFERROR(V12*$F35,0) -> 21093.75 | W35: =IFERROR(W12*$F35,0) -> 21093.75 | X35: =IFERROR(X12*$F35,0) -> 21093.75 | Y35: =IFERROR(Y12*$F35,0) -> 21093.75 | Z35: =SUM(V35:Y35) -> 84375 | AA35: =IFERROR(AA12*$F35,0) -> 24257.812 | AB35: =IFERROR(AB12*$F35,0) -> 24257.812 | AC35: =IFERROR(AC12*$F35,0) -> 24257.812 | AD35: =IFERROR(AD12*$F35,0) -> 24257.812 | AE35: =SUM(AA35:AD35) -> 97031.25 | AF35: =IFERROR(AF12*$F35,0) -> 27896.484 | AG35: =IFERROR(AG12*$F35,0) -> 27896.484 | AH35: =IFERROR(AH12*$F35,0) -> 27896.484 | AI35: =IFERROR(AI12*$F35,0) -> 27896.484 | AJ35: =SUM(AF35:AI35) -> 111585.94 | AK35: =IFERROR(AK12*$F35,0) -> 32080.957 | AL35: =IFERROR(AL12*$F35,0) -> 32080.957 | AM35: =IFERROR(AM12*$F35,0) -> 32080.957 | AN35: =IFERROR(AN12*$F35,0) -> 32080.957 | AO35: =SUM(AK35:AN35) -> 128323.83 | AP35: =IFERROR(AP12*$F35,0) -> 36893.101 | AQ35: =IFERROR(AQ12*$F35,0) -> 36893.101 | AR35: =IFERROR(AR12*$F35,0) -> 36893.101 | AS35: =IFERROR(AS12*$F35,0) -> 36893.101 | AT35: =SUM(AP35:AS35) -> 147572.4 | AU35: =IFERROR(AU12*$F35,0) -> 42427.066 | AV35: =IFERROR(AV12*$F35,0) -> 42427.066 | AW35: =IFERROR(AW12*$F35,0) -> 42427.066 | AX35: =IFERROR(AX12*$F35,0) -> 42427.066 | AY35: =SUM(AU35:AX35) -> 169708.26 | AZ35: =IFERROR(AZ12*$F35,0) -> 48791.126 | BA35: =IFERROR(BA12*$F35,0) -> 48791.126 | BB35: =IFERROR(BB12*$F35,0) -> 48791.126 | BC35: =IFERROR(BC12*$F35,0) -> 48791.126 | BD35: =SUM(AZ35:BC35) -> 195164.5 | BE35: =IFERROR(BE12*$F35,0) -> 56109.794 | BF35: =IFERROR(BF12*$F35,0) -> 56109.794 | BG35: =IFERROR(BG12*$F35,0) -> 56109.794 | BH35: =IFERROR(BH12*$F35,0) -> 56109.794 | BI35: =SUM(BE35:BH35) -> 224439.18 | BJ35: =IFERROR(BJ12*$F35,0) -> 64526.264 | BK35: =IFERROR(BK12*$F35,0) -> 64526.264 | BL35: =IFERROR(BL12*$F35,0) -> 64526.264 | BM35: =IFERROR(BM12*$F35,0) -> 64526.264 | BN35: =SUM(BJ35:BM35) -> 258105.05
A36: =A13 -> 0 | B36: =B13 -> 0 | C36: =C13 -> 0 | D36: =D13 -> 0 | E36: =E13 -> 0 | F36: ='Customer''s Questionnaire'!M46 -> 0 | G36: =IFERROR(G13*$F36,0) -> 0 | H36: =IFERROR(H13*$F36,0) -> 0 | I36: =IFERROR(I13*$F36,0) -> 0 | J36: =IFERROR(J13*$F36,0) -> 0 | K36: =SUM(G36:J36) -> 0 | L36: =IFERROR(L13*$F36,0) -> 0 | M36: =IFERROR(M13*$F36,0) -> 0 | N36: =IFERROR(N13*$F36,0) -> 0 | O36: =IFERROR(O13*$F36,0) -> 0 | P36: =SUM(L36:O36) -> 0 | Q36: =IFERROR(Q13*$F36,0) -> 0 | R36: =IFERROR(R13*$F36,0) -> 0 | S36: =IFERROR(S13*$F36,0) -> 0 | T36: =IFERROR(T13*$F36,0) -> 0 | U36: =SUM(Q36:T36) -> 0 | V36: =IFERROR(V13*$F36,0) -> 0 | W36: =IFERROR(W13*$F36,0) -> 0 | X36: =IFERROR(X13*$F36,0) -> 0 | Y36: =IFERROR(Y13*$F36,0) -> 0 | Z36: =SUM(V36:Y36) -> 0 | AA36: =IFERROR(AA13*$F36,0) -> 0 | AB36: =IFERROR(AB13*$F36,0) -> 0 | AC36: =IFERROR(AC13*$F36,0) -> 0 | AD36: =IFERROR(AD13*$F36,0) -> 0 | AE36: =SUM(AA36:AD36) -> 0 | AF36: =IFERROR(AF13*$F36,0) -> 0 | AG36: =IFERROR(AG13*$F36,0) -> 0 | AH36: =IFERROR(AH13*$F36,0) -> 0 | AI36: =IFERROR(AI13*$F36,0) -> 0 | AJ36: =SUM(AF36:AI36) -> 0 | AK36: =IFERROR(AK13*$F36,0) -> 0 | AL36: =IFERROR(AL13*$F36,0) -> 0 | AM36: =IFERROR(AM13*$F36,0) -> 0 | AN36: =IFERROR(AN13*$F36,0) -> 0 | AO36: =SUM(AK36:AN36) -> 0 | AP36: =IFERROR(AP13*$F36,0) -> 0 | AQ36: =IFERROR(AQ13*$F36,0) -> 0 | AR36: =IFERROR(AR13*$F36,0) -> 0 | AS36: =IFERROR(AS13*$F36,0) -> 0 | AT36: =SUM(AP36:AS36) -> 0 | AU36: =IFERROR(AU13*$F36,0) -> 0 | AV36: =IFERROR(AV13*$F36,0) -> 0 | AW36: =IFERROR(AW13*$F36,0) -> 0 | AX36: =IFERROR(AX13*$F36,0) -> 0 | AY36: =SUM(AU36:AX36) -> 0 | AZ36: =IFERROR(AZ13*$F36,0) -> 0 | BA36: =IFERROR(BA13*$F36,0) -> 0 | BB36: =IFERROR(BB13*$F36,0) -> 0 | BC36: =IFERROR(BC13*$F36,0) -> 0 | BD36: =SUM(AZ36:BC36) -> 0 | BE36: =IFERROR(BE13*$F36,0) -> 0 | BF36: =IFERROR(BF13*$F36,0) -> 0 | BG36: =IFERROR(BG13*$F36,0) -> 0 | BH36: =IFERROR(BH13*$F36,0) -> 0 | BI36: =SUM(BE36:BH36) -> 0 | BJ36: =IFERROR(BJ13*$F36,0) -> 0 | BK36: =IFERROR(BK13*$F36,0) -> 0 | BL36: =IFERROR(BL13*$F36,0) -> 0 | BM36: =IFERROR(BM13*$F36,0) -> 0 | BN36: =SUM(BJ36:BM36) -> 0
A37: =A14 -> 0 | B37: =B14 -> 0 | C37: =C14 -> 0 | D37: =D14 -> 0 | E37: =E14 -> 0 | F37: ='Customer''s Questionnaire'!M47 -> 0 | G37: =IFERROR(G14*$F37,0) -> 0 | H37: =IFERROR(H14*$F37,0) -> 0 | I37: =IFERROR(I14*$F37,0) -> 0 | J37: =IFERROR(J14*$F37,0) -> 0 | K37: =SUM(G37:J37) -> 0 | L37: =IFERROR(L14*$F37,0) -> 0 | M37: =IFERROR(M14*$F37,0) -> 0 | N37: =IFERROR(N14*$F37,0) -> 0 | O37: =IFERROR(O14*$F37,0) -> 0 | P37: =SUM(L37:O37) -> 0 | Q37: =IFERROR(Q14*$F37,0) -> 0 | R37: =IFERROR(R14*$F37,0) -> 0 | S37: =IFERROR(S14*$F37,0) -> 0 | T37: =IFERROR(T14*$F37,0) -> 0 | U37: =SUM(Q37:T37) -> 0 | V37: =IFERROR(V14*$F37,0) -> 0 | W37: =IFERROR(W14*$F37,0) -> 0 | X37: =IFERROR(X14*$F37,0) -> 0 | Y37: =IFERROR(Y14*$F37,0) -> 0 | Z37: =SUM(V37:Y37) -> 0 | AA37: =IFERROR(AA14*$F37,0) -> 0 | AB37: =IFERROR(AB14*$F37,0) -> 0 | AC37: =IFERROR(AC14*$F37,0) -> 0 | AD37: =IFERROR(AD14*$F37,0) -> 0 | AE37: =SUM(AA37:AD37) -> 0 | AF37: =IFERROR(AF14*$F37,0) -> 0 | AG37: =IFERROR(AG14*$F37,0) -> 0 | AH37: =IFERROR(AH14*$F37,0) -> 0 | AI37: =IFERROR(AI14*$F37,0) -> 0 | AJ37: =SUM(AF37:AI37) -> 0 | AK37: =IFERROR(AK14*$F37,0) -> 0 | AL37: =IFERROR(AL14*$F37,0) -> 0 | AM37: =IFERROR(AM14*$F37,0) -> 0 | AN37: =IFERROR(AN14*$F37,0) -> 0 | AO37: =SUM(AK37:AN37) -> 0 | AP37: =IFERROR(AP14*$F37,0) -> 0 | AQ37: =IFERROR(AQ14*$F37,0) -> 0 | AR37: =IFERROR(AR14*$F37,0) -> 0 | AS37: =IFERROR(AS14*$F37,0) -> 0 | AT37: =SUM(AP37:AS37) -> 0 | AU37: =IFERROR(AU14*$F37,0) -> 0 | AV37: =IFERROR(AV14*$F37,0) -> 0 | AW37: =IFERROR(AW14*$F37,0) -> 0 | AX37: =IFERROR(AX14*$F37,0) -> 0 | AY37: =SUM(AU37:AX37) -> 0 | AZ37: =IFERROR(AZ14*$F37,0) -> 0 | BA37: =IFERROR(BA14*$F37,0) -> 0 | BB37: =IFERROR(BB14*$F37,0) -> 0 | BC37: =IFERROR(BC14*$F37,0) -> 0 | BD37: =SUM(AZ37:BC37) -> 0 | BE37: =IFERROR(BE14*$F37,0) -> 0 | BF37: =IFERROR(BF14*$F37,0) -> 0 | BG37: =IFERROR(BG14*$F37,0) -> 0 | BH37: =IFERROR(BH14*$F37,0) -> 0 | BI37: =SUM(BE37:BH37) -> 0 | BJ37: =IFERROR(BJ14*$F37,0) -> 0 | BK37: =IFERROR(BK14*$F37,0) -> 0 | BL37: =IFERROR(BL14*$F37,0) -> 0 | BM37: =IFERROR(BM14*$F37,0) -> 0 | BN37: =SUM(BJ37:BM37) -> 0
A38: =A15 -> 0 | B38: =B15 -> 0 | C38: =C15 -> 0 | D38: =D15 -> 0 | E38: =E15 -> 0 | F38: ='Customer''s Questionnaire'!M48 -> 0 | G38: =IFERROR(G15*$F38,0) -> 0 | H38: =IFERROR(H15*$F38,0) -> 0 | I38: =IFERROR(I15*$F38,0) -> 0 | J38: =IFERROR(J15*$F38,0) -> 0 | K38: =SUM(G38:J38) -> 0 | L38: =IFERROR(L15*$F38,0) -> 0 | M38: =IFERROR(M15*$F38,0) -> 0 | N38: =IFERROR(N15*$F38,0) -> 0 | O38: =IFERROR(O15*$F38,0) -> 0 | P38: =SUM(L38:O38) -> 0 | Q38: =IFERROR(Q15*$F38,0) -> 0 | R38: =IFERROR(R15*$F38,0) -> 0 | S38: =IFERROR(S15*$F38,0) -> 0 | T38: =IFERROR(T15*$F38,0) -> 0 | U38: =SUM(Q38:T38) -> 0 | V38: =IFERROR(V15*$F38,0) -> 0 | W38: =IFERROR(W15*$F38,0) -> 0 | X38: =IFERROR(X15*$F38,0) -> 0 | Y38: =IFERROR(Y15*$F38,0) -> 0 | Z38: =SUM(V38:Y38) -> 0 | AA38: =IFERROR(AA15*$F38,0) -> 0 | AB38: =IFERROR(AB15*$F38,0) -> 0 | AC38: =IFERROR(AC15*$F38,0) -> 0 | AD38: =IFERROR(AD15*$F38,0) -> 0 | AE38: =SUM(AA38:AD38) -> 0 | AF38: =IFERROR(AF15*$F38,0) -> 0 | AG38: =IFERROR(AG15*$F38,0) -> 0 | AH38: =IFERROR(AH15*$F38,0) -> 0 | AI38: =IFERROR(AI15*$F38,0) -> 0 | AJ38: =SUM(AF38:AI38) -> 0 | AK38: =IFERROR(AK15*$F38,0) -> 0 | AL38: =IFERROR(AL15*$F38,0) -> 0 | AM38: =IFERROR(AM15*$F38,0) -> 0 | AN38: =IFERROR(AN15*$F38,0) -> 0 | AO38: =SUM(AK38:AN38) -> 0 | AP38: =IFERROR(AP15*$F38,0) -> 0 | AQ38: =IFERROR(AQ15*$F38,0) -> 0 | AR38: =IFERROR(AR15*$F38,0) -> 0 | AS38: =IFERROR(AS15*$F38,0) -> 0 | AT38: =SUM(AP38:AS38) -> 0 | AU38: =IFERROR(AU15*$F38,0) -> 0 | AV38: =IFERROR(AV15*$F38,0) -> 0 | AW38: =IFERROR(AW15*$F38,0) -> 0 | AX38: =IFERROR(AX15*$F38,0) -> 0 | AY38: =SUM(AU38:AX38) -> 0 | AZ38: =IFERROR(AZ15*$F38,0) -> 0 | BA38: =IFERROR(BA15*$F38,0) -> 0 | BB38: =IFERROR(BB15*$F38,0) -> 0 | BC38: =IFERROR(BC15*$F38,0) -> 0 | BD38: =SUM(AZ38:BC38) -> 0 | BE38: =IFERROR(BE15*$F38,0) -> 0 | BF38: =IFERROR(BF15*$F38,0) -> 0 | BG38: =IFERROR(BG15*$F38,0) -> 0 | BH38: =IFERROR(BH15*$F38,0) -> 0 | BI38: =SUM(BE38:BH38) -> 0 | BJ38: =IFERROR(BJ15*$F38,0) -> 0 | BK38: =IFERROR(BK15*$F38,0) -> 0 | BL38: =IFERROR(BL15*$F38,0) -> 0 | BM38: =IFERROR(BM15*$F38,0) -> 0 | BN38: =SUM(BJ38:BM38) -> 0
A39: =A16 -> 0 | B39: =B16 -> 0 | C39: =C16 -> 0 | D39: =D16 -> 0 | E39: =E16 -> 0 | F39: ='Customer''s Questionnaire'!M49 -> 0 | G39: =IFERROR(G16*$F39,0) -> 0 | H39: =IFERROR(H16*$F39,0) -> 0 | I39: =IFERROR(I16*$F39,0) -> 0 | J39: =IFERROR(J16*$F39,0) -> 0 | K39: =SUM(G39:J39) -> 0 | L39: =IFERROR(L16*$F39,0) -> 0 | M39: =IFERROR(M16*$F39,0) -> 0 | N39: =IFERROR(N16*$F39,0) -> 0 | O39: =IFERROR(O16*$F39,0) -> 0 | P39: =SUM(L39:O39) -> 0 | Q39: =IFERROR(Q16*$F39,0) -> 0 | R39: =IFERROR(R16*$F39,0) -> 0 | S39: =IFERROR(S16*$F39,0) -> 0 | T39: =IFERROR(T16*$F39,0) -> 0 | U39: =SUM(Q39:T39) -> 0 | V39: =IFERROR(V16*$F39,0) -> 0 | W39: =IFERROR(W16*$F39,0) -> 0 | X39: =IFERROR(X16*$F39,0) -> 0 | Y39: =IFERROR(Y16*$F39,0) -> 0 | Z39: =SUM(V39:Y39) -> 0 | AA39: =IFERROR(AA16*$F39,0) -> 0 | AB39: =IFERROR(AB16*$F39,0) -> 0 | AC39: =IFERROR(AC16*$F39,0) -> 0 | AD39: =IFERROR(AD16*$F39,0) -> 0 | AE39: =SUM(AA39:AD39) -> 0 | AF39: =IFERROR(AF16*$F39,0) -> 0 | AG39: =IFERROR(AG16*$F39,0) -> 0 | AH39: =IFERROR(AH16*$F39,0) -> 0 | AI39: =IFERROR(AI16*$F39,0) -> 0 | AJ39: =SUM(AF39:AI39) -> 0 | AK39: =IFERROR(AK16*$F39,0) -> 0 | AL39: =IFERROR(AL16*$F39,0) -> 0 | AM39: =IFERROR(AM16*$F39,0) -> 0 | AN39: =IFERROR(AN16*$F39,0) -> 0 | AO39: =SUM(AK39:AN39) -> 0 | AP39: =IFERROR(AP16*$F39,0) -> 0 | AQ39: =IFERROR(AQ16*$F39,0) -> 0 | AR39: =IFERROR(AR16*$F39,0) -> 0 | AS39: =IFERROR(AS16*$F39,0) -> 0 | AT39: =SUM(AP39:AS39) -> 0 | AU39: =IFERROR(AU16*$F39,0) -> 0 | AV39: =IFERROR(AV16*$F39,0) -> 0 | AW39: =IFERROR(AW16*$F39,0) -> 0 | AX39: =IFERROR(AX16*$F39,0) -> 0 | AY39: =SUM(AU39:AX39) -> 0 | AZ39: =IFERROR(AZ16*$F39,0) -> 0 | BA39: =IFERROR(BA16*$F39,0) -> 0 | BB39: =IFERROR(BB16*$F39,0) -> 0 | BC39: =IFERROR(BC16*$F39,0) -> 0 | BD39: =SUM(AZ39:BC39) -> 0 | BE39: =IFERROR(BE16*$F39,0) -> 0 | BF39: =IFERROR(BF16*$F39,0) -> 0 | BG39: =IFERROR(BG16*$F39,0) -> 0 | BH39: =IFERROR(BH16*$F39,0) -> 0 | BI39: =SUM(BE39:BH39) -> 0 | BJ39: =IFERROR(BJ16*$F39,0) -> 0 | BK39: =IFERROR(BK16*$F39,0) -> 0 | BL39: =IFERROR(BL16*$F39,0) -> 0 | BM39: =IFERROR(BM16*$F39,0) -> 0 | BN39: =SUM(BJ39:BM39) -> 0
A40: =A17 -> 0 | B40: =B17 -> 0 | C40: =C17 -> 0 | D40: =D17 -> 0 | E40: =E17 -> 0 | F40: ='Customer''s Questionnaire'!M50 -> 0 | G40: =IFERROR(G17*$F40,0) -> 0 | H40: =IFERROR(H17*$F40,0) -> 0 | I40: =IFERROR(I17*$F40,0) -> 0 | J40: =IFERROR(J17*$F40,0) -> 0 | K40: =SUM(G40:J40) -> 0 | L40: =IFERROR(L17*$F40,0) -> 0 | M40: =IFERROR(M17*$F40,0) -> 0 | N40: =IFERROR(N17*$F40,0) -> 0 | O40: =IFERROR(O17*$F40,0) -> 0 | P40: =SUM(L40:O40) -> 0 | Q40: =IFERROR(Q17*$F40,0) -> 0 | R40: =IFERROR(R17*$F40,0) -> 0 | S40: =IFERROR(S17*$F40,0) -> 0 | T40: =IFERROR(T17*$F40,0) -> 0 | U40: =SUM(Q40:T40) -> 0 | V40: =IFERROR(V17*$F40,0) -> 0 | W40: =IFERROR(W17*$F40,0) -> 0 | X40: =IFERROR(X17*$F40,0) -> 0 | Y40: =IFERROR(Y17*$F40,0) -> 0 | Z40: =SUM(V40:Y40) -> 0 | AA40: =IFERROR(AA17*$F40,0) -> 0 | AB40: =IFERROR(AB17*$F40,0) -> 0 | AC40: =IFERROR(AC17*$F40,0) -> 0 | AD40: =IFERROR(AD17*$F40,0) -> 0 | AE40: =SUM(AA40:AD40) -> 0 | AF40: =IFERROR(AF17*$F40,0) -> 0 | AG40: =IFERROR(AG17*$F40,0) -> 0 | AH40: =IFERROR(AH17*$F40,0) -> 0 | AI40: =IFERROR(AI17*$F40,0) -> 0 | AJ40: =SUM(AF40:AI40) -> 0 | AK40: =IFERROR(AK17*$F40,0) -> 0 | AL40: =IFERROR(AL17*$F40,0) -> 0 | AM40: =IFERROR(AM17*$F40,0) -> 0 | AN40: =IFERROR(AN17*$F40,0) -> 0 | AO40: =SUM(AK40:AN40) -> 0 | AP40: =IFERROR(AP17*$F40,0) -> 0 | AQ40: =IFERROR(AQ17*$F40,0) -> 0 | AR40: =IFERROR(AR17*$F40,0) -> 0 | AS40: =IFERROR(AS17*$F40,0) -> 0 | AT40: =SUM(AP40:AS40) -> 0 | AU40: =IFERROR(AU17*$F40,0) -> 0 | AV40: =IFERROR(AV17*$F40,0) -> 0 | AW40: =IFERROR(AW17*$F40,0) -> 0 | AX40: =IFERROR(AX17*$F40,0) -> 0 | AY40: =SUM(AU40:AX40) -> 0 | AZ40: =IFERROR(AZ17*$F40,0) -> 0 | BA40: =IFERROR(BA17*$F40,0) -> 0 | BB40: =IFERROR(BB17*$F40,0) -> 0 | BC40: =IFERROR(BC17*$F40,0) -> 0 | BD40: =SUM(AZ40:BC40) -> 0 | BE40: =IFERROR(BE17*$F40,0) -> 0 | BF40: =IFERROR(BF17*$F40,0) -> 0 | BG40: =IFERROR(BG17*$F40,0) -> 0 | BH40: =IFERROR(BH17*$F40,0) -> 0 | BI40: =SUM(BE40:BH40) -> 0 | BJ40: =IFERROR(BJ17*$F40,0) -> 0 | BK40: =IFERROR(BK17*$F40,0) -> 0 | BL40: =IFERROR(BL17*$F40,0) -> 0 | BM40: =IFERROR(BM17*$F40,0) -> 0 | BN40: =SUM(BJ40:BM40) -> 0
A41: =A18 -> 0 | B41: =B18 -> 0 | C41: =C18 -> 0 | D41: =D18 -> 0 | E41: =E18 -> 0 | F41: ='Customer''s Questionnaire'!M51 -> 0 | G41: =IFERROR(G18*$F41,0) -> 0 | H41: =IFERROR(H18*$F41,0) -> 0 | I41: =IFERROR(I18*$F41,0) -> 0 | J41: =IFERROR(J18*$F41,0) -> 0 | K41: =SUM(G41:J41) -> 0 | L41: =IFERROR(L18*$F41,0) -> 0 | M41: =IFERROR(M18*$F41,0) -> 0 | N41: =IFERROR(N18*$F41,0) -> 0 | O41: =IFERROR(O18*$F41,0) -> 0 | P41: =SUM(L41:O41) -> 0 | Q41: =IFERROR(Q18*$F41,0) -> 0 | R41: =IFERROR(R18*$F41,0) -> 0 | S41: =IFERROR(S18*$F41,0) -> 0 | T41: =IFERROR(T18*$F41,0) -> 0 | U41: =SUM(Q41:T41) -> 0 | V41: =IFERROR(V18*$F41,0) -> 0 | W41: =IFERROR(W18*$F41,0) -> 0 | X41: =IFERROR(X18*$F41,0) -> 0 | Y41: =IFERROR(Y18*$F41,0) -> 0 | Z41: =SUM(V41:Y41) -> 0 | AA41: =IFERROR(AA18*$F41,0) -> 0 | AB41: =IFERROR(AB18*$F41,0) -> 0 | AC41: =IFERROR(AC18*$F41,0) -> 0 | AD41: =IFERROR(AD18*$F41,0) -> 0 | AE41: =SUM(AA41:AD41) -> 0 | AF41: =IFERROR(AF18*$F41,0) -> 0 | AG41: =IFERROR(AG18*$F41,0) -> 0 | AH41: =IFERROR(AH18*$F41,0) -> 0 | AI41: =IFERROR(AI18*$F41,0) -> 0 | AJ41: =SUM(AF41:AI41) -> 0 | AK41: =IFERROR(AK18*$F41,0) -> 0 | AL41: =IFERROR(AL18*$F41,0) -> 0 | AM41: =IFERROR(AM18*$F41,0) -> 0 | AN41: =IFERROR(AN18*$F41,0) -> 0 | AO41: =SUM(AK41:AN41) -> 0 | AP41: =IFERROR(AP18*$F41,0) -> 0 | AQ41: =IFERROR(AQ18*$F41,0) -> 0 | AR41: =IFERROR(AR18*$F41,0) -> 0 | AS41: =IFERROR(AS18*$F41,0) -> 0 | AT41: =SUM(AP41:AS41) -> 0 | AU41: =IFERROR(AU18*$F41,0) -> 0 | AV41: =IFERROR(AV18*$F41,0) -> 0 | AW41: =IFERROR(AW18*$F41,0) -> 0 | AX41: =IFERROR(AX18*$F41,0) -> 0 | AY41: =SUM(AU41:AX41) -> 0 | AZ41: =IFERROR(AZ18*$F41,0) -> 0 | BA41: =IFERROR(BA18*$F41,0) -> 0 | BB41: =IFERROR(BB18*$F41,0) -> 0 | BC41: =IFERROR(BC18*$F41,0) -> 0 | BD41: =SUM(AZ41:BC41) -> 0 | BE41: =IFERROR(BE18*$F41,0) -> 0 | BF41: =IFERROR(BF18*$F41,0) -> 0 | BG41: =IFERROR(BG18*$F41,0) -> 0 | BH41: =IFERROR(BH18*$F41,0) -> 0 | BI41: =SUM(BE41:BH41) -> 0 | BJ41: =IFERROR(BJ18*$F41,0) -> 0 | BK41: =IFERROR(BK18*$F41,0) -> 0 | BL41: =IFERROR(BL18*$F41,0) -> 0 | BM41: =IFERROR(BM18*$F41,0) -> 0 | BN41: =SUM(BJ41:BM41) -> 0
A42: =A19 -> 0 | B42: =B19 -> 0 | C42: =C19 -> 0 | D42: =D19 -> 0 | E42: =E19 -> 0 | F42: ='Customer''s Questionnaire'!M52 -> 0 | G42: =IFERROR(G19*$F42,0) -> 0 | H42: =IFERROR(H19*$F42,0) -> 0 | I42: =IFERROR(I19*$F42,0) -> 0 | J42: =IFERROR(J19*$F42,0) -> 0 | K42: =SUM(G42:J42) -> 0 | L42: =IFERROR(L19*$F42,0) -> 0 | M42: =IFERROR(M19*$F42,0) -> 0 | N42: =IFERROR(N19*$F42,0) -> 0 | O42: =IFERROR(O19*$F42,0) -> 0 | P42: =SUM(L42:O42) -> 0 | Q42: =IFERROR(Q19*$F42,0) -> 0 | R42: =IFERROR(R19*$F42,0) -> 0 | S42: =IFERROR(S19*$F42,0) -> 0 | T42: =IFERROR(T19*$F42,0) -> 0 | U42: =SUM(Q42:T42) -> 0 | V42: =IFERROR(V19*$F42,0) -> 0 | W42: =IFERROR(W19*$F42,0) -> 0 | X42: =IFERROR(X19*$F42,0) -> 0 | Y42: =IFERROR(Y19*$F42,0) -> 0 | Z42: =SUM(V42:Y42) -> 0 | AA42: =IFERROR(AA19*$F42,0) -> 0 | AB42: =IFERROR(AB19*$F42,0) -> 0 | AC42: =IFERROR(AC19*$F42,0) -> 0 | AD42: =IFERROR(AD19*$F42,0) -> 0 | AE42: =SUM(AA42:AD42) -> 0 | AF42: =IFERROR(AF19*$F42,0) -> 0 | AG42: =IFERROR(AG19*$F42,0) -> 0 | AH42: =IFERROR(AH19*$F42,0) -> 0 | AI42: =IFERROR(AI19*$F42,0) -> 0 | AJ42: =SUM(AF42:AI42) -> 0 | AK42: =IFERROR(AK19*$F42,0) -> 0 | AL42: =IFERROR(AL19*$F42,0) -> 0 | AM42: =IFERROR(AM19*$F42,0) -> 0 | AN42: =IFERROR(AN19*$F42,0) -> 0 | AO42: =SUM(AK42:AN42) -> 0 | AP42: =IFERROR(AP19*$F42,0) -> 0 | AQ42: =IFERROR(AQ19*$F42,0) -> 0 | AR42: =IFERROR(AR19*$F42,0) -> 0 | AS42: =IFERROR(AS19*$F42,0) -> 0 | AT42: =SUM(AP42:AS42) -> 0 | AU42: =IFERROR(AU19*$F42,0) -> 0 | AV42: =IFERROR(AV19*$F42,0) -> 0 | AW42: =IFERROR(AW19*$F42,0) -> 0 | AX42: =IFERROR(AX19*$F42,0) -> 0 | AY42: =SUM(AU42:AX42) -> 0 | AZ42: =IFERROR(AZ19*$F42,0) -> 0 | BA42: =IFERROR(BA19*$F42,0) -> 0 | BB42: =IFERROR(BB19*$F42,0) -> 0 | BC42: =IFERROR(BC19*$F42,0) -> 0 | BD42: =SUM(AZ42:BC42) -> 0 | BE42: =IFERROR(BE19*$F42,0) -> 0 | BF42: =IFERROR(BF19*$F42,0) -> 0 | BG42: =IFERROR(BG19*$F42,0) -> 0 | BH42: =IFERROR(BH19*$F42,0) -> 0 | BI42: =SUM(BE42:BH42) -> 0 | BJ42: =IFERROR(BJ19*$F42,0) -> 0 | BK42: =IFERROR(BK19*$F42,0) -> 0 | BL42: =IFERROR(BL19*$F42,0) -> 0 | BM42: =IFERROR(BM19*$F42,0) -> 0 | BN42: =SUM(BJ42:BM42) -> 0
A43: =A20 -> 0 | B43: =B20 -> 0 | C43: =C20 -> 0 | D43: =D20 -> 0 | E43: =E20 -> 0 | F43: ='Customer''s Questionnaire'!M53 -> 0 | G43: =IFERROR(G20*$F43,0) -> 0 | H43: =IFERROR(H20*$F43,0) -> 0 | I43: =IFERROR(I20*$F43,0) -> 0 | J43: =IFERROR(J20*$F43,0) -> 0 | K43: =SUM(G43:J43) -> 0 | L43: =IFERROR(L20*$F43,0) -> 0 | M43: =IFERROR(M20*$F43,0) -> 0 | N43: =IFERROR(N20*$F43,0) -> 0 | O43: =IFERROR(O20*$F43,0) -> 0 | P43: =SUM(L43:O43) -> 0 | Q43: =IFERROR(Q20*$F43,0) -> 0 | R43: =IFERROR(R20*$F43,0) -> 0 | S43: =IFERROR(S20*$F43,0) -> 0 | T43: =IFERROR(T20*$F43,0) -> 0 | U43: =SUM(Q43:T43) -> 0 | V43: =IFERROR(V20*$F43,0) -> 0 | W43: =IFERROR(W20*$F43,0) -> 0 | X43: =IFERROR(X20*$F43,0) -> 0 | Y43: =IFERROR(Y20*$F43,0) -> 0 | Z43: =SUM(V43:Y43) -> 0 | AA43: =IFERROR(AA20*$F43,0) -> 0 | AB43: =IFERROR(AB20*$F43,0) -> 0 | AC43: =IFERROR(AC20*$F43,0) -> 0 | AD43: =IFERROR(AD20*$F43,0) -> 0 | AE43: =SUM(AA43:AD43) -> 0 | AF43: =IFERROR(AF20*$F43,0) -> 0 | AG43: =IFERROR(AG20*$F43,0) -> 0 | AH43: =IFERROR(AH20*$F43,0) -> 0 | AI43: =IFERROR(AI20*$F43,0) -> 0 | AJ43: =SUM(AF43:AI43) -> 0 | AK43: =IFERROR(AK20*$F43,0) -> 0 | AL43: =IFERROR(AL20*$F43,0) -> 0 | AM43: =IFERROR(AM20*$F43,0) -> 0 | AN43: =IFERROR(AN20*$F43,0) -> 0 | AO43: =SUM(AK43:AN43) -> 0 | AP43: =IFERROR(AP20*$F43,0) -> 0 | AQ43: =IFERROR(AQ20*$F43,0) -> 0 | AR43: =IFERROR(AR20*$F43,0) -> 0 | AS43: =IFERROR(AS20*$F43,0) -> 0 | AT43: =SUM(AP43:AS43) -> 0 | AU43: =IFERROR(AU20*$F43,0) -> 0 | AV43: =IFERROR(AV20*$F43,0) -> 0 | AW43: =IFERROR(AW20*$F43,0) -> 0 | AX43: =IFERROR(AX20*$F43,0) -> 0 | AY43: =SUM(AU43:AX43) -> 0 | AZ43: =IFERROR(AZ20*$F43,0) -> 0 | BA43: =IFERROR(BA20*$F43,0) -> 0 | BB43: =IFERROR(BB20*$F43,0) -> 0 | BC43: =IFERROR(BC20*$F43,0) -> 0 | BD43: =SUM(AZ43:BC43) -> 0 | BE43: =IFERROR(BE20*$F43,0) -> 0 | BF43: =IFERROR(BF20*$F43,0) -> 0 | BG43: =IFERROR(BG20*$F43,0) -> 0 | BH43: =IFERROR(BH20*$F43,0) -> 0 | BI43: =SUM(BE43:BH43) -> 0 | BJ43: =IFERROR(BJ20*$F43,0) -> 0 | BK43: =IFERROR(BK20*$F43,0) -> 0 | BL43: =IFERROR(BL20*$F43,0) -> 0 | BM43: =IFERROR(BM20*$F43,0) -> 0 | BN43: =SUM(BJ43:BM43) -> 0
A44: =A21 -> 0 | B44: =B21 -> 0 | C44: =C21 -> 0 | D44: =D21 -> 0 | E44: =E21 -> 0 | F44: ='Customer''s Questionnaire'!M54 -> 0 | G44: =IFERROR(G21*$F44,0) -> 0 | H44: =IFERROR(H21*$F44,0) -> 0 | I44: =IFERROR(I21*$F44,0) -> 0 | J44: =IFERROR(J21*$F44,0) -> 0 | K44: =SUM(G44:J44) -> 0 | L44: =IFERROR(L21*$F44,0) -> 0 | M44: =IFERROR(M21*$F44,0) -> 0 | N44: =IFERROR(N21*$F44,0) -> 0 | O44: =IFERROR(O21*$F44,0) -> 0 | P44: =SUM(L44:O44) -> 0 | Q44: =IFERROR(Q21*$F44,0) -> 0 | R44: =IFERROR(R21*$F44,0) -> 0 | S44: =IFERROR(S21*$F44,0) -> 0 | T44: =IFERROR(T21*$F44,0) -> 0 | U44: =SUM(Q44:T44) -> 0 | V44: =IFERROR(V21*$F44,0) -> 0 | W44: =IFERROR(W21*$F44,0) -> 0 | X44: =IFERROR(X21*$F44,0) -> 0 | Y44: =IFERROR(Y21*$F44,0) -> 0 | Z44: =SUM(V44:Y44) -> 0 | AA44: =IFERROR(AA21*$F44,0) -> 0 | AB44: =IFERROR(AB21*$F44,0) -> 0 | AC44: =IFERROR(AC21*$F44,0) -> 0 | AD44: =IFERROR(AD21*$F44,0) -> 0 | AE44: =SUM(AA44:AD44) -> 0 | AF44: =IFERROR(AF21*$F44,0) -> 0 | AG44: =IFERROR(AG21*$F44,0) -> 0 | AH44: =IFERROR(AH21*$F44,0) -> 0 | AI44: =IFERROR(AI21*$F44,0) -> 0 | AJ44: =SUM(AF44:AI44) -> 0 | AK44: =IFERROR(AK21*$F44,0) -> 0 | AL44: =IFERROR(AL21*$F44,0) -> 0 | AM44: =IFERROR(AM21*$F44,0) -> 0 | AN44: =IFERROR(AN21*$F44,0) -> 0 | AO44: =SUM(AK44:AN44) -> 0 | AP44: =IFERROR(AP21*$F44,0) -> 0 | AQ44: =IFERROR(AQ21*$F44,0) -> 0 | AR44: =IFERROR(AR21*$F44,0) -> 0 | AS44: =IFERROR(AS21*$F44,0) -> 0 | AT44: =SUM(AP44:AS44) -> 0 | AU44: =IFERROR(AU21*$F44,0) -> 0 | AV44: =IFERROR(AV21*$F44,0) -> 0 | AW44: =IFERROR(AW21*$F44,0) -> 0 | AX44: =IFERROR(AX21*$F44,0) -> 0 | AY44: =SUM(AU44:AX44) -> 0 | AZ44: =IFERROR(AZ21*$F44,0) -> 0 | BA44: =IFERROR(BA21*$F44,0) -> 0 | BB44: =IFERROR(BB21*$F44,0) -> 0 | BC44: =IFERROR(BC21*$F44,0) -> 0 | BD44: =SUM(AZ44:BC44) -> 0 | BE44: =IFERROR(BE21*$F44,0) -> 0 | BF44: =IFERROR(BF21*$F44,0) -> 0 | BG44: =IFERROR(BG21*$F44,0) -> 0 | BH44: =IFERROR(BH21*$F44,0) -> 0 | BI44: =SUM(BE44:BH44) -> 0 | BJ44: =IFERROR(BJ21*$F44,0) -> 0 | BK44: =IFERROR(BK21*$F44,0) -> 0 | BL44: =IFERROR(BL21*$F44,0) -> 0 | BM44: =IFERROR(BM21*$F44,0) -> 0 | BN44: =SUM(BJ44:BM44) -> 0
A45: =A22 -> 0 | B45: =B22 -> 0 | C45: =C22 -> 0 | D45: =D22 -> 0 | E45: =E22 -> 0 | F45: ='Customer''s Questionnaire'!M55 -> 0 | G45: =IFERROR(G22*$F45,0) -> 0 | H45: =IFERROR(H22*$F45,0) -> 0 | I45: =IFERROR(I22*$F45,0) -> 0 | J45: =IFERROR(J22*$F45,0) -> 0 | K45: =SUM(G45:J45) -> 0 | L45: =IFERROR(L22*$F45,0) -> 0 | M45: =IFERROR(M22*$F45,0) -> 0 | N45: =IFERROR(N22*$F45,0) -> 0 | O45: =IFERROR(O22*$F45,0) -> 0 | P45: =SUM(L45:O45) -> 0 | Q45: =IFERROR(Q22*$F45,0) -> 0 | R45: =IFERROR(R22*$F45,0) -> 0 | S45: =IFERROR(S22*$F45,0) -> 0 | T45: =IFERROR(T22*$F45,0) -> 0 | U45: =SUM(Q45:T45) -> 0 | V45: =IFERROR(V22*$F45,0) -> 0 | W45: =IFERROR(W22*$F45,0) -> 0 | X45: =IFERROR(X22*$F45,0) -> 0 | Y45: =IFERROR(Y22*$F45,0) -> 0 | Z45: =SUM(V45:Y45) -> 0 | AA45: =IFERROR(AA22*$F45,0) -> 0 | AB45: =IFERROR(AB22*$F45,0) -> 0 | AC45: =IFERROR(AC22*$F45,0) -> 0 | AD45: =IFERROR(AD22*$F45,0) -> 0 | AE45: =SUM(AA45:AD45) -> 0 | AF45: =IFERROR(AF22*$F45,0) -> 0 | AG45: =IFERROR(AG22*$F45,0) -> 0 | AH45: =IFERROR(AH22*$F45,0) -> 0 | AI45: =IFERROR(AI22*$F45,0) -> 0 | AJ45: =SUM(AF45:AI45) -> 0 | AK45: =IFERROR(AK22*$F45,0) -> 0 | AL45: =IFERROR(AL22*$F45,0) -> 0 | AM45: =IFERROR(AM22*$F45,0) -> 0 | AN45: =IFERROR(AN22*$F45,0) -> 0 | AO45: =SUM(AK45:AN45) -> 0 | AP45: =IFERROR(AP22*$F45,0) -> 0 | AQ45: =IFERROR(AQ22*$F45,0) -> 0 | AR45: =IFERROR(AR22*$F45,0) -> 0 | AS45: =IFERROR(AS22*$F45,0) -> 0 | AT45: =SUM(AP45:AS45) -> 0 | AU45: =IFERROR(AU22*$F45,0) -> 0 | AV45: =IFERROR(AV22*$F45,0) -> 0 | AW45: =IFERROR(AW22*$F45,0) -> 0 | AX45: =IFERROR(AX22*$F45,0) -> 0 | AY45: =SUM(AU45:AX45) -> 0 | AZ45: =IFERROR(AZ22*$F45,0) -> 0 | BA45: =IFERROR(BA22*$F45,0) -> 0 | BB45: =IFERROR(BB22*$F45,0) -> 0 | BC45: =IFERROR(BC22*$F45,0) -> 0 | BD45: =SUM(AZ45:BC45) -> 0 | BE45: =IFERROR(BE22*$F45,0) -> 0 | BF45: =IFERROR(BF22*$F45,0) -> 0 | BG45: =IFERROR(BG22*$F45,0) -> 0 | BH45: =IFERROR(BH22*$F45,0) -> 0 | BI45: =SUM(BE45:BH45) -> 0 | BJ45: =IFERROR(BJ22*$F45,0) -> 0 | BK45: =IFERROR(BK22*$F45,0) -> 0 | BL45: =IFERROR(BL22*$F45,0) -> 0 | BM45: =IFERROR(BM22*$F45,0) -> 0 | BN45: =SUM(BJ45:BM45) -> 0
... A53: =A30 -> 0 | B53: =B30 -> 0 | C53: =C30 -> 0 | D53: =D30 -> 0 | E53: =E30 -> 0 | F53: ='Customer''s Questionnaire'!M63 -> 0 | G53: =IFERROR(G30*$F53,0) -> 0 | H53: =IFERROR(H30*$F53,0) -> 0 | I53: =IFERROR(I30*$F53,0) -> 0 | J53: =IFERROR(J30*$F53,0) -> 0 | K53: =SUM(G53:J53) -> 0 | L53: =IFERROR(L30*$F53,0) -> 0 | M53: =IFERROR(M30*$F53,0) -> 0 | N53: =IFERROR(N30*$F53,0) -> 0 | O53: =IFERROR(O30*$F53,0) -> 0 | P53: =SUM(L53:O53) -> 0 | Q53: =IFERROR(Q30*$F53,0) -> 0 | R53: =IFERROR(R30*$F53,0) -> 0 | S53: =IFERROR(S30*$F53,0) -> 0 | T53: =IFERROR(T30*$F53,0) -> 0 | U53: =SUM(Q53:T53) -> 0 | V53: =IFERROR(V30*$F53,0) -> 0 | W53: =IFERROR(W30*$F53,0) -> 0 | X53: =IFERROR(X30*$F53,0) -> 0 | Y53: =IFERROR(Y30*$F53,0) -> 0 | Z53: =SUM(V53:Y53) -> 0 | AA53: =IFERROR(AA30*$F53,0) -> 0 | AB53: =IFERROR(AB30*$F53,0) -> 0 | AC53: =IFERROR(AC30*$F53,0) -> 0 | AD53: =IFERROR(AD30*$F53,0) -> 0 | AE53: =SUM(AA53:AD53) -> 0 | AF53: =IFERROR(AF30*$F53,0) -> 0 | AG53: =IFERROR(AG30*$F53,0) -> 0 | AH53: =IFERROR(AH30*$F53,0) -> 0 | AI53: =IFERROR(AI30*$F53,0) -> 0 | AJ53: =SUM(AF53:AI53) -> 0 | AK53: =IFERROR(AK30*$F53,0) -> 0 | AL53: =IFERROR(AL30*$F53,0) -> 0 | AM53: =IFERROR(AM30*$F53,0) -> 0 | AN53: =IFERROR(AN30*$F53,0) -> 0 | AO53: =SUM(AK53:AN53) -> 0 | AP53: =IFERROR(AP30*$F53,0) -> 0 | AQ53: =IFERROR(AQ30*$F53,0) -> 0 | AR53: =IFERROR(AR30*$F53,0) -> 0 | AS53: =IFERROR(AS30*$F53,0) -> 0 | AT53: =SUM(AP53:AS53) -> 0 | AU53: =IFERROR(AU30*$F53,0) -> 0 | AV53: =IFERROR(AV30*$F53,0) -> 0 | AW53: =IFERROR(AW30*$F53,0) -> 0 | AX53: =IFERROR(AX30*$F53,0) -> 0 | AY53: =SUM(AU53:AX53) -> 0 | AZ53: =IFERROR(AZ30*$F53,0) -> 0 | BA53: =IFERROR(BA30*$F53,0) -> 0 | BB53: =IFERROR(BB30*$F53,0) -> 0 | BC53: =IFERROR(BC30*$F53,0) -> 0 | BD53: =SUM(AZ53:BC53) -> 0 | BE53: =IFERROR(BE30*$F53,0) -> 0 | BF53: =IFERROR(BF30*$F53,0) -> 0 | BG53: =IFERROR(BG30*$F53,0) -> 0 | BH53: =IFERROR(BH30*$F53,0) -> 0 | BI53: =SUM(BE53:BH53) -> 0 | BJ53: =IFERROR(BJ30*$F53,0) -> 0 | BK53: =IFERROR(BK30*$F53,0) -> 0 | BL53: =IFERROR(BL30*$F53,0) -> 0 | BM53: =IFERROR(BM30*$F53,0) -> 0 | BN53: =SUM(BJ53:BM53) -> 0
A54: TOTAL Revenues | B54: Total | E54: Total | G54: =IF($K$31>0,SUM(G$34:G$53),$G$8/4) -> 20000 | H54: =IF($K$31>0,SUM(H$34:H$53),$G$8/4) -> 20000 | I54: =IF($K$31>0,SUM(I$34:I$53),$G$8/4) -> 20000 | J54: =IF($K$31>0,SUM(J$34:J$53),$G$8/4) -> 20000 | K54: =SUM(K34:K39) -> 80000 | L54: =IF($P$31>0,SUM(L$34:L$53),$L$8/4) -> 25000 | M54: =IF($P$31>0,SUM(M$34:M$53),$L$8/4) -> 25000 | N54: =IF($P$31>0,SUM(N$34:N$53),$L$8/4) -> 25000 | O54: =IF($P$31>0,SUM(O$34:O$53),$L$8/4) -> 25000 | P54: =SUM(P34:P53) -> 100000 | Q54: =IF($U$31>0,SUM(Q$34:Q$53),$Q$8/4) -> 33750 | R54: =IF($U$31>0,SUM(R$34:R$53),$Q$8/4) -> 33750 | S54: =IF($U$31>0,SUM(S$34:S$53),$Q$8/4) -> 33750 | T54: =IF($U$31>0,SUM(T$34:T$53),$Q$8/4) -> 33750 | U54: =SUM(U34:U53) -> 135000 | V54: =IF($Z$31>0,SUM(V$34:V$53),$V$8/4) -> 42187.5 | W54: =IF($Z$31>0,SUM(W$34:W$53),$V$8/4) -> 42187.5 | X54: =IF($Z$31>0,SUM(X$34:X$53),$V$8/4) -> 42187.5 | Y54: =IF($Z$31>0,SUM(Y$34:Y$53),$V$8/4) -> 42187.5 | Z54: =SUM(Z34:Z53) -> 168750 | AA54: =IF($AE$31>0,SUM(AA$34:AA$53),$AA$8/4) -> 48515.625 | AB54: =IF($AE$31>0,SUM(AB$34:AB$53),$AA$8/4) -> 48515.625 | AC54: =IF($AE$31>0,SUM(AC$34:AC$53),$AA$8/4) -> 48515.625 | AD54: =IF($AE$31>0,SUM(AD$34:AD$53),$AA$8/4) -> 48515.625 | AE54: =SUM(AE34:AE53) -> 194062.5 | AF54: =IF($AJ$31>0,SUM(AF$34:AF$53),$AF$8/4) -> 55792.969 | AG54: =IF($AJ$31>0,SUM(AG$34:AG$53),$AF$8/4) -> 55792.969 | AH54: =IF($AJ$31>0,SUM(AH$34:AH$53),$AF$8/4) -> 55792.969 | AI54: =IF($AJ$31>0,SUM(AI$34:AI$53),$AF$8/4) -> 55792.969 | AJ54: =SUM(AJ34:AJ53) -> 223171.87 | AK54: =IF($AO$31>0,SUM(AK$34:AK$53),$AK$8/4) -> 64161.914 | AL54: =IF($AO$31>0,SUM(AL$34:AL$53),$AK$8/4) -> 64161.914 | AM54: =IF($AO$31>0,SUM(AM$34:AM$53),$AK$8/4) -> 64161.914 | AN54: =IF($AO$31>0,SUM(AN$34:AN$53),$AK$8/4) -> 64161.914 | AO54: =SUM(AO34:AO53) -> 256647.66 | AP54: =IF($AT$31>0,SUM(AP$34:AP$53),$AP$8/4) -> 73786.201 | AQ54: =IF($AT$31>0,SUM(AQ$34:AQ$53),$AP$8/4) -> 73786.201 | AR54: =IF($AT$31>0,SUM(AR$34:AR$53),$AP$8/4) -> 73786.201 | AS54: =IF($AT$31>0,SUM(AS$34:AS$53),$AP$8/4) -> 73786.201 | AT54: =SUM(AT34:AT53) -> 295144.8 | AU54: =IF($AY$31>0,SUM(AU$34:AU$53),$AU$8/4) -> 84854.131 | AV54: =IF($AY$31>0,SUM(AV$34:AV$53),$AU$8/4) -> 84854.131 | AW54: =IF($AY$31>0,SUM(AW$34:AW$53),$AU$8/4) -> 84854.131 | AX54: =IF($AY$31>0,SUM(AX$34:AX$53),$AU$8/4) -> 84854.131 | AY54: =SUM(AY34:AY53) -> 339416.53 | AZ54: =IF($BD$31>0,SUM(AZ$34:AZ$53),$AZ$8/4) -> 97582.251 | BA54: =IF($BD$31>0,SUM(BA$34:BA$53),$AZ$8/4) -> 97582.251 | BB54: =IF($BD$31>0,SUM(BB$34:BB$53),$AZ$8/4) -> 97582.251 | BC54: =IF($BD$31>0,SUM(BC$34:BC$53),$AZ$8/4) -> 97582.251 | BD54: =SUM(BD34:BD53) -> 390329 | BE54: =IF($BI$31>0,SUM(BE$34:BE$53),$BE$8/4) -> 112219.59 | BF54: =IF($BI$31>0,SUM(BF$34:BF$53),$BE$8/4) -> 112219.59 | BG54: =IF($BI$31>0,SUM(BG$34:BG$53),$BE$8/4) -> 112219.59 | BH54: =IF($BI$31>0,SUM(BH$34:BH$53),$BE$8/4) -> 112219.59 | BI54: =SUM(BI34:BI53) -> 448878.35 | BJ54: =IF($BN$31>0,SUM(BJ$34:BJ$53),$BJ$8/4) -> 129052.53 | BK54: =IF($BN$31>0,SUM(BK$34:BK$53),$BJ$8/4) -> 129052.53 | BL54: =IF($BN$31>0,SUM(BL$34:BL$53),$BJ$8/4) -> 129052.53 | BM54: =IF($BN$31>0,SUM(BM$34:BM$53),$BJ$8/4) -> 129052.53 | BN54: =SUM(BN34:BN53) -> 516210.11

Sheet COGS
G4: Q. | H4: Q. | I4: Q. | J4: Q. | K4: Q. | L4: Q. | M4: Q. | N4: Q. | O4: Q. | P4: Q. | Q4: Q. | R4: Q. | S4: Q. | T4: Q. | U4: Q. | V4: Q. | W4: Q. | X4: Q. | Y4: Q. | Z4: Q. | AA4: Q. | AB4: Q. | AC4: Q. | AD4: Q. | AE4: Q. | AF4: Q. | AG4: Q. | AH4: Q. | AI4: Q. | AJ4: Q. | AK4: Q. | AL4: Q. | AM4: Q. | AN4: Q. | AO4: Q. | AP4: Q. | AQ4: Q. | AR4: Q. | AS4: Q. | AT4: Q. | AU4: Q. | AV4: Q. | AW4: Q. | AX4: Q. | AY4: Q. | AZ4: Q. | BA4: Q. | BB4: Q. | BC4: Q. | BD4: Q. | BE4: Q. | BF4: Q. | BG4: Q. | BH4: Q. | BI4: Q. | BJ4: Q. | BK4: Q. | BL4: Q. | BM4: Q. | BN4: Q.
A5: Period | F5: Unit Cost | G5: ='Rev. Build'!G10 -> Q1-2026 | H5: ='Rev. Build'!H10 -> Q2-2026 | I5: ='Rev. Build'!I10 -> Q3-2026 | J5: ='Rev. Build'!J10 -> Q4-2026 | K5: ='Rev. Build'!K10 -> 2026 | L5: ='Rev. Build'!L10 -> Q1-2027 | M5: ='Rev. Build'!M10 -> Q2-2027 | N5: ='Rev. Build'!N10 -> Q3-2027 | ... BN5: ='Rev. Build'!BN10 -> 2037
A8: Quantity | B8: Customer | C8: Type | D8: Territory | E8: Product | F8: —
A9: ='Rev. Build'!A11 -> Hardware | B9: ='Rev. Build'!B11 -> Hungry AF | C9: ='Rev. Build'!C11 -> B2C | D9: ='Rev. Build'!D11 -> US | E9: ='Rev. Build'!E11 -> Big MAC | G9: ='Rev. Build'!G11 -> 10 | H9: ='Rev. Build'!H11 -> 10 | I9: ='Rev. Build'!I11 -> 10 | J9: ='Rev. Build'!J11 -> 10 | K9: ='Rev. Build'!K11 -> 40 | L9: ='Rev. Build'!L11 -> 12.5 | M9: ='Rev. Build'!M11 -> 12.5 | N9: ='Rev. Build'!N11 -> 12.5 | ... BN9: ='Rev. Build'!BN11 -> 258.10505
A10: ='Rev. Build'!A12 -> Software / SaaS | B10: ='Rev. Build'!B12 -> BULO | C10: ='Rev. Build'!C12 -> Direct | D10: ='Rev. Build'!D12 -> EU | E10: ='Rev. Build'!E12 -> MCMC | G10: ='Rev. Build'!G12 -> 1000 | H10: ='Rev. Build'!H12 -> 1000 | I10: ='Rev. Build'!I12 -> 1000 | J10: ='Rev. Build'!J12 -> 1000 | K10: ='Rev. Build'!K12 -> 4000 | L10: ='Rev. Build'!L12 -> 1250 | M10: ='Rev. Build'!M12 -> 1250 | N10: ='Rev. Build'!N12 -> 1250 | ... BN10: ='Rev. Build'!BN12 -> 25810.505
A11: ='Rev. Build'!A13 -> 0 | B11: ='Rev. Build'!B13 -> 0 | C11: ='Rev. Build'!C13 -> 0 | D11: ='Rev. Build'!D13 -> 0 | E11: ='Rev. Build'!E13 -> 0 | G11: ='Rev. Build'!G13 -> 0 | H11: ='Rev. Build'!H13 -> 0 | I11: ='Rev. Build'!I13 -> 0 | J11: ='Rev. Build'!J13 -> 0 | K11: ='Rev. Build'!K13 -> 0 | L11: ='Rev. Build'!L13 -> 0 | M11: ='Rev. Build'!M13 -> 0 | N11: ='Rev. Build'!N13 -> 0 | ... BN11: ='Rev. Build'!BN13 -> 0
A12: ='Rev. Build'!A14 -> 0 | B12: ='Rev. Build'!B14 -> 0 | C12: ='Rev. Build'!C14 -> 0 | D12: ='Rev. Build'!D14 -> 0 | E12: ='Rev. Build'!E14 -> 0 | G12: ='Rev. Build'!G14 -> 0 | H12: ='Rev. Build'!H14 -> 0 | I12: ='Rev. Build'!I14 -> 0 | J12: ='Rev. Build'!J14 -> 0 | K12: ='Rev. Build'!K14 -> 0 | L12: ='Rev. Build'!L14 -> 0 | M12: ='Rev. Build'!M14 -> 0 | N12: ='Rev. Build'!N14 -> 0 | ... BN12: ='Rev. Build'!BN14 -> 0
A13: ='Rev. Build'!A15 -> 0 | B13: ='Rev. Build'!B15 -> 0 | C13: ='Rev. Build'!C15 -> 0 | D13: ='Rev. Build'!D15 -> 0 | E13: ='Rev. Build'!E15 -> 0 | G13: ='Rev. Build'!G15 -> 0 | H13: ='Rev. Build'!H15 -> 0 | I13: ='Rev. Build'!I15 -> 0 | J13: ='Rev. Build'!J15 -> 0 | K13: ='Rev. Build'!K15 -> 0 | L13: ='Rev. Build'!L15 -> 0 | M13: ='Rev. Build'!M15 -> 0 | N13: ='Rev. Build'!N15 -> 0 | ... BN13: ='Rev. Build'!BN15 -> 0
A14: ='Rev. Build'!A16 -> 0 | B14: ='Rev. Build'!B16 -> 0 | C14: ='Rev. Build'!C16 -> 0 | D14: ='Rev. Build'!D16 -> 0 | E14: ='Rev. Build'!E16 -> 0 | G14: ='Rev. Build'!G16 -> 0 | H14: ='Rev. Build'!H16 -> 0 | I14: ='Rev. Build'!I16 -> 0 | J14: ='Rev. Build'!J16 -> 0 | K14: ='Rev. Build'!K16 -> 0 | L14: ='Rev. Build'!L16 -> 0 | M14: ='Rev. Build'!M16 -> 0 | N14: ='Rev. Build'!N16 -> 0 | ... BN14: ='Rev. Build'!BN16 -> 0
A15: ='Rev. Build'!A17 -> 0 | B15: ='Rev. Build'!B17 -> 0 | C15: ='Rev. Build'!C17 -> 0 | D15: ='Rev. Build'!D17 -> 0 | E15: ='Rev. Build'!E17 -> 0 | G15: ='Rev. Build'!G17 -> 0 | H15: ='Rev. Build'!H17 -> 0 | I15: ='Rev. Build'!I17 -> 0 | J15: ='Rev. Build'!J17 -> 0 | K15: ='Rev. Build'!K17 -> 0 | L15: ='Rev. Build'!L17 -> 0 | M15: ='Rev. Build'!M17 -> 0 | N15: ='Rev. Build'!N17 -> 0 | ... BN15: ='Rev. Build'!BN17 -> 0
A16: ='Rev. Build'!A18 -> 0 | B16: ='Rev. Build'!B18 -> 0 | C16: ='Rev. Build'!C18 -> 0 | D16: ='Rev. Build'!D18 -> 0 | E16: ='Rev. Build'!E18 -> 0 | G16: ='Rev. Build'!G18 -> 0 | H16: ='Rev. Build'!H18 -> 0 | I16: ='Rev. Build'!I18 -> 0 | J16: ='Rev. Build'!J18 -> 0 | K16: ='Rev. Build'!K18 -> 0 | L16: ='Rev. Build'!L18 -> 0 | M16: ='Rev. Build'!M18 -> 0 | N16: ='Rev. Build'!N18 -> 0 | ... BN16: ='Rev. Build'!BN18 -> 0
A17: ='Rev. Build'!A19 -> 0 | B17: ='Rev. Build'!B19 -> 0 | C17: ='Rev. Build'!C19 -> 0 | D17: ='Rev. Build'!D19 -> 0 | E17: ='Rev. Build'!E19 -> 0 | G17: ='Rev. Build'!G19 -> 0 | H17: ='Rev. Build'!H19 -> 0 | I17: ='Rev. Build'!I19 -> 0 | J17: ='Rev. Build'!J19 -> 0 | K17: ='Rev. Build'!K19 -> 0 | L17: ='Rev. Build'!L19 -> 0 | M17: ='Rev. Build'!M19 -> 0 | N17: ='Rev. Build'!N19 -> 0 | ... BN17: ='Rev. Build'!BN19 -> 0
A18: ='Rev. Build'!A20 -> 0 | B18: ='Rev. Build'!B20 -> 0 | C18: ='Rev. Build'!C20 -> 0 | D18: ='Rev. Build'!D20 -> 0 | E18: ='Rev. Build'!E20 -> 0 | G18: ='Rev. Build'!G20 -> 0 | H18: ='Rev. Build'!H20 -> 0 | I18: ='Rev. Build'!I20 -> 0 | J18: ='Rev. Build'!J20 -> 0 | K18: ='Rev. Build'!K20 -> 0 | L18: ='Rev. Build'!L20 -> 0 | M18: ='Rev. Build'!M20 -> 0 | N18: ='Rev. Build'!N20 -> 0 | ... BN18: ='Rev. Build'!BN20 -> 0
A19: ='Rev. Build'!A21 -> 0 | B19: ='Rev. Build'!B21 -> 0 | C19: ='Rev. Build'!C21 -> 0 | D19: ='Rev. Build'!D21 -> 0 | E19: ='Rev. Build'!E21 -> 0 | G19: ='Rev. Build'!G21 -> 0 | H19: ='Rev. Build'!H21 -> 0 | I19: ='Rev. Build'!I21 -> 0 | J19: ='Rev. Build'!J21 -> 0 | K19: ='Rev. Build'!K21 -> 0 | L19: ='Rev. Build'!L21 -> 0 | M19: ='Rev. Build'!M21 -> 0 | N19: ='Rev. Build'!N21 -> 0 | ... BN19: ='Rev. Build'!BN21 -> 0
A20: ='Rev. Build'!A22 -> 0 | B20: ='Rev. Build'!B22 -> 0 | C20: ='Rev. Build'!C22 -> 0 | D20: ='Rev. Build'!D22 -> 0 | E20: ='Rev. Build'!E22 -> 0 | G20: ='Rev. Build'!G22 -> 0 | H20: ='Rev. Build'!H22 -> 0 | I20: ='Rev. Build'!I22 -> 0 | J20: ='Rev. Build'!J22 -> 0 | K20: ='Rev. Build'!K22 -> 0 | L20: ='Rev. Build'!L22 -> 0 | M20: ='Rev. Build'!M22 -> 0 | N20: ='Rev. Build'!N22 -> 0 | ... BN20: ='Rev. Build'!BN22 -> 0
... A28: ='Rev. Build'!A30 -> 0 | B28: ='Rev. Build'!B30 -> 0 | C28: ='Rev. Build'!C30 -> 0 | D28: ='Rev. Build'!D30 -> 0 | E28: ='Rev. Build'!E30 -> 0 | G28: ='Rev. Build'!G30 -> 0 | H28: ='Rev. Build'!H30 -> 0 | I28: ='Rev. Build'!I30 -> 0 | J28: ='Rev. Build'!J30 -> 0 | K28: ='Rev. Build'!K30 -> 0 | L28: ='Rev. Build'!L30 -> 0 | M28: ='Rev. Build'!M30 -> 0 | N28: ='Rev. Build'!N30 -> 0 | ... BN28: ='Rev. Build'!BN30 -> 0
A29: Total Qty | G29: =SUM(G9:G28) -> 1010 | H29: =SUM(H9:H28) -> 1010 | I29: =SUM(I9:I28) -> 1010 | J29: =SUM(J9:J28) -> 1010 | K29: =SUM(K9:K28) -> 4040 | L29: =SUM(L9:L28) -> 1262.5 | M29: =SUM(M9:M28) -> 1262.5 | N29: =SUM(N9:N28) -> 1262.5 | ... BN29: =SUM(BN9:BN28) -> 26068.61
A30: Cost | B30: Customer | C30: Type | D30: Territory | E30: Product | F30: Unit Cost
A31: =A9 -> Hardware | B31: =B9 -> Hungry AF | C31: =C9 -> B2C | D31: =D9 -> US | E31: =E9 -> Big MAC | F31: ='Customer''s Questionnaire'!N44 -> 500 | G31: =IFERROR(G9*$F31,0) -> 5000 | H31: =IFERROR(H9*$F31,0) -> 5000 | I31: =IFERROR(I9*$F31,0) -> 5000 | J31: =IFERROR(J9*$F31,0) -> 5000 | K31: =SUM(G31:J31) -> 20000 | L31: =IFERROR(L9*$F31,0) -> 6250 | M31: =IFERROR(M9*$F31,0) -> 6250 | N31: =IFERROR(N9*$F31,0) -> 6250 | O31: =IFERROR(O9*$F31,0) -> 6250 | P31: =SUM(L31:O31) -> 25000 | Q31: =IFERROR(Q9*$F31,0) -> 8437.5 | R31: =IFERROR(R9*$F31,0) -> 8437.5 | S31: =IFERROR(S9*$F31,0) -> 8437.5 | T31: =IFERROR(T9*$F31,0) -> 8437.5 | U31: =SUM(Q31:T31) -> 33750 | V31: =IFERROR(V9*$F31,0) -> 10546.875 | W31: =IFERROR(W9*$F31,0) -> 10546.875 | X31: =IFERROR(X9*$F31,0) -> 10546.875 | Y31: =IFERROR(Y9*$F31,0) -> 10546.875 | Z31: =SUM(V31:Y31) -> 42187.5 | AA31: =IFERROR(AA9*$F31,0) -> 12128.906 | AB31: =IFERROR(AB9*$F31,0) -> 12128.906 | AC31: =IFERROR(AC9*$F31,0) -> 12128.906 | AD31: =IFERROR(AD9*$F31,0) -> 12128.906 | AE31: =SUM(AA31:AD31) -> 48515.625 | AF31: =IFERROR(AF9*$F31,0) -> 13948.242 | AG31: =IFERROR(AG9*$F31,0) -> 13948.242 | AH31: =IFERROR(AH9*$F31,0) -> 13948.242 | AI31: =IFERROR(AI9*$F31,0) -> 13948.242 | AJ31: =SUM(AF31:AI31) -> 55792.969 | AK31: =IFERROR(AK9*$F31,0) -> 16040.479 | AL31: =IFERROR(AL9*$F31,0) -> 16040.479 | AM31: =IFERROR(AM9*$F31,0) -> 16040.479 | AN31: =IFERROR(AN9*$F31,0) -> 16040.479 | AO31: =SUM(AK31:AN31) -> 64161.914 | AP31: =IFERROR(AP9*$F31,0) -> 18446.55 | AQ31: =IFERROR(AQ9*$F31,0) -> 18446.55 | AR31: =IFERROR(AR9*$F31,0) -> 18446.55 | AS31: =IFERROR(AS9*$F31,0) -> 18446.55 | AT31: =SUM(AP31:AS31) -> 73786.201 | AU31: =IFERROR(AU9*$F31,0) -> 21213.533 | AV31: =IFERROR(AV9*$F31,0) -> 21213.533 | AW31: =IFERROR(AW9*$F31,0) -> 21213.533 | AX31: =IFERROR(AX9*$F31,0) -> 21213.533 | AY31: =SUM(AU31:AX31) -> 84854.131 | AZ31: =IFERROR(AZ9*$F31,0) -> 24395.563 | BA31: =IFERROR(BA9*$F31,0) -> 24395.563 | BB31: =IFERROR(BB9*$F31,0) -> 24395.563 | BC31: =IFERROR(BC9*$F31,0) -> 24395.563 | BD31: =SUM(AZ31:BC31) -> 97582.251 | BE31: =IFERROR(BE9*$F31,0) -> 28054.897 | BF31: =IFERROR(BF9*$F31,0) -> 28054.897 | BG31: =IFERROR(BG9*$F31,0) -> 28054.897 | BH31: =IFERROR(BH9*$F31,0) -> 28054.897 | BI31: =SUM(BE31:BH31) -> 112219.59 | BJ31: =IFERROR(BJ9*$F31,0) -> 32263.132 | BK31: =IFERROR(BK9*$F31,0) -> 32263.132 | BL31: =IFERROR(BL9*$F31,0) -> 32263.132 | BM31: =IFERROR(BM9*$F31,0) -> 32263.132 | BN31: =SUM(BJ31:BM31) -> 129052.53
A32: =A10 -> Software / SaaS | B32: =B10 -> BULO | C32: =C10 -> Direct | D32: =D10 -> EU | E32: =E10 -> MCMC | F32: ='Customer''s Questionnaire'!N45 -> 5 | G32: =IFERROR(G10*$F32,0) -> 5000 | H32: =IFERROR(H10*$F32,0) -> 5000 | I32: =IFERROR(I10*$F32,0) -> 5000 | J32: =IFERROR(J10*$F32,0) -> 5000 | K32: =SUM(G32:J32) -> 20000 | L32: =IFERROR(L10*$F32,0) -> 6250 | M32: =IFERROR(M10*$F32,0) -> 6250 | N32: =IFERROR(N10*$F32,0) -> 6250 | O32: =IFERROR(O10*$F32,0) -> 6250 | P32: =SUM(L32:O32) -> 25000 | Q32: =IFERROR(Q10*$F32,0) -> 8437.5 | R32: =IFERROR(R10*$F32,0) -> 8437.5 | S32: =IFERROR(S10*$F32,0) -> 8437.5 | T32: =IFERROR(T10*$F32,0) -> 8437.5 | U32: =SUM(Q32:T32) -> 33750 | V32: =IFERROR(V10*$F32,0) -> 10546.875 | W32: =IFERROR(W10*$F32,0) -> 10546.875 | X32: =IFERROR(X10*$F32,0) -> 10546.875 | Y32: =IFERROR(Y10*$F32,0) -> 10546.875 | Z32: =SUM(V32:Y32) -> 42187.5 | AA32: =IFERROR(AA10*$F32,0) -> 12128.906 | AB32: =IFERROR(AB10*$F32,0) -> 12128.906 | AC32: =IFERROR(AC10*$F32,0) -> 12128.906 | AD32: =IFERROR(AD10*$F32,0) -> 12128.906 | AE32: =SUM(AA32:AD32) -> 48515.625 | AF32: =IFERROR(AF10*$F32,0) -> 13948.242 | AG32: =IFERROR(AG10*$F32,0) -> 13948.242 | AH32: =IFERROR(AH10*$F32,0) -> 13948.242 | AI32: =IFERROR(AI10*$F32,0) -> 13948.242 | AJ32: =SUM(AF32:AI32) -> 55792.969 | AK32: =IFERROR(AK10*$F32,0) -> 16040.479 | AL32: =IFERROR(AL10*$F32,0) -> 16040.479 | AM32: =IFERROR(AM10*$F32,0) -> 16040.479 | AN32: =IFERROR(AN10*$F32,0) -> 16040.479 | AO32: =SUM(AK32:AN32) -> 64161.914 | AP32: =IFERROR(AP10*$F32,0) -> 18446.55 | AQ32: =IFERROR(AQ10*$F32,0) -> 18446.55 | AR32: =IFERROR(AR10*$F32,0) -> 18446.55 | AS32: =IFERROR(AS10*$F32,0) -> 18446.55 | AT32: =SUM(AP32:AS32) -> 73786.201 | AU32: =IFERROR(AU10*$F32,0) -> 21213.533 | AV32: =IFERROR(AV10*$F32,0) -> 21213.533 | AW32: =IFERROR(AW10*$F32,0) -> 21213.533 | AX32: =IFERROR(AX10*$F32,0) -> 21213.533 | AY32: =SUM(AU32:AX32) -> 84854.131 | AZ32: =IFERROR(AZ10*$F32,0) -> 24395.563 | BA32: =IFERROR(BA10*$F32,0) -> 24395.563 | BB32: =IFERROR(BB10*$F32,0) -> 24395.563 | BC32: =IFERROR(BC10*$F32,0) -> 24395.563 | BD32: =SUM(AZ32:BC32) -> 97582.251 | BE32: =IFERROR(BE10*$F32,0) -> 28054.897 | BF32: =IFERROR(BF10*$F32,0) -> 28054.897 | BG32: =IFERROR(BG10*$F32,0) -> 28054.897 | BH32: =IFERROR(BH10*$F32,0) -> 28054.897 | BI32: =SUM(BE32:BH32) -> 112219.59 | BJ32: =IFERROR(BJ10*$F32,0) -> 32263.132 | BK32: =IFERROR(BK10*$F32,0) -> 32263.132 | BL32: =IFERROR(BL10*$F32,0) -> 32263.132 | BM32: =IFERROR(BM10*$F32,0) -> 32263.132 | BN32: =SUM(BJ32:BM32) -> 129052.53
A33: =A11 -> 0 | B33: =B11 -> 0 | C33: =C11 -> 0 | D33: =D11 -> 0 | E33: =E11 -> 0 | F33: ='Customer''s Questionnaire'!N46 -> 0 | G33: =IFERROR(G11*$F33,0) -> 0 | H33: =IFERROR(H11*$F33,0) -> 0 | I33: =IFERROR(I11*$F33,0) -> 0 | J33: =IFERROR(J11*$F33,0) -> 0 | K33: =SUM(G33:J33) -> 0 | L33: =IFERROR(L11*$F33,0) -> 0 | M33: =IFERROR(M11*$F33,0) -> 0 | N33: =IFERROR(N11*$F33,0) -> 0 | O33: =IFERROR(O11*$F33,0) -> 0 | P33: =SUM(L33:O33) -> 0 | Q33: =IFERROR(Q11*$F33,0) -> 0 | R33: =IFERROR(R11*$F33,0) -> 0 | S33: =IFERROR(S11*$F33,0) -> 0 | T33: =IFERROR(T11*$F33,0) -> 0 | U33: =SUM(Q33:T33) -> 0 | V33: =IFERROR(V11*$F33,0) -> 0 | W33: =IFERROR(W11*$F33,0) -> 0 | X33: =IFERROR(X11*$F33,0) -> 0 | Y33: =IFERROR(Y11*$F33,0) -> 0 | Z33: =SUM(V33:Y33) -> 0 | AA33: =IFERROR(AA11*$F33,0) -> 0 | AB33: =IFERROR(AB11*$F33,0) -> 0 | AC33: =IFERROR(AC11*$F33,0) -> 0 | AD33: =IFERROR(AD11*$F33,0) -> 0 | AE33: =SUM(AA33:AD33) -> 0 | AF33: =IFERROR(AF11*$F33,0) -> 0 | AG33: =IFERROR(AG11*$F33,0) -> 0 | AH33: =IFERROR(AH11*$F33,0) -> 0 | AI33: =IFERROR(AI11*$F33,0) -> 0 | AJ33: =SUM(AF33:AI33) -> 0 | AK33: =IFERROR(AK11*$F33,0) -> 0 | AL33: =IFERROR(AL11*$F33,0) -> 0 | AM33: =IFERROR(AM11*$F33,0) -> 0 | AN33: =IFERROR(AN11*$F33,0) -> 0 | AO33: =SUM(AK33:AN33) -> 0 | AP33: =IFERROR(AP11*$F33,0) -> 0 | AQ33: =IFERROR(AQ11*$F33,0) -> 0 | AR33: =IFERROR(AR11*$F33,0) -> 0 | AS33: =IFERROR(AS11*$F33,0) -> 0 | AT33: =SUM(AP33:AS33) -> 0 | AU33: =IFERROR(AU11*$F33,0) -> 0 | AV33: =IFERROR(AV11*$F33,0) -> 0 | AW33: =IFERROR(AW11*$F33,0) -> 0 | AX33: =IFERROR(AX11*$F33,0) -> 0 | AY33: =SUM(AU33:AX33) -> 0 | AZ33: =IFERROR(AZ11*$F33,0) -> 0 | BA33: =IFERROR(BA11*$F33,0) -> 0 | BB33: =IFERROR(BB11*$F33,0) -> 0 | BC33: =IFERROR(BC11*$F33,0) -> 0 | BD33: =SUM(AZ33:BC33) -> 0 | BE33: =IFERROR(BE11*$F33,0) -> 0 | BF33: =IFERROR(BF11*$F33,0) -> 0 | BG33: =IFERROR(BG11*$F33,0) -> 0 | BH33: =IFERROR(BH11*$F33,0) -> 0 | BI33: =SUM(BE33:BH33) -> 0 | BJ33: =IFERROR(BJ11*$F33,0) -> 0 | BK33: =IFERROR(BK11*$F33,0) -> 0 | BL33: =IFERROR(BL11*$F33,0) -> 0 | BM33: =IFERROR(BM11*$F33,0) -> 0 | BN33: =SUM(BJ33:BM33) -> 0
A34: =A12 -> 0 | B34: =B12 -> 0 | C34: =C12 -> 0 | D34: =D12 -> 0 | E34: =E12 -> 0 | F34: ='Customer''s Questionnaire'!N47 -> 0 | G34: =IFERROR(G12*$F34,0) -> 0 | H34: =IFERROR(H12*$F34,0) -> 0 | I34: =IFERROR(I12*$F34,0) -> 0 | J34: =IFERROR(J12*$F34,0) -> 0 | K34: =SUM(G34:J34) -> 0 | L34: =IFERROR(L12*$F34,0) -> 0 | M34: =IFERROR(M12*$F34,0) -> 0 | N34: =IFERROR(N12*$F34,0) -> 0 | O34: =IFERROR(O12*$F34,0) -> 0 | P34: =SUM(L34:O34) -> 0 | Q34: =IFERROR(Q12*$F34,0) -> 0 | R34: =IFERROR(R12*$F34,0) -> 0 | S34: =IFERROR(S12*$F34,0) -> 0 | T34: =IFERROR(T12*$F34,0) -> 0 | U34: =SUM(Q34:T34) -> 0 | V34: =IFERROR(V12*$F34,0) -> 0 | W34: =IFERROR(W12*$F34,0) -> 0 | X34: =IFERROR(X12*$F34,0) -> 0 | Y34: =IFERROR(Y12*$F34,0) -> 0 | Z34: =SUM(V34:Y34) -> 0 | AA34: =IFERROR(AA12*$F34,0) -> 0 | AB34: =IFERROR(AB12*$F34,0) -> 0 | AC34: =IFERROR(AC12*$F34,0) -> 0 | AD34: =IFERROR(AD12*$F34,0) -> 0 | AE34: =SUM(AA34:AD34) -> 0 | AF34: =IFERROR(AF12*$F34,0) -> 0 | AG34: =IFERROR(AG12*$F34,0) -> 0 | AH34: =IFERROR(AH12*$F34,0) -> 0 | AI34: =IFERROR(AI12*$F34,0) -> 0 | AJ34: =SUM(AF34:AI34) -> 0 | AK34: =IFERROR(AK12*$F34,0) -> 0 | AL34: =IFERROR(AL12*$F34,0) -> 0 | AM34: =IFERROR(AM12*$F34,0) -> 0 | AN34: =IFERROR(AN12*$F34,0) -> 0 | AO34: =SUM(AK34:AN34) -> 0 | AP34: =IFERROR(AP12*$F34,0) -> 0 | AQ34: =IFERROR(AQ12*$F34,0) -> 0 | AR34: =IFERROR(AR12*$F34,0) -> 0 | AS34: =IFERROR(AS12*$F34,0) -> 0 | AT34: =SUM(AP34:AS34) -> 0 | AU34: =IFERROR(AU12*$F34,0) -> 0 | AV34: =IFERROR(AV12*$F34,0) -> 0 | AW34: =IFERROR(AW12*$F34,0) -> 0 | AX34: =IFERROR(AX12*$F34,0) -> 0 | AY34: =SUM(AU34:AX34) -> 0 | AZ34: =IFERROR(AZ12*$F34,0) -> 0 | BA34: =IFERROR(BA12*$F34,0) -> 0 | BB34: =IFERROR(BB12*$F34,0) -> 0 | BC34: =IFERROR(BC12*$F34,0) -> 0 | BD34: =SUM(AZ34:BC34) -> 0 | BE34: =IFERROR(BE12*$F34,0) -> 0 | BF34: =IFERROR(BF12*$F34,0) -> 0 | BG34: =IFERROR(BG12*$F34,0) -> 0 | BH34: =IFERROR(BH12*$F34,0) -> 0 | BI34: =SUM(BE34:BH34) -> 0 | BJ34: =IFERROR(BJ12*$F34,0) -> 0 | BK34: =IFERROR(BK12*$F34,0) -> 0 | BL34: =IFERROR(BL12*$F34,0) -> 0 | BM34: =IFERROR(BM12*$F34,0) -> 0 | BN34: =SUM(BJ34:BM34) -> 0
A35: =A13 -> 0 | B35: =B13 -> 0 | C35: =C13 -> 0 | D35: =D13 -> 0 | E35: =E13 -> 0 | F35: ='Customer''s Questionnaire'!N48 -> 0 | G35: =IFERROR(G13*$F35,0) -> 0 | H35: =IFERROR(H13*$F35,0) -> 0 | I35: =IFERROR(I13*$F35,0) -> 0 | J35: =IFERROR(J13*$F35,0) -> 0 | K35: =SUM(G35:J35) -> 0 | L35: =IFERROR(L13*$F35,0) -> 0 | M35: =IFERROR(M13*$F35,0) -> 0 | N35: =IFERROR(N13*$F35,0) -> 0 | O35: =IFERROR(O13*$F35,0) -> 0 | P35: =SUM(L35:O35) -> 0 | Q35: =IFERROR(Q13*$F35,0) -> 0 | R35: =IFERROR(R13*$F35,0) -> 0 | S35: =IFERROR(S13*$F35,0) -> 0 | T35: =IFERROR(T13*$F35,0) -> 0 | U35: =SUM(Q35:T35) -> 0 | V35: =IFERROR(V13*$F35,0) -> 0 | W35: =IFERROR(W13*$F35,0) -> 0 | X35: =IFERROR(X13*$F35,0) -> 0 | Y35: =IFERROR(Y13*$F35,0) -> 0 | Z35: =SUM(V35:Y35) -> 0 | AA35: =IFERROR(AA13*$F35,0) -> 0 | AB35: =IFERROR(AB13*$F35,0) -> 0 | AC35: =IFERROR(AC13*$F35,0) -> 0 | AD35: =IFERROR(AD13*$F35,0) -> 0 | AE35: =SUM(AA35:AD35) -> 0 | AF35: =IFERROR(AF13*$F35,0) -> 0 | AG35: =IFERROR(AG13*$F35,0) -> 0 | AH35: =IFERROR(AH13*$F35,0) -> 0 | AI35: =IFERROR(AI13*$F35,0) -> 0 | AJ35: =SUM(AF35:AI35) -> 0 | AK35: =IFERROR(AK13*$F35,0) -> 0 | AL35: =IFERROR(AL13*$F35,0) -> 0 | AM35: =IFERROR(AM13*$F35,0) -> 0 | AN35: =IFERROR(AN13*$F35,0) -> 0 | AO35: =SUM(AK35:AN35) -> 0 | AP35: =IFERROR(AP13*$F35,0) -> 0 | AQ35: =IFERROR(AQ13*$F35,0) -> 0 | AR35: =IFERROR(AR13*$F35,0) -> 0 | AS35: =IFERROR(AS13*$F35,0) -> 0 | AT35: =SUM(AP35:AS35) -> 0 | AU35: =IFERROR(AU13*$F35,0) -> 0 | AV35: =IFERROR(AV13*$F35,0) -> 0 | AW35: =IFERROR(AW13*$F35,0) -> 0 | AX35: =IFERROR(AX13*$F35,0) -> 0 | AY35: =SUM(AU35:AX35) -> 0 | AZ35: =IFERROR(AZ13*$F35,0) -> 0 | BA35: =IFERROR(BA13*$F35,0) -> 0 | BB35: =IFERROR(BB13*$F35,0) -> 0 | BC35: =IFERROR(BC13*$F35,0) -> 0 | BD35: =SUM(AZ35:BC35) -> 0 | BE35: =IFERROR(BE13*$F35,0) -> 0 | BF35: =IFERROR(BF13*$F35,0) -> 0 | BG35: =IFERROR(BG13*$F35,0) -> 0 | BH35: =IFERROR(BH13*$F35,0) -> 0 | BI35: =SUM(BE35:BH35) -> 0 | BJ35: =IFERROR(BJ13*$F35,0) -> 0 | BK35: =IFERROR(BK13*$F35,0) -> 0 | BL35: =IFERROR(BL13*$F35,0) -> 0 | BM35: =IFERROR(BM13*$F35,0) -> 0 | BN35: =SUM(BJ35:BM35) -> 0
A36: =A14 -> 0 | B36: =B14 -> 0 | C36: =C14 -> 0 | D36: =D14 -> 0 | E36: =E14 -> 0 | F36: ='Customer''s Questionnaire'!N49 -> 0 | G36: =IFERROR(G14*$F36,0) -> 0 | H36: =IFERROR(H14*$F36,0) -> 0 | I36: =IFERROR(I14*$F36,0) -> 0 | J36: =IFERROR(J14*$F36,0) -> 0 | K36: =SUM(G36:J36) -> 0 | L36: =IFERROR(L14*$F36,0) -> 0 | M36: =IFERROR(M14*$F36,0) -> 0 | N36: =IFERROR(N14*$F36,0) -> 0 | O36: =IFERROR(O14*$F36,0) -> 0 | P36: =SUM(L36:O36) -> 0 | Q36: =IFERROR(Q14*$F36,0) -> 0 | R36: =IFERROR(R14*$F36,0) -> 0 | S36: =IFERROR(S14*$F36,0) -> 0 | T36: =IFERROR(T14*$F36,0) -> 0 | U36: =SUM(Q36:T36) -> 0 | V36: =IFERROR(V14*$F36,0) -> 0 | W36: =IFERROR(W14*$F36,0) -> 0 | X36: =IFERROR(X14*$F36,0) -> 0 | Y36: =IFERROR(Y14*$F36,0) -> 0 | Z36: =SUM(V36:Y36) -> 0 | AA36: =IFERROR(AA14*$F36,0) -> 0 | AB36: =IFERROR(AB14*$F36,0) -> 0 | AC36: =IFERROR(AC14*$F36,0) -> 0 | AD36: =IFERROR(AD14*$F36,0) -> 0 | AE36: =SUM(AA36:AD36) -> 0 | AF36: =IFERROR(AF14*$F36,0) -> 0 | AG36: =IFERROR(AG14*$F36,0) -> 0 | AH36: =IFERROR(AH14*$F36,0) -> 0 | AI36: =IFERROR(AI14*$F36,0) -> 0 | AJ36: =SUM(AF36:AI36) -> 0 | AK36: =IFERROR(AK14*$F36,0) -> 0 | AL36: =IFERROR(AL14*$F36,0) -> 0 | AM36: =IFERROR(AM14*$F36,0) -> 0 | AN36: =IFERROR(AN14*$F36,0) -> 0 | AO36: =SUM(AK36:AN36) -> 0 | AP36: =IFERROR(AP14*$F36,0) -> 0 | AQ36: =IFERROR(AQ14*$F36,0) -> 0 | AR36: =IFERROR(AR14*$F36,0) -> 0 | AS36: =IFERROR(AS14*$F36,0) -> 0 | AT36: =SUM(AP36:AS36) -> 0 | AU36: =IFERROR(AU14*$F36,0) -> 0 | AV36: =IFERROR(AV14*$F36,0) -> 0 | AW36: =IFERROR(AW14*$F36,0) -> 0 | AX36: =IFERROR(AX14*$F36,0) -> 0 | AY36: =SUM(AU36:AX36) -> 0 | AZ36: =IFERROR(AZ14*$F36,0) -> 0 | BA36: =IFERROR(BA14*$F36,0) -> 0 | BB36: =IFERROR(BB14*$F36,0) -> 0 | BC36: =IFERROR(BC14*$F36,0) -> 0 | BD36: =SUM(AZ36:BC36) -> 0 | BE36: =IFERROR(BE14*$F36,0) -> 0 | BF36: =IFERROR(BF14*$F36,0) -> 0 | BG36: =IFERROR(BG14*$F36,0) -> 0 | BH36: =IFERROR(BH14*$F36,0) -> 0 | BI36: =SUM(BE36:BH36) -> 0 | BJ36: =IFERROR(BJ14*$F36,0) -> 0 | BK36: =IFERROR(BK14*$F36,0) -> 0 | BL36: =IFERROR(BL14*$F36,0) -> 0 | BM36: =IFERROR(BM14*$F36,0) -> 0 | BN36: =SUM(BJ36:BM36) -> 0
A37: =A15 -> 0 | B37: =B15 -> 0 | C37: =C15 -> 0 | D37: =D15 -> 0 | E37: =E15 -> 0 | F37: ='Customer''s Questionnaire'!N50 -> 0 | G37: =IFERROR(G15*$F37,0) -> 0 | H37: =IFERROR(H15*$F37,0) -> 0 | I37: =IFERROR(I15*$F37,0) -> 0 | J37: =IFERROR(J15*$F37,0) -> 0 | K37: =SUM(G37:J37) -> 0 | L37: =IFERROR(L15*$F37,0) -> 0 | M37: =IFERROR(M15*$F37,0) -> 0 | N37: =IFERROR(N15*$F37,0) -> 0 | O37: =IFERROR(O15*$F37,0) -> 0 | P37: =SUM(L37:O37) -> 0 | Q37: =IFERROR(Q15*$F37,0) -> 0 | R37: =IFERROR(R15*$F37,0) -> 0 | S37: =IFERROR(S15*$F37,0) -> 0 | T37: =IFERROR(T15*$F37,0) -> 0 | U37: =SUM(Q37:T37) -> 0 | V37: =IFERROR(V15*$F37,0) -> 0 | W37: =IFERROR(W15*$F37,0) -> 0 | X37: =IFERROR(X15*$F37,0) -> 0 | Y37: =IFERROR(Y15*$F37,0) -> 0 | Z37: =SUM(V37:Y37) -> 0 | AA37: =IFERROR(AA15*$F37,0) -> 0 | AB37: =IFERROR(AB15*$F37,0) -> 0 | AC37: =IFERROR(AC15*$F37,0) -> 0 | AD37: =IFERROR(AD15*$F37,0) -> 0 | AE37: =SUM(AA37:AD37) -> 0 | AF37: =IFERROR(AF15*$F37,0) -> 0 | AG37: =IFERROR(AG15*$F37,0) -> 0 | AH37: =IFERROR(AH15*$F37,0) -> 0 | AI37: =IFERROR(AI15*$F37,0) -> 0 | AJ37: =SUM(AF37:AI37) -> 0 | AK37: =IFERROR(AK15*$F37,0) -> 0 | AL37: =IFERROR(AL15*$F37,0) -> 0 | AM37: =IFERROR(AM15*$F37,0) -> 0 | AN37: =IFERROR(AN15*$F37,0) -> 0 | AO37: =SUM(AK37:AN37) -> 0 | AP37: =IFERROR(AP15*$F37,0) -> 0 | AQ37: =IFERROR(AQ15*$F37,0) -> 0 | AR37: =IFERROR(AR15*$F37,0) -> 0 | AS37: =IFERROR(AS15*$F37,0) -> 0 | AT37: =SUM(AP37:AS37) -> 0 | AU37: =IFERROR(AU15*$F37,0) -> 0 | AV37: =IFERROR(AV15*$F37,0) -> 0 | AW37: =IFERROR(AW15*$F37,0) -> 0 | AX37: =IFERROR(AX15*$F37,0) -> 0 | AY37: =SUM(AU37:AX37) -> 0 | AZ37: =IFERROR(AZ15*$F37,0) -> 0 | BA37: =IFERROR(BA15*$F37,0) -> 0 | BB37: =IFERROR(BB15*$F37,0) -> 0 | BC37: =IFERROR(BC15*$F37,0) -> 0 | BD37: =SUM(AZ37:BC37) -> 0 | BE37: =IFERROR(BE15*$F37,0) -> 0 | BF37: =IFERROR(BF15*$F37,0) -> 0 | BG37: =IFERROR(BG15*$F37,0) -> 0 | BH37: =IFERROR(BH15*$F37,0) -> 0 | BI37: =SUM(BE37:BH37) -> 0 | BJ37: =IFERROR(BJ15*$F37,0) -> 0 | BK37: =IFERROR(BK15*$F37,0) -> 0 | BL37: =IFERROR(BL15*$F37,0) -> 0 | BM37: =IFERROR(BM15*$F37,0) -> 0 | BN37: =SUM(BJ37:BM37) -> 0
A38: =A16 -> 0 | B38: =B16 -> 0 | C38: =C16 -> 0 | D38: =D16 -> 0 | E38: =E16 -> 0 | F38: ='Customer''s Questionnaire'!N51 -> 0 | G38: =IFERROR(G16*$F38,0) -> 0 | H38: =IFERROR(H16*$F38,0) -> 0 | I38: =IFERROR(I16*$F38,0) -> 0 | J38: =IFERROR(J16*$F38,0) -> 0 | K38: =SUM(G38:J38) -> 0 | L38: =IFERROR(L16*$F38,0) -> 0 | M38: =IFERROR(M16*$F38,0) -> 0 | N38: =IFERROR(N16*$F38,0) -> 0 | O38: =IFERROR(O16*$F38,0) -> 0 | P38: =SUM(L38:O38) -> 0 | Q38: =IFERROR(Q16*$F38,0) -> 0 | R38: =IFERROR(R16*$F38,0) -> 0 | S38: =IFERROR(S16*$F38,0) -> 0 | T38: =IFERROR(T16*$F38,0) -> 0 | U38: =SUM(Q38:T38) -> 0 | V38: =IFERROR(V16*$F38,0) -> 0 | W38: =IFERROR(W16*$F38,0) -> 0 | X38: =IFERROR(X16*$F38,0) -> 0 | Y38: =IFERROR(Y16*$F38,0) -> 0 | Z38: =SUM(V38:Y38) -> 0 | AA38: =IFERROR(AA16*$F38,0) -> 0 | AB38: =IFERROR(AB16*$F38,0) -> 0 | AC38: =IFERROR(AC16*$F38,0) -> 0 | AD38: =IFERROR(AD16*$F38,0) -> 0 | AE38: =SUM(AA38:AD38) -> 0 | AF38: =IFERROR(AF16*$F38,0) -> 0 | AG38: =IFERROR(AG16*$F38,0) -> 0 | AH38: =IFERROR(AH16*$F38,0) -> 0 | AI38: =IFERROR(AI16*$F38,0) -> 0 | AJ38: =SUM(AF38:AI38) -> 0 | AK38: =IFERROR(AK16*$F38,0) -> 0 | AL38: =IFERROR(AL16*$F38,0) -> 0 | AM38: =IFERROR(AM16*$F38,0) -> 0 | AN38: =IFERROR(AN16*$F38,0) -> 0 | AO38: =SUM(AK38:AN38) -> 0 | AP38: =IFERROR(AP16*$F38,0) -> 0 | AQ38: =IFERROR(AQ16*$F38,0) -> 0 | AR38: =IFERROR(AR16*$F38,0) -> 0 | AS38: =IFERROR(AS16*$F38,0) -> 0 | AT38: =SUM(AP38:AS38) -> 0 | AU38: =IFERROR(AU16*$F38,0) -> 0 | AV38: =IFERROR(AV16*$F38,0) -> 0 | AW38: =IFERROR(AW16*$F38,0) -> 0 | AX38: =IFERROR(AX16*$F38,0) -> 0 | AY38: =SUM(AU38:AX38) -> 0 | AZ38: =IFERROR(AZ16*$F38,0) -> 0 | BA38: =IFERROR(BA16*$F38,0) -> 0 | BB38: =IFERROR(BB16*$F38,0) -> 0 | BC38: =IFERROR(BC16*$F38,0) -> 0 | BD38: =SUM(AZ38:BC38) -> 0 | BE38: =IFERROR(BE16*$F38,0) -> 0 | BF38: =IFERROR(BF16*$F38,0) -> 0 | BG38: =IFERROR(BG16*$F38,0) -> 0 | BH38: =IFERROR(BH16*$F38,0) -> 0 | BI38: =SUM(BE38:BH38) -> 0 | BJ38: =IFERROR(BJ16*$F38,0) -> 0 | BK38: =IFERROR(BK16*$F38,0) -> 0 | BL38: =IFERROR(BL16*$F38,0) -> 0 | BM38: =IFERROR(BM16*$F38,0) -> 0 | BN38: =SUM(BJ38:BM38) -> 0
A39: =A17 -> 0 | B39: =B17 -> 0 | C39: =C17 -> 0 | D39: =D17 -> 0 | E39: =E17 -> 0 | F39: ='Customer''s Questionnaire'!N52 -> 0 | G39: =IFERROR(G17*$F39,0) -> 0 | H39: =IFERROR(H17*$F39,0) -> 0 | I39: =IFERROR(I17*$F39,0) -> 0 | J39: =IFERROR(J17*$F39,0) -> 0 | K39: =SUM(G39:J39) -> 0 | L39: =IFERROR(L17*$F39,0) -> 0 | M39: =IFERROR(M17*$F39,0) -> 0 | N39: =IFERROR(N17*$F39,0) -> 0 | O39: =IFERROR(O17*$F39,0) -> 0 | P39: =SUM(L39:O39) -> 0 | Q39: =IFERROR(Q17*$F39,0) -> 0 | R39: =IFERROR(R17*$F39,0) -> 0 | S39: =IFERROR(S17*$F39,0) -> 0 | T39: =IFERROR(T17*$F39,0) -> 0 | U39: =SUM(Q39:T39) -> 0 | V39: =IFERROR(V17*$F39,0) -> 0 | W39: =IFERROR(W17*$F39,0) -> 0 | X39: =IFERROR(X17*$F39,0) -> 0 | Y39: =IFERROR(Y17*$F39,0) -> 0 | Z39: =SUM(V39:Y39) -> 0 | AA39: =IFERROR(AA17*$F39,0) -> 0 | AB39: =IFERROR(AB17*$F39,0) -> 0 | AC39: =IFERROR(AC17*$F39,0) -> 0 | AD39: =IFERROR(AD17*$F39,0) -> 0 | AE39: =SUM(AA39:AD39) -> 0 | AF39: =IFERROR(AF17*$F39,0) -> 0 | AG39: =IFERROR(AG17*$F39,0) -> 0 | AH39: =IFERROR(AH17*$F39,0) -> 0 | AI39: =IFERROR(AI17*$F39,0) -> 0 | AJ39: =SUM(AF39:AI39) -> 0 | AK39: =IFERROR(AK17*$F39,0) -> 0 | AL39: =IFERROR(AL17*$F39,0) -> 0 | AM39: =IFERROR(AM17*$F39,0) -> 0 | AN39: =IFERROR(AN17*$F39,0) -> 0 | AO39: =SUM(AK39:AN39) -> 0 | AP39: =IFERROR(AP17*$F39,0) -> 0 | AQ39: =IFERROR(AQ17*$F39,0) -> 0 | AR39: =IFERROR(AR17*$F39,0) -> 0 | AS39: =IFERROR(AS17*$F39,0) -> 0 | AT39: =SUM(AP39:AS39) -> 0 | AU39: =IFERROR(AU17*$F39,0) -> 0 | AV39: =IFERROR(AV17*$F39,0) -> 0 | AW39: =IFERROR(AW17*$F39,0) -> 0 | AX39: =IFERROR(AX17*$F39,0) -> 0 | AY39: =SUM(AU39:AX39) -> 0 | AZ39: =IFERROR(AZ17*$F39,0) -> 0 | BA39: =IFERROR(BA17*$F39,0) -> 0 | BB39: =IFERROR(BB17*$F39,0) -> 0 | BC39: =IFERROR(BC17*$F39,0) -> 0 | BD39: =SUM(AZ39:BC39) -> 0 | BE39: =IFERROR(BE17*$F39,0) -> 0 | BF39: =IFERROR(BF17*$F39,0) -> 0 | BG39: =IFERROR(BG17*$F39,0) -> 0 | BH39: =IFERROR(BH17*$F39,0) -> 0 | BI39: =SUM(BE39:BH39) -> 0 | BJ39: =IFERROR(BJ17*$F39,0) -> 0 | BK39: =IFERROR(BK17*$F39,0) -> 0 | BL39: =IFERROR(BL17*$F39,0) -> 0 | BM39: =IFERROR(BM17*$F39,0) -> 0 | BN39: =SUM(BJ39:BM39) -> 0
A40: =A18 -> 0 | B40: =B18 -> 0 | C40: =C18 -> 0 | D40: =D18 -> 0 | E40: =E18 -> 0 | F40: ='Customer''s Questionnaire'!N53 -> 0 | G40: =IFERROR(G18*$F40,0) -> 0 | H40: =IFERROR(H18*$F40,0) -> 0 | I40: =IFERROR(I18*$F40,0) -> 0 | J40: =IFERROR(J18*$F40,0) -> 0 | K40: =SUM(G40:J40) -> 0 | L40: =IFERROR(L18*$F40,0) -> 0 | M40: =IFERROR(M18*$F40,0) -> 0 | N40: =IFERROR(N18*$F40,0) -> 0 | O40: =IFERROR(O18*$F40,0) -> 0 | P40: =SUM(L40:O40) -> 0 | Q40: =IFERROR(Q18*$F40,0) -> 0 | R40: =IFERROR(R18*$F40,0) -> 0 | S40: =IFERROR(S18*$F40,0) -> 0 | T40: =IFERROR(T18*$F40,0) -> 0 | U40: =SUM(Q40:T40) -> 0 | V40: =IFERROR(V18*$F40,0) -> 0 | W40: =IFERROR(W18*$F40,0) -> 0 | X40: =IFERROR(X18*$F40,0) -> 0 | Y40: =IFERROR(Y18*$F40,0) -> 0 | Z40: =SUM(V40:Y40) -> 0 | AA40: =IFERROR(AA18*$F40,0) -> 0 | AB40: =IFERROR(AB18*$F40,0) -> 0 | AC40: =IFERROR(AC18*$F40,0) -> 0 | AD40: =IFERROR(AD18*$F40,0) -> 0 | AE40: =SUM(AA40:AD40) -> 0 | AF40: =IFERROR(AF18*$F40,0) -> 0 | AG40: =IFERROR(AG18*$F40,0) -> 0 | AH40: =IFERROR(AH18*$F40,0) -> 0 | AI40: =IFERROR(AI18*$F40,0) -> 0 | AJ40: =SUM(AF40:AI40) -> 0 | AK40: =IFERROR(AK18*$F40,0) -> 0 | AL40: =IFERROR(AL18*$F40,0) -> 0 | AM40: =IFERROR(AM18*$F40,0) -> 0 | AN40: =IFERROR(AN18*$F40,0) -> 0 | AO40: =SUM(AK40:AN40) -> 0 | AP40: =IFERROR(AP18*$F40,0) -> 0 | AQ40: =IFERROR(AQ18*$F40,0) -> 0 | AR40: =IFERROR(AR18*$F40,0) -> 0 | AS40: =IFERROR(AS18*$F40,0) -> 0 | AT40: =SUM(AP40:AS40) -> 0 | AU40: =IFERROR(AU18*$F40,0) -> 0 | AV40: =IFERROR(AV18*$F40,0) -> 0 | AW40: =IFERROR(AW18*$F40,0) -> 0 | AX40: =IFERROR(AX18*$F40,0) -> 0 | AY40: =SUM(AU40:AX40) -> 0 | AZ40: =IFERROR(AZ18*$F40,0) -> 0 | BA40: =IFERROR(BA18*$F40,0) -> 0 | BB40: =IFERROR(BB18*$F40,0) -> 0 | BC40: =IFERROR(BC18*$F40,0) -> 0 | BD40: =SUM(AZ40:BC40) -> 0 | BE40: =IFERROR(BE18*$F40,0) -> 0 | BF40: =IFERROR(BF18*$F40,0) -> 0 | BG40: =IFERROR(BG18*$F40,0) -> 0 | BH40: =IFERROR(BH18*$F40,0) -> 0 | BI40: =SUM(BE40:BH40) -> 0 | BJ40: =IFERROR(BJ18*$F40,0) -> 0 | BK40: =IFERROR(BK18*$F40,0) -> 0 | BL40: =IFERROR(BL18*$F40,0) -> 0 | BM40: =IFERROR(BM18*$F40,0) -> 0 | BN40: =SUM(BJ40:BM40) -> 0
A41: =A19 -> 0 | B41: =B19 -> 0 | C41: =C19 -> 0 | D41: =D19 -> 0 | E41: =E19 -> 0 | F41: ='Customer''s Questionnaire'!N54 -> 0 | G41: =IFERROR(G19*$F41,0) -> 0 | H41: =IFERROR(H19*$F41,0) -> 0 | I41: =IFERROR(I19*$F41,0) -> 0 | J41: =IFERROR(J19*$F41,0) -> 0 | K41: =SUM(G41:J41) -> 0 | L41: =IFERROR(L19*$F41,0) -> 0 | M41: =IFERROR(M19*$F41,0) -> 0 | N41: =IFERROR(N19*$F41,0) -> 0 | O41: =IFERROR(O19*$F41,0) -> 0 | P41: =SUM(L41:O41) -> 0 | Q41: =IFERROR(Q19*$F41,0) -> 0 | R41: =IFERROR(R19*$F41,0) -> 0 | S41: =IFERROR(S19*$F41,0) -> 0 | T41: =IFERROR(T19*$F41,0) -> 0 | U41: =SUM(Q41:T41) -> 0 | V41: =IFERROR(V19*$F41,0) -> 0 | W41: =IFERROR(W19*$F41,0) -> 0 | X41: =IFERROR(X19*$F41,0) -> 0 | Y41: =IFERROR(Y19*$F41,0) -> 0 | Z41: =SUM(V41:Y41) -> 0 | AA41: =IFERROR(AA19*$F41,0) -> 0 | AB41: =IFERROR(AB19*$F41,0) -> 0 | AC41: =IFERROR(AC19*$F41,0) -> 0 | AD41: =IFERROR(AD19*$F41,0) -> 0 | AE41: =SUM(AA41:AD41) -> 0 | AF41: =IFERROR(AF19*$F41,0) -> 0 | AG41: =IFERROR(AG19*$F41,0) -> 0 | AH41: =IFERROR(AH19*$F41,0) -> 0 | AI41: =IFERROR(AI19*$F41,0) -> 0 | AJ41: =SUM(AF41:AI41) -> 0 | AK41: =IFERROR(AK19*$F41,0) -> 0 | AL41: =IFERROR(AL19*$F41,0) -> 0 | AM41: =IFERROR(AM19*$F41,0) -> 0 | AN41: =IFERROR(AN19*$F41,0) -> 0 | AO41: =SUM(AK41:AN41) -> 0 | AP41: =IFERROR(AP19*$F41,0) -> 0 | AQ41: =IFERROR(AQ19*$F41,0) -> 0 | AR41: =IFERROR(AR19*$F41,0) -> 0 | AS41: =IFERROR(AS19*$F41,0) -> 0 | AT41: =SUM(AP41:AS41) -> 0 | AU41: =IFERROR(AU19*$F41,0) -> 0 | AV41: =IFERROR(AV19*$F41,0) -> 0 | AW41: =IFERROR(AW19*$F41,0) -> 0 | AX41: =IFERROR(AX19*$F41,0) -> 0 | AY41: =SUM(AU41:AX41) -> 0 | AZ41: =IFERROR(AZ19*$F41,0) -> 0 | BA41: =IFERROR(BA19*$F41,0) -> 0 | BB41: =IFERROR(BB19*$F41,0) -> 0 | BC41: =IFERROR(BC19*$F41,0) -> 0 | BD41: =SUM(AZ41:BC41) -> 0 | BE41: =IFERROR(BE19*$F41,0) -> 0 | BF41: =IFERROR(BF19*$F41,0) -> 0 | BG41: =IFERROR(BG19*$F41,0) -> 0 | BH41: =IFERROR(BH19*$F41,0) -> 0 | BI41: =SUM(BE41:BH41) -> 0 | BJ41: =IFERROR(BJ19*$F41,0) -> 0 | BK41: =IFERROR(BK19*$F41,0) -> 0 | BL41: =IFERROR(BL19*$F41,0) -> 0 | BM41: =IFERROR(BM19*$F41,0) -> 0 | BN41: =SUM(BJ41:BM41) -> 0
A42: =A20 -> 0 | B42: =B20 -> 0 | C42: =C20 -> 0 | D42: =D20 -> 0 | E42: =E20 -> 0 | F42: ='Customer''s Questionnaire'!N55 -> 0 | G42: =IFERROR(G20*$F42,0) -> 0 | H42: =IFERROR(H20*$F42,0) -> 0 | I42: =IFERROR(I20*$F42,0) -> 0 | J42: =IFERROR(J20*$F42,0) -> 0 | K42: =SUM(G42:J42) -> 0 | L42: =IFERROR(L20*$F42,0) -> 0 | M42: =IFERROR(M20*$F42,0) -> 0 | N42: =IFERROR(N20*$F42,0) -> 0 | O42: =IFERROR(O20*$F42,0) -> 0 | P42: =SUM(L42:O42) -> 0 | Q42: =IFERROR(Q20*$F42,0) -> 0 | R42: =IFERROR(R20*$F42,0) -> 0 | S42: =IFERROR(S20*$F42,0) -> 0 | T42: =IFERROR(T20*$F42,0) -> 0 | U42: =SUM(Q42:T42) -> 0 | V42: =IFERROR(V20*$F42,0) -> 0 | W42: =IFERROR(W20*$F42,0) -> 0 | X42: =IFERROR(X20*$F42,0) -> 0 | Y42: =IFERROR(Y20*$F42,0) -> 0 | Z42: =SUM(V42:Y42) -> 0 | AA42: =IFERROR(AA20*$F42,0) -> 0 | AB42: =IFERROR(AB20*$F42,0) -> 0 | AC42: =IFERROR(AC20*$F42,0) -> 0 | AD42: =IFERROR(AD20*$F42,0) -> 0 | AE42: =SUM(AA42:AD42) -> 0 | AF42: =IFERROR(AF20*$F42,0) -> 0 | AG42: =IFERROR(AG20*$F42,0) -> 0 | AH42: =IFERROR(AH20*$F42,0) -> 0 | AI42: =IFERROR(AI20*$F42,0) -> 0 | AJ42: =SUM(AF42:AI42) -> 0 | AK42: =IFERROR(AK20*$F42,0) -> 0 | AL42: =IFERROR(AL20*$F42,0) -> 0 | AM42: =IFERROR(AM20*$F42,0) -> 0 | AN42: =IFERROR(AN20*$F42,0) -> 0 | AO42: =SUM(AK42:AN42) -> 0 | AP42: =IFERROR(AP20*$F42,0) -> 0 | AQ42: =IFERROR(AQ20*$F42,0) -> 0 | AR42: =IFERROR(AR20*$F42,0) -> 0 | AS42: =IFERROR(AS20*$F42,0) -> 0 | AT42: =SUM(AP42:AS42) -> 0 | AU42: =IFERROR(AU20*$F42,0) -> 0 | AV42: =IFERROR(AV20*$F42,0) -> 0 | AW42: =IFERROR(AW20*$F42,0) -> 0 | AX42: =IFERROR(AX20*$F42,0) -> 0 | AY42: =SUM(AU42:AX42) -> 0 | AZ42: =IFERROR(AZ20*$F42,0) -> 0 | BA42: =IFERROR(BA20*$F42,0) -> 0 | BB42: =IFERROR(BB20*$F42,0) -> 0 | BC42: =IFERROR(BC20*$F42,0) -> 0 | BD42: =SUM(AZ42:BC42) -> 0 | BE42: =IFERROR(BE20*$F42,0) -> 0 | BF42: =IFERROR(BF20*$F42,0) -> 0 | BG42: =IFERROR(BG20*$F42,0) -> 0 | BH42: =IFERROR(BH20*$F42,0) -> 0 | BI42: =SUM(BE42:BH42) -> 0 | BJ42: =IFERROR(BJ20*$F42,0) -> 0 | BK42: =IFERROR(BK20*$F42,0) -> 0 | BL42: =IFERROR(BL20*$F42,0) -> 0 | BM42: =IFERROR(BM20*$F42,0) -> 0 | BN42: =SUM(BJ42:BM42) -> 0
... A50: =A28 -> 0 | B50: =B28 -> 0 | C50: =C28 -> 0 | D50: =D28 -> 0 | E50: =E28 -> 0 | F50: ='Customer''s Questionnaire'!N63 -> 0 | G50: =IFERROR(G28*$F50,0) -> 0 | H50: =IFERROR(H28*$F50,0) -> 0 | I50: =IFERROR(I28*$F50,0) -> 0 | J50: =IFERROR(J28*$F50,0) -> 0 | K50: =SUM(G50:J50) -> 0 | L50: =IFERROR(L28*$F50,0) -> 0 | M50: =IFERROR(M28*$F50,0) -> 0 | N50: =IFERROR(N28*$F50,0) -> 0 | O50: =IFERROR(O28*$F50,0) -> 0 | P50: =SUM(L50:O50) -> 0 | Q50: =IFERROR(Q28*$F50,0) -> 0 | R50: =IFERROR(R28*$F50,0) -> 0 | S50: =IFERROR(S28*$F50,0) -> 0 | T50: =IFERROR(T28*$F50,0) -> 0 | U50: =SUM(Q50:T50) -> 0 | V50: =IFERROR(V28*$F50,0) -> 0 | W50: =IFERROR(W28*$F50,0) -> 0 | X50: =IFERROR(X28*$F50,0) -> 0 | Y50: =IFERROR(Y28*$F50,0) -> 0 | Z50: =SUM(V50:Y50) -> 0 | AA50: =IFERROR(AA28*$F50,0) -> 0 | AB50: =IFERROR(AB28*$F50,0) -> 0 | AC50: =IFERROR(AC28*$F50,0) -> 0 | AD50: =IFERROR(AD28*$F50,0) -> 0 | AE50: =SUM(AA50:AD50) -> 0 | AF50: =IFERROR(AF28*$F50,0) -> 0 | AG50: =IFERROR(AG28*$F50,0) -> 0 | AH50: =IFERROR(AH28*$F50,0) -> 0 | AI50: =IFERROR(AI28*$F50,0) -> 0 | AJ50: =SUM(AF50:AI50) -> 0 | AK50: =IFERROR(AK28*$F50,0) -> 0 | AL50: =IFERROR(AL28*$F50,0) -> 0 | AM50: =IFERROR(AM28*$F50,0) -> 0 | AN50: =IFERROR(AN28*$F50,0) -> 0 | AO50: =SUM(AK50:AN50) -> 0 | AP50: =IFERROR(AP28*$F50,0) -> 0 | AQ50: =IFERROR(AQ28*$F50,0) -> 0 | AR50: =IFERROR(AR28*$F50,0) -> 0 | AS50: =IFERROR(AS28*$F50,0) -> 0 | AT50: =SUM(AP50:AS50) -> 0 | AU50: =IFERROR(AU28*$F50,0) -> 0 | AV50: =IFERROR(AV28*$F50,0) -> 0 | AW50: =IFERROR(AW28*$F50,0) -> 0 | AX50: =IFERROR(AX28*$F50,0) -> 0 | AY50: =SUM(AU50:AX50) -> 0 | AZ50: =IFERROR(AZ28*$F50,0) -> 0 | BA50: =IFERROR(BA28*$F50,0) -> 0 | BB50: =IFERROR(BB28*$F50,0) -> 0 | BC50: =IFERROR(BC28*$F50,0) -> 0 | BD50: =SUM(AZ50:BC50) -> 0 | BE50: =IFERROR(BE28*$F50,0) -> 0 | BF50: =IFERROR(BF28*$F50,0) -> 0 | BG50: =IFERROR(BG28*$F50,0) -> 0 | BH50: =IFERROR(BH28*$F50,0) -> 0 | BI50: =SUM(BE50:BH50) -> 0 | BJ50: =IFERROR(BJ28*$F50,0) -> 0 | BK50: =IFERROR(BK28*$F50,0) -> 0 | BL50: =IFERROR(BL28*$F50,0) -> 0 | BM50: =IFERROR(BM28*$F50,0) -> 0 | BN50: =SUM(BJ50:BM50) -> 0
A51: Total COGS | G51: =SUM(G31:G50) -> 10000 | H51: =SUM(H31:H50) -> 10000 | I51: =SUM(I31:I50) -> 10000 | J51: =SUM(J31:J50) -> 10000 | K51: =SUM(K31:K50) -> 40000 | L51: =SUM(L31:L50) -> 12500 | M51: =SUM(M31:M50) -> 12500 | N51: =SUM(N31:N50) -> 12500 | ... BN51: =SUM(BN31:BN50) -> 258105.05

Sheet OPEX
G4: Q. | H4: Q. | I4: Q. | J4: Q. | K4: Q. | L4: Q. | M4: Q. | N4: Q. | O4: Q. | P4: Q. | Q4: Q. | R4: Q. | S4: Q. | T4: Q. | U4: Q. | V4: Q. | W4: Q. | X4: Q. | Y4: Q. | Z4: Q. | AA4: Q. | AB4: Q. | AC4: Q. | AD4: Q. | AE4: Q. | AF4: Q. | AG4: Q. | AH4: Q. | AI4: Q. | AJ4: Q. | AK4: Q. | AL4: Q. | AM4: Q. | AN4: Q. | AO4: Q. | AP4: Q. | AQ4: Q. | AR4: Q. | AS4: Q. | AT4: Q. | AU4: Q. | AV4: Q. | AW4: Q. | AX4: Q. | AY4: Q. | AZ4: Q. | BA4: Q. | BB4: Q. | BC4: Q. | BD4: Q. | BE4: Q. | BF4: Q. | BG4: Q. | BH4: Q. | BI4: Q. | BJ4: Q. | BK4: Q. | BL4: Q. | BM4: Q. | BN4: Q.
A5: Period | F5: Input / Annual | G5: ='Rev. Build'!G10 -> Q1-2026 | H5: ='Rev. Build'!H10 -> Q2-2026 | I5: ='Rev. Build'!I10 -> Q3-2026 | J5: ='Rev. Build'!J10 -> Q4-2026 | K5: ='Rev. Build'!K10 -> 2026 | L5: ='Rev. Build'!L10 -> Q1-2027 | M5: ='Rev. Build'!M10 -> Q2-2027 | N5: ='Rev. Build'!N10 -> Q3-2027 | ... BN5: ='Rev. Build'!BN10 -> 2037
A6: R&D — Operating Expenses
A7: Selected Stage | F7: ='Customer''s Questionnaire'!I9 -> Round C | G7: ='Customer''s Questionnaire'!$I$9 -> Round C | L7: =IFERROR(_xlfn.XLOOKUP($F$8&L9,Benchmark_Table!$F:$F,Benchmark_Table!$B:$B,G7),G7) -> Series C | Q7: =IFERROR(_xlfn.XLOOKUP($F$8&Q9,Benchmark_Table!$F:$F,Benchmark_Table!$B:$B,L7),L7) -> Series C | V7: =IFERROR(_xlfn.XLOOKUP($F$8&V9,Benchmark_Table!$F:$F,Benchmark_Table!$B:$B,Q7),Q7) -> Series D/E | AA7: =IFERROR(_xlfn.XLOOKUP($F$8&AA9,Benchmark_Table!$F:$F,Benchmark_Table!$B:$B,V7),V7) -> Pre-IPO | AF7: =IFERROR(_xlfn.XLOOKUP($F$8&AF9,Benchmark_Table!$F:$F,Benchmark_Table!$B:$B,AA7),AA7) -> Pre-IPO | AK7: =IFERROR(_xlfn.XLOOKUP($F$8&AK9,Benchmark_Table!$F:$F,Benchmark_Table!$B:$B,AF7),AF7) -> Pre-IPO | AP7: =IFERROR(_xlfn.XLOOKUP($F$8&AP9,Benchmark_Table!$F:$F,Benchmark_Table!$B:$B,AK7),AK7) -> Pre-IPO | AU7: =IFERROR(_xlfn.XLOOKUP($F$8&AU9,Benchmark_Table!$F:$F,Benchmark_Table!$B:$B,AP7),AP7) -> Pre-IPO | AZ7: =IFERROR(_xlfn.XLOOKUP($F$8&AZ9,Benchmark_Table!$F:$F,Benchmark_Table!$B:$B,AU7),AU7) -> Pre-IPO | BE7: =IFERROR(_xlfn.XLOOKUP($F$8&BE9,Benchmark_Table!$F:$F,Benchmark_Table!$B:$B,AZ7),AZ7) -> Pre-IPO | BJ7: =IFERROR(_xlfn.XLOOKUP($F$8&BJ9,Benchmark_Table!$F:$F,Benchmark_Table!$B:$B,BE7),BE7) -> Pre-IPO
A8: Selected Sector | F8: ='Customer''s Questionnaire'!I8 -> Food-Tech / Ag-Tech | G8: ='Customer''s Questionnaire'!$I$8 -> Food-Tech / Ag-Tech | L8: =G8 -> Food-Tech / Ag-Tech | Q8: =L8 -> Food-Tech / Ag-Tech | V8: =Q8 -> Food-Tech / Ag-Tech | AA8: =V8 -> Food-Tech / Ag-Tech | AF8: =AA8 -> Food-Tech / Ag-Tech | AK8: =AF8 -> Food-Tech / Ag-Tech | AP8: =AK8 -> Food-Tech / Ag-Tech | AU8: =AP8 -> Food-Tech / Ag-Tech | AZ8: =AU8 -> Food-Tech / Ag-Tech | BE8: =AZ8 -> Food-Tech / Ag-Tech | BJ8: =BE8 -> Food-Tech / Ag-Tech
A9: Avg_Years_Since_Founding | F9: ='Customer''s Questionnaire'!$I$11 -> 7 | G9: ='Customer''s Questionnaire'!$I$11 -> 7 | L9: =G9+1 -> 8 | Q9: =L9+1 -> 9 | V9: =Q9+1 -> 10 | AA9: =V9+1 -> 11 | AF9: =AA9+1 -> 12 | AK9: =AF9+1 -> 13 | AP9: =AK9+1 -> 14 | AU9: =AP9+1 -> 15 | AZ9: =AU9+1 -> 16 | BE9: =AZ9+1 -> 17 | BJ9: =BE9+1 -> 18
A10: OPEX Benchmark | F10: ='Customer''s Questionnaire'!$J$10 -> Too High | G10: ='Customer''s Questionnaire'!$J$10 -> Too High | L10: =G10 -> Too High | Q10: =L10 -> Too High | V10: =Q10 -> Too High | AA10: =V10 -> Too High | AF10: =AA10 -> Too High | AK10: =AF10 -> Too High | AP10: =AK10 -> Too High | AU10: =AP10 -> Too High | AZ10: =AU10 -> Too High | BE10: =AZ10 -> Too High | BJ10: =BE10 -> Too High
A11: Applied R&D Growth % | G11: =_xlfn.IFNA(IFERROR(INDEX(Benchmark_Table!$H$2:$BL$136,MATCH(G8&G7&G9,Benchmark_Table!$G$2:$G$136,0),MATCH(IF(OR(G10="Too Low",G10="Low"),"R&D_Growth_Low",IF(OR(G10="Too High",G10="High"),"R&D_Growth_High","R&D_Growth_Base")),Benchmark_Table!$H$1:$BL$1,0))*1,0),0) -> 0 | H11: =_xlfn.IFNA(IFERROR(INDEX(Benchmark_Table!$H$2:$BL$136,MATCH(G8&G7&G9,Benchmark_Table!$G$2:$G$136,0),MATCH(IF(OR(G10="Too Low",G10="Low"),"R&D_Growth_Low",IF(OR(G10="Too High",G10="High"),"R&D_Growth_High","R&D_Growth_Base")),Benchmark_Table!$H$1:$BL$1,0))*1,0),0) -> 0 | I11: =_xlfn.IFNA(IFERROR(INDEX(Benchmark_Table!$H$2:$BL$136,MATCH(G8&G7&G9,Benchmark_Table!$G$2:$G$136,0),MATCH(IF(OR(G10="Too Low",G10="Low"),"R&D_Growth_Low",IF(OR(G10="Too High",G10="High"),"R&D_Growth_High","R&D_Growth_Base")),Benchmark_Table!$H$1:$BL$1,0))*1,0),0) -> 0 | J11: =_xlfn.IFNA(IFERROR(INDEX(Benchmark_Table!$H$2:$BL$136,MATCH(G8&G7&G9,Benchmark_Table!$G$2:$G$136,0),MATCH(IF(OR(G10="Too Low",G10="Low"),"R&D_Growth_Low",IF(OR(G10="Too High",G10="High"),"R&D_Growth_High","R&D_Growth_Base")),Benchmark_Table!$H$1:$BL$1,0))*1,0),0) -> 0 | K11: =_xlfn.IFNA(IFERROR(INDEX(Benchmark_Table!$H$2:$BL$136,MATCH(G8&G7&G9,Benchmark_Table!$G$2:$G$136,0),MATCH(IF(OR(G10="Too Low",G10="Low"),"R&D_Growth_Low",IF(OR(G10="Too High",G10="High"),"R&D_Growth_High","R&D_Growth_Base")),Benchmark_Table!$H$1:$BL$1,0))*1,0),0) -> 0 | L11: =_xlfn.IFNA(IFERROR(INDEX(Benchmark_Table!$H$2:$BL$136,MATCH(L8&L7&L9,Benchmark_Table!$G$2:$G$136,0),MATCH(IF(OR(L10="Too Low",L10="Low"),"R&D_Growth_Low",IF(OR(L10="Too High",L10="High"),"R&D_Growth_High","R&D_Growth_Base")),Benchmark_Table!$H$1:$BL$1,0))*1,G11),G11) -> 0.33 | M11: =_xlfn.IFNA(IFERROR(INDEX(Benchmark_Table!$H$2:$BL$136,MATCH(L8&L7&L9,Benchmark_Table!$G$2:$G$136,0),MATCH(IF(OR(L10="Too Low",L10="Low"),"R&D_Growth_Low",IF(OR(L10="Too High",L10="High"),"R&D_Growth_High","R&D_Growth_Base")),Benchmark_Table!$H$1:$BL$1,0))*1,G11),G11) -> 0.33 | N11: =_xlfn.IFNA(IFERROR(INDEX(Benchmark_Table!$H$2:$BL$136,MATCH(L8&L7&L9,Benchmark_Table!$G$2:$G$136,0),MATCH(IF(OR(L10="Too Low",L10="Low"),"R&D_Growth_Low",IF(OR(L10="Too High",L10="High"),"R&D_Growth_High","R&D_Growth_Base")),Benchmark_Table!$H$1:$BL$1,0))*1,G11),G11) -> 0.33 | O11: =_xlfn.IFNA(IFERROR(INDEX(Benchmark_Table!$H$2:$BL$136,MATCH(L8&L7&L9,Benchmark_Table!$G$2:$G$136,0),MATCH(IF(OR(L10="Too Low",L10="Low"),"R&D_Growth_Low",IF(OR(L10="Too High",L10="High"),"R&D_Growth_High","R&D_Growth_Base")),Benchmark_Table!$H$1:$BL$1,0))*1,G11),G11) -> 0.33 | P11: =_xlfn.IFNA(IFERROR(INDEX(Benchmark_Table!$H$2:$BL$136,MATCH(L8&L7&L9,Benchmark_Table!$G$2:$G$136,0),MATCH(IF(OR(L10="Too Low",L10="Low"),"R&D_Growth_Low",IF(OR(L10="Too High",L10="High"),"R&D_Growth_High","R&D_Growth_Base")),Benchmark_Table!$H$1:$BL$1,0))*1,G11),G11) -> 0.33 | Q11: =_xlfn.IFNA(IFERROR(INDEX(Benchmark_Table!$H$2:$BL$136,MATCH(Q8&Q7&Q9,Benchmark_Table!$G$2:$G$136,0),MATCH(IF(OR(Q10="Too Low",Q10="Low"),"R&D_Growth_Low",IF(OR(Q10="Too High",Q10="High"),"R&D_Growth_High","R&D_Growth_Base")),Benchmark_Table!$H$1:$BL$1,0))*1,L11),L11) -> 0.33 | R11: =_xlfn.IFNA(IFERROR(INDEX(Benchmark_Table!$H$2:$BL$136,MATCH(Q8&Q7&Q9,Benchmark_Table!$G$2:$G$136,0),MATCH(IF(OR(Q10="Too Low",Q10="Low"),"R&D_Growth_Low",IF(OR(Q10="Too High",Q10="High"),"R&D_Growth_High","R&D_Growth_Base")),Benchmark_Table!$H$1:$BL$1,0))*1,L11),L11) -> 0.33 | S11: =_xlfn.IFNA(IFERROR(INDEX(Benchmark_Table!$H$2:$BL$136,MATCH(Q8&Q7&Q9,Benchmark_Table!$G$2:$G$136,0),MATCH(IF(OR(Q10="Too Low",Q10="Low"),"R&D_Growth_Low",IF(OR(Q10="Too High",Q10="High"),"R&D_Growth_High","R&D_Growth_Base")),Benchmark_Table!$H$1:$BL$1,0))*1,L11),L11) -> 0.33 | T11: =_xlfn.IFNA(IFERROR(INDEX(Benchmark_Table!$H$2:$BL$136,MATCH(Q8&Q7&Q9,Benchmark_Table!$G$2:$G$136,0),MATCH(IF(OR(Q10="Too Low",Q10="Low"),"R&D_Growth_Low",IF(OR(Q10="Too High",Q10="High"),"R&D_Growth_High","R&D_Growth_Base")),Benchmark_Table!$H$1:$BL$1,0))*1,L11),L11) -> 0.33 | U11: =_xlfn.IFNA(IFERROR(INDEX(Benchmark_Table!$H$2:$BL$136,MATCH(Q8&Q7&Q9,Benchmark_Table!$G$2:$G$136,0),MATCH(IF(OR(Q10="Too Low",Q10="Low"),"R&D_Growth_Low",IF(OR(Q10="Too High",Q10="High"),"R&D_Growth_High","R&D_Growth_Base")),Benchmark_Table!$H$1:$BL$1,0))*1,L11),L11) -> 0.33 | V11: =_xlfn.IFNA(IFERROR(INDEX(Benchmark_Table!$H$2:$BL$136,MATCH(V8&V7&V9,Benchmark_Table!$G$2:$G$136,0),MATCH(IF(OR(V10="Too Low",V10="Low"),"R&D_Growth_Low",IF(OR(V10="Too High",V10="High"),"R&D_Growth_High","R&D_Growth_Base")),Benchmark_Table!$H$1:$BL$1,0))*1,Q11),Q11) -> 0.28 | W11: =_xlfn.IFNA(IFERROR(INDEX(Benchmark_Table!$H$2:$BL$136,MATCH(V8&V7&V9,Benchmark_Table!$G$2:$G$136,0),MATCH(IF(OR(V10="Too Low",V10="Low"),"R&D_Growth_Low",IF(OR(V10="Too High",V10="High"),"R&D_Growth_High","R&D_Growth_Base")),Benchmark_Table!$H$1:$BL$1,0))*1,Q11),Q11) -> 0.28 | X11: =_xlfn.IFNA(IFERROR(INDEX(Benchmark_Table!$H$2:$BL$136,MATCH(V8&V7&V9,Benchmark_Table!$G$2:$G$136,0),MATCH(IF(OR(V10="Too Low",V10="Low"),"R&D_Growth_Low",IF(OR(V10="Too High",V10="High"),"R&D_Growth_High","R&D_Growth_Base")),Benchmark_Table!$H$1:$BL$1,0))*1,Q11),Q11) -> 0.28 | Y11: =_xlfn.IFNA(IFERROR(INDEX(Benchmark_Table!$H$2:$BL$136,MATCH(V8&V7&V9,Benchmark_Table!$G$2:$G$136,0),MATCH(IF(OR(V10="Too Low",V10="Low"),"R&D_Growth_Low",IF(OR(V10="Too High",V10="High"),"R&D_Growth_High","R&D_Growth_Base")),Benchmark_Table!$H$1:$BL$1,0))*1,Q11),Q11) -> 0.28 | Z11: =_xlfn.IFNA(IFERROR(INDEX(Benchmark_Table!$H$2:$BL$136,MATCH(V8&V7&V9,Benchmark_Table!$G$2:$G$136,0),MATCH(IF(OR(V10="Too Low",V10="Low"),"R&D_Growth_Low",IF(OR(V10="Too High",V10="High"),"R&D_Growth_High","R&D_Growth_Base")),Benchmark_Table!$H$1:$BL$1,0))*1,Q11),Q11) -> 0.28 | AA11: =_xlfn.IFNA(IFERROR(INDEX(Benchmark_Table!$H$2:$BL$136,MATCH(AA8&AA7&AA9,Benchmark_Table!$G$2:$G$136,0),MATCH(IF(OR(AA10="Too Low",AA10="Low"),"R&D_Growth_Low",IF(OR(AA10="Too High",AA10="High"),"R&D_Growth_High","R&D_Growth_Base")),Benchmark_Table!$H$1:$BL$1,0))*1,V11),V11) -> 0.2 | AB11: =_xlfn.IFNA(IFERROR(INDEX(Benchmark_Table!$H$2:$BL$136,MATCH(AA8&AA7&AA9,Benchmark_Table!$G$2:$G$136,0),MATCH(IF(OR(AA10="Too Low",AA10="Low"),"R&D_Growth_Low",IF(OR(AA10="Too High",AA10="High"),"R&D_Growth_High","R&D_Growth_Base")),Benchmark_Table!$H$1:$BL$1,0))*1,V11),V11) -> 0.2 | AC11: =_xlfn.IFNA(IFERROR(INDEX(Benchmark_Table!$H$2:$BL$136,MATCH(AA8&AA7&AA9,Benchmark_Table!$G$2:$G$136,0),MATCH(IF(OR(AA10="Too Low",AA10="Low"),"R&D_Growth_Low",IF(OR(AA10="Too High",AA10="High"),"R&D_Growth_High","R&D_Growth_Base")),Benchmark_Table!$H$1:$BL$1,0))*1,V11),V11) -> 0.2 | AD11: =_xlfn.IFNA(IFERROR(INDEX(Benchmark_Table!$H$2:$BL$136,MATCH(AA8&AA7&AA9,Benchmark_Table!$G$2:$G$136,0),MATCH(IF(OR(AA10="Too Low",AA10="Low"),"R&D_Growth_Low",IF(OR(AA10="Too High",AA10="High"),"R&D_Growth_High","R&D_Growth_Base")),Benchmark_Table!$H$1:$BL$1,0))*1,V11),V11) -> 0.2 | AE11: =_xlfn.IFNA(IFERROR(INDEX(Benchmark_Table!$H$2:$BL$136,MATCH(AA8&AA7&AA9,Benchmark_Table!$G$2:$G$136,0),MATCH(IF(OR(AA10="Too Low",AA10="Low"),"R&D_Growth_Low",IF(OR(AA10="Too High",AA10="High"),"R&D_Growth_High","R&D_Growth_Base")),Benchmark_Table!$H$1:$BL$1,0))*1,V11),V11) -> 0.2 | AF11: =_xlfn.IFNA(IFERROR(INDEX(Benchmark_Table!$H$2:$BL$136,MATCH(AF8&AF7&AF9,Benchmark_Table!$G$2:$G$136,0),MATCH(IF(OR(AF10="Too Low",AF10="Low"),"R&D_Growth_Low",IF(OR(AF10="Too High",AF10="High"),"R&D_Growth_High","R&D_Growth_Base")),Benchmark_Table!$H$1:$BL$1,0))*1,AA11),AA11) -> 0.2 | AG11: =_xlfn.IFNA(IFERROR(INDEX(Benchmark_Table!$H$2:$BL$136,MATCH(AF8&AF7&AF9,Benchmark_Table!$G$2:$G$136,0),MATCH(IF(OR(AF10="Too Low",AF10="Low"),"R&D_Growth_Low",IF(OR(AF10="Too High",AF10="High"),"R&D_Growth_High","R&D_Growth_Base")),Benchmark_Table!$H$1:$BL$1,0))*1,AA11),AA11) -> 0.2 | AH11: =_xlfn.IFNA(IFERROR(INDEX(Benchmark_Table!$H$2:$BL$136,MATCH(AF8&AF7&AF9,Benchmark_Table!$G$2:$G$136,0),MATCH(IF(OR(AF10="Too Low",AF10="Low"),"R&D_Growth_Low",IF(OR(AF10="Too High",AF10="High"),"R&D_Growth_High","R&D_Growth_Base")),Benchmark_Table!$H$1:$BL$1,0))*1,AA11),AA11) -> 0.2 | AI11: =_xlfn.IFNA(IFERROR(INDEX(Benchmark_Table!$H$2:$BL$136,MATCH(AF8&AF7&AF9,Benchmark_Table!$G$2:$G$136,0),MATCH(IF(OR(AF10="Too Low",AF10="Low"),"R&D_Growth_Low",IF(OR(AF10="Too High",AF10="High"),"R&D_Growth_High","R&D_Growth_Base")),Benchmark_Table!$H$1:$BL$1,0))*1,AA11),AA11) -> 0.2 | AJ11: =_xlfn.IFNA(IFERROR(INDEX(Benchmark_Table!$H$2:$BL$136,MATCH(AF8&AF7&AF9,Benchmark_Table!$G$2:$G$136,0),MATCH(IF(OR(AF10="Too Low",AF10="Low"),"R&D_Growth_Low",IF(OR(AF10="Too High",AF10="High"),"R&D_Growth_High","R&D_Growth_Base")),Benchmark_Table!$H$1:$BL$1,0))*1,AA11),AA11) -> 0.2 | AK11: =_xlfn.IFNA(IFERROR(INDEX(Benchmark_Table!$H$2:$BL$136,MATCH(AK8&AK7&AK9,Benchmark_Table!$G$2:$G$136,0),MATCH(IF(OR(AK10="Too Low",AK10="Low"),"R&D_Growth_Low",IF(OR(AK10="Too High",AK10="High"),"R&D_Growth_High","R&D_Growth_Base")),Benchmark_Table!$H$1:$BL$1,0))*1,AF11),AF11) -> 0.2 | AL11: =_xlfn.IFNA(IFERROR(INDEX(Benchmark_Table!$H$2:$BL$136,MATCH(AK8&AK7&AK9,Benchmark_Table!$G$2:$G$136,0),MATCH(IF(OR(AK10="Too Low",AK10="Low"),"R&D_Growth_Low",IF(OR(AK10="Too High",AK10="High"),"R&D_Growth_High","R&D_Growth_Base")),Benchmark_Table!$H$1:$BL$1,0))*1,AF11),AF11) -> 0.2 | AM11: =_xlfn.IFNA(IFERROR(INDEX(Benchmark_Table!$H$2:$BL$136,MATCH(AK8&AK7&AK9,Benchmark_Table!$G$2:$G$136,0),MATCH(IF(OR(AK10="Too Low",AK10="Low"),"R&D_Growth_Low",IF(OR(AK10="Too High",AK10="High"),"R&D_Growth_High","R&D_Growth_Base")),Benchmark_Table!$H$1:$BL$1,0))*1,AF11),AF11) -> 0.2 | AN11: =_xlfn.IFNA(IFERROR(INDEX(Benchmark_Table!$H$2:$BL$136,MATCH(AK8&AK7&AK9,Benchmark_Table!$G$2:$G$136,0),MATCH(IF(OR(AK10="Too Low",AK10="Low"),"R&D_Growth_Low",IF(OR(AK10="Too High",AK10="High"),"R&D_Growth_High","R&D_Growth_Base")),Benchmark_Table!$H$1:$BL$1,0))*1,AF11),AF11) -> 0.2 | AO11: =_xlfn.IFNA(IFERROR(INDEX(Benchmark_Table!$H$2:$BL$136,MATCH(AK8&AK7&AK9,Benchmark_Table!$G$2:$G$136,0),MATCH(IF(OR(AK10="Too Low",AK10="Low"),"R&D_Growth_Low",IF(OR(AK10="Too High",AK10="High"),"R&D_Growth_High","R&D_Growth_Base")),Benchmark_Table!$H$1:$BL$1,0))*1,AF11),AF11) -> 0.2 | AP11: =_xlfn.IFNA(IFERROR(INDEX(Benchmark_Table!$H$2:$BL$136,MATCH(AP8&AP7&AP9,Benchmark_Table!$G$2:$G$136,0),MATCH(IF(OR(AP10="Too Low",AP10="Low"),"R&D_Growth_Low",IF(OR(AP10="Too High",AP10="High"),"R&D_Growth_High","R&D_Growth_Base")),Benchmark_Table!$H$1:$BL$1,0))*1,AK11),AK11) -> 0.2 | AQ11: =_xlfn.IFNA(IFERROR(INDEX(Benchmark_Table!$H$2:$BL$136,MATCH(AP8&AP7&AP9,Benchmark_Table!$G$2:$G$136,0),MATCH(IF(OR(AP10="Too Low",AP10="Low"),"R&D_Growth_Low",IF(OR(AP10="Too High",AP10="High"),"R&D_Growth_High","R&D_Growth_Base")),Benchmark_Table!$H$1:$BL$1,0))*1,AK11),AK11) -> 0.2 | AR11: =_xlfn.IFNA(IFERROR(INDEX(Benchmark_Table!$H$2:$BL$136,MATCH(AP8&AP7&AP9,Benchmark_Table!$G$2:$G$136,0),MATCH(IF(OR(AP10="Too Low",AP10="Low"),"R&D_Growth_Low",IF(OR(AP10="Too High",AP10="High"),"R&D_Growth_High","R&D_Growth_Base")),Benchmark_Table!$H$1:$BL$1,0))*1,AK11),AK11) -> 0.2 | AS11: =_xlfn.IFNA(IFERROR(INDEX(Benchmark_Table!$H$2:$BL$136,MATCH(AP8&AP7&AP9,Benchmark_Table!$G$2:$G$136,0),MATCH(IF(OR(AP10="Too Low",AP10="Low"),"R&D_Growth_Low",IF(OR(AP10="Too High",AP10="High"),"R&D_Growth_High","R&D_Growth_Base")),Benchmark_Table!$H$1:$BL$1,0))*1,AK11),AK11) -> 0.2 | AT11: =_xlfn.IFNA(IFERROR(INDEX(Benchmark_Table!$H$2:$BL$136,MATCH(AP8&AP7&AP9,Benchmark_Table!$G$2:$G$136,0),MATCH(IF(OR(AP10="Too Low",AP10="Low"),"R&D_Growth_Low",IF(OR(AP10="Too High",AP10="High"),"R&D_Growth_High","R&D_Growth_Base")),Benchmark_Table!$H$1:$BL$1,0))*1,AK11),AK11) -> 0.2 | AU11: =_xlfn.IFNA(IFERROR(INDEX(Benchmark_Table!$H$2:$BL$136,MATCH(AU8&AU7&AU9,Benchmark_Table!$G$2:$G$136,0),MATCH(IF(OR(AU10="Too Low",AU10="Low"),"R&D_Growth_Low",IF(OR(AU10="Too High",AU10="High"),"R&D_Growth_High","R&D_Growth_Base")),Benchmark_Table!$H$1:$BL$1,0))*1,AP11),AP11) -> 0.2 | AV11: =_xlfn.IFNA(IFERROR(INDEX(Benchmark_Table!$H$2:$BL$136,MATCH(AU8&AU7&AU9,Benchmark_Table!$G$2:$G$136,0),MATCH(IF(OR(AU10="Too Low",AU10="Low"),"R&D_Growth_Low",IF(OR(AU10="Too High",AU10="High"),"R&D_Growth_High","R&D_Growth_Base")),Benchmark_Table!$H$1:$BL$1,0))*1,AP11),AP11) -> 0.2 | AW11: =_xlfn.IFNA(IFERROR(INDEX(Benchmark_Table!$H$2:$BL$136,MATCH(AU8&AU7&AU9,Benchmark_Table!$G$2:$G$136,0),MATCH(IF(OR(AU10="Too Low",AU10="Low"),"R&D_Growth_Low",IF(OR(AU10="Too High",AU10="High"),"R&D_Growth_High","R&D_Growth_Base")),Benchmark_Table!$H$1:$BL$1,0))*1,AP11),AP11) -> 0.2 | AX11: =_xlfn.IFNA(IFERROR(INDEX(Benchmark_Table!$H$2:$BL$136,MATCH(AU8&AU7&AU9,Benchmark_Table!$G$2:$G$136,0),MATCH(IF(OR(AU10="Too Low",AU10="Low"),"R&D_Growth_Low",IF(OR(AU10="Too High",AU10="High"),"R&D_Growth_High","R&D_Growth_Base")),Benchmark_Table!$H$1:$BL$1,0))*1,AP11),AP11) -> 0.2 | AY11: =_xlfn.IFNA(IFERROR(INDEX(Benchmark_Table!$H$2:$BL$136,MATCH(AU8&AU7&AU9,Benchmark_Table!$G$2:$G$136,0),MATCH(IF(OR(AU10="Too Low",AU10="Low"),"R&D_Growth_Low",IF(OR(AU10="Too High",AU10="High"),"R&D_Growth_High","R&D_Growth_Base")),Benchmark_Table!$H$1:$BL$1,0))*1,AP11),AP11) -> 0.2 | AZ11: =_xlfn.IFNA(IFERROR(INDEX(Benchmark_Table!$H$2:$BL$136,MATCH(AZ8&AZ7&AZ9,Benchmark_Table!$G$2:$G$136,0),MATCH(IF(OR(AZ10="Too Low",AZ10="Low"),"R&D_Growth_Low",IF(OR(AZ10="Too High",AZ10="High"),"R&D_Growth_High","R&D_Growth_Base")),Benchmark_Table!$H$1:$BL$1,0))*1,AU11),AU11) -> 0.2 | BA11: =_xlfn.IFNA(IFERROR(INDEX(Benchmark_Table!$H$2:$BL$136,MATCH(AZ8&AZ7&AZ9,Benchmark_Table!$G$2:$G$136,0),MATCH(IF(OR(AZ10="Too Low",AZ10="Low"),"R&D_Growth_Low",IF(OR(AZ10="Too High",AZ10="High"),"R&D_Growth_High","R&D_Growth_Base")),Benchmark_Table!$H$1:$BL$1,0))*1,AU11),AU11) -> 0.2 | BB11: =_xlfn.IFNA(IFERROR(INDEX(Benchmark_Table!$H$2:$BL$136,MATCH(AZ8&AZ7&AZ9,Benchmark_Table!$G$2:$G$136,0),MATCH(IF(OR(AZ10="Too Low",AZ10="Low"),"R&D_Growth_Low",IF(OR(AZ10="Too High",AZ10="High"),"R&D_Growth_High","R&D_Growth_Base")),Benchmark_Table!$H$1:$BL$1,0))*1,AU11),AU11) -> 0.2 | BC11: =_xlfn.IFNA(IFERROR(INDEX(Benchmark_Table!$H$2:$BL$136,MATCH(AZ8&AZ7&AZ9,Benchmark_Table!$G$2:$G$136,0),MATCH(IF(OR(AZ10="Too Low",AZ10="Low"),"R&D_Growth_Low",IF(OR(AZ10="Too High",AZ10="High"),"R&D_Growth_High","R&D_Growth_Base")),Benchmark_Table!$H$1:$BL$1,0))*1,AU11),AU11) -> 0.2 | BD11: =_xlfn.IFNA(IFERROR(INDEX(Benchmark_Table!$H$2:$BL$136,MATCH(AZ8&AZ7&AZ9,Benchmark_Table!$G$2:$G$136,0),MATCH(IF(OR(AZ10="Too Low",AZ10="Low"),"R&D_Growth_Low",IF(OR(AZ10="Too High",AZ10="High"),"R&D_Growth_High","R&D_Growth_Base")),Benchmark_Table!$H$1:$BL$1,0))*1,AU11),AU11) -> 0.2 | BE11: =_xlfn.IFNA(IFERROR(INDEX(Benchmark_Table!$H$2:$BL$136,MATCH(BE8&BE7&BE9,Benchmark_Table!$G$2:$G$136,0),MATCH(IF(OR(BE10="Too Low",BE10="Low"),"R&D_Growth_Low",IF(OR(BE10="Too High",BE10="High"),"R&D_Growth_High","R&D_Growth_Base")),Benchmark_Table!$H$1:$BL$1,0))*1,AZ11),AZ11) -> 0.2 | BF11: =_xlfn.IFNA(IFERROR(INDEX(Benchmark_Table!$H$2:$BL$136,MATCH(BE8&BE7&BE9,Benchmark_Table!$G$2:$G$136,0),MATCH(IF(OR(BE10="Too Low",BE10="Low"),"R&D_Growth_Low",IF(OR(BE10="Too High",BE10="High"),"R&D_Growth_High","R&D_Growth_Base")),Benchmark_Table!$H$1:$BL$1,0))*1,AZ11),AZ11) -> 0.2 | BG11: =_xlfn.IFNA(IFERROR(INDEX(Benchmark_Table!$H$2:$BL$136,MATCH(BE8&BE7&BE9,Benchmark_Table!$G$2:$G$136,0),MATCH(IF(OR(BE10="Too Low",BE10="Low"),"R&D_Growth_Low",IF(OR(BE10="Too High",BE10="High"),"R&D_Growth_High","R&D_Growth_Base")),Benchmark_Table!$H$1:$BL$1,0))*1,AZ11),AZ11) -> 0.2 | BH11: =_xlfn.IFNA(IFERROR(INDEX(Benchmark_Table!$H$2:$BL$136,MATCH(BE8&BE7&BE9,Benchmark_Table!$G$2:$G$136,0),MATCH(IF(OR(BE10="Too Low",BE10="Low"),"R&D_Growth_Low",IF(OR(BE10="Too High",BE10="High"),"R&D_Growth_High","R&D_Growth_Base")),Benchmark_Table!$H$1:$BL$1,0))*1,AZ11),AZ11) -> 0.2 | BI11: =_xlfn.IFNA(IFERROR(INDEX(Benchmark_Table!$H$2:$BL$136,MATCH(BE8&BE7&BE9,Benchmark_Table!$G$2:$G$136,0),MATCH(IF(OR(BE10="Too Low",BE10="Low"),"R&D_Growth_Low",IF(OR(BE10="Too High",BE10="High"),"R&D_Growth_High","R&D_Growth_Base")),Benchmark_Table!$H$1:$BL$1,0))*1,AZ11),AZ11) -> 0.2 | BJ11: =_xlfn.IFNA(IFERROR(INDEX(Benchmark_Table!$H$2:$BL$136,MATCH(BJ8&BJ7&BJ9,Benchmark_Table!$G$2:$G$136,0),MATCH(IF(OR(BJ10="Too Low",BJ10="Low"),"R&D_Growth_Low",IF(OR(BJ10="Too High",BJ10="High"),"R&D_Growth_High","R&D_Growth_Base")),Benchmark_Table!$H$1:$BL$1,0))*1,BE11),BE11) -> 0.2 | BK11: =_xlfn.IFNA(IFERROR(INDEX(Benchmark_Table!$H$2:$BL$136,MATCH(BJ8&BJ7&BJ9,Benchmark_Table!$G$2:$G$136,0),MATCH(IF(OR(BJ10="Too Low",BJ10="Low"),"R&D_Growth_Low",IF(OR(BJ10="Too High",BJ10="High"),"R&D_Growth_High","R&D_Growth_Base")),Benchmark_Table!$H$1:$BL$1,0))*1,BE11),BE11) -> 0.2 | BL11: =_xlfn.IFNA(IFERROR(INDEX(Benchmark_Table!$H$2:$BL$136,MATCH(BJ8&BJ7&BJ9,Benchmark_Table!$G$2:$G$136,0),MATCH(IF(OR(BJ10="Too Low",BJ10="Low"),"R&D_Growth_Low",IF(OR(BJ10="Too High",BJ10="High"),"R&D_Growth_High","R&D_Growth_Base")),Benchmark_Table!$H$1:$BL$1,0))*1,BE11),BE11) -> 0.2 | BM11: =_xlfn.IFNA(IFERROR(INDEX(Benchmark_Table!$H$2:$BL$136,MATCH(BJ8&BJ7&BJ9,Benchmark_Table!$G$2:$G$136,0),MATCH(IF(OR(BJ10="Too Low",BJ10="Low"),"R&D_Growth_Low",IF(OR(BJ10="Too High",BJ10="High"),"R&D_Growth_High","R&D_Growth_Base")),Benchmark_Table!$H$1:$BL$1,0))*1,BE11),BE11) -> 0.2 | BN11: =_xlfn.IFNA(IFERROR(INDEX(Benchmark_Table!$H$2:$BL$136,MATCH(BJ8&BJ7&BJ9,Benchmark_Table!$G$2:$G$136,0),MATCH(IF(OR(BJ10="Too Low",BJ10="Low"),"R&D_Growth_Low",IF(OR(BJ10="Too High",BJ10="High"),"R&D_Growth_High","R&D_Growth_Base")),Benchmark_Table!$H$1:$BL$1,0))*1,BE11),BE11) -> 0.2
A12: Avg Annual Salary per R&D FTE (USD) | E12: Annual → | F12: 100000
A14: # of R&D FTEs | G14: =K14 -> 3 | H14: =K14 -> 3 | I14: =K14 -> 3 | J14: =K14 -> 3 | K14: =IFERROR('Customer''s Questionnaire'!I69*1,0) -> 3 | L14: =P14 -> 4 | M14: =P14 -> 4 | N14: =P14 -> 4 | O14: =P14 -> 4 | P14: =IFERROR('Customer''s Questionnaire'!J69*1,0) -> 4 | Q14: =U14 -> 5.32 | R14: =U14 -> 5.32 | S14: =U14 -> 5.32 | T14: =U14 -> 5.32 | U14: =P14*(1+Q11) -> 5.32 | V14: =Z14 -> 6.8096 | W14: =Z14 -> 6.8096 | X14: =Z14 -> 6.8096 | Y14: =Z14 -> 6.8096 | Z14: =U14*(1+V11) -> 6.8096 | AA14: =AE14 -> 8.17152 | AB14: =AE14 -> 8.17152 | AC14: =AE14 -> 8.17152 | AD14: =AE14 -> 8.17152 | AE14: =Z14*(1+AA11) -> 8.17152 | AF14: =AJ14 -> 9.805824 | AG14: =AJ14 -> 9.805824 | AH14: =AJ14 -> 9.805824 | AI14: =AJ14 -> 9.805824 | AJ14: =AE14*(1+AF11) -> 9.805824 | AK14: =AO14 -> 11.766989 | AL14: =AO14 -> 11.766989 | AM14: =AO14 -> 11.766989 | AN14: =AO14 -> 11.766989 | AO14: =AJ14*(1+AK11) -> 11.766989 | AP14: =AT14 -> 14.120387 | AQ14: =AT14 -> 14.120387 | AR14: =AT14 -> 14.120387 | AS14: =AT14 -> 14.120387 | AT14: =AO14*(1+AP11) -> 14.120387 | AU14: =AY14 -> 16.944464 | AV14: =AY14 -> 16.944464 | AW14: =AY14 -> 16.944464 | AX14: =AY14 -> 16.944464 | AY14: =AT14*(1+AU11) -> 16.944464 | AZ14: =BD14 -> 20.333357 | BA14: =BD14 -> 20.333357 | BB14: =BD14 -> 20.333357 | BC14: =BD14 -> 20.333357 | BD14: =AY14*(1+AZ11) -> 20.333357 | BE14: =BI14 -> 24.400028 | BF14: =BI14 -> 24.400028 | BG14: =BI14 -> 24.400028 | BH14: =BI14 -> 24.400028 | BI14: =BD14*(1+BE11) -> 24.400028 | BJ14: =BN14 -> 29.280034 | BK14: =BN14 -> 29.280034 | BL14: =BN14 -> 29.280034 | BM14: =BN14 -> 29.280034 | BN14: =BI14*(1+BJ11) -> 29.280034
A15: R&D Salaries | G15: =G14*$F12/4 -> 75000 | H15: =H14*$F12/4 -> 75000 | I15: =I14*$F12/4 -> 75000 | J15: =J14*$F12/4 -> 75000 | K15: =SUM(G15:J15) -> 300000 | L15: =L14*$F12/4 -> 100000 | M15: =M14*$F12/4 -> 100000 | N15: =N14*$F12/4 -> 100000 | O15: =O14*$F12/4 -> 100000 | P15: =SUM(L15:O15) -> 400000 | Q15: =Q14*$F12/4 -> 133000 | R15: =R14*$F12/4 -> 133000 | S15: =S14*$F12/4 -> 133000 | T15: =T14*$F12/4 -> 133000 | U15: =SUM(Q15:T15) -> 532000 | V15: =V14*$F12/4 -> 170240 | W15: =W14*$F12/4 -> 170240 | X15: =X14*$F12/4 -> 170240 | Y15: =Y14*$F12/4 -> 170240 | Z15: =SUM(V15:Y15) -> 680960 | AA15: =AA14*$F12/4 -> 204288 | AB15: =AB14*$F12/4 -> 204288 | AC15: =AC14*$F12/4 -> 204288 | AD15: =AD14*$F12/4 -> 204288 | AE15: =SUM(AA15:AD15) -> 817152 | AF15: =AF14*$F12/4 -> 245145.6 | AG15: =AG14*$F12/4 -> 245145.6 | AH15: =AH14*$F12/4 -> 245145.6 | AI15: =AI14*$F12/4 -> 245145.6 | AJ15: =SUM(AF15:AI15) -> 980582.4 | AK15: =AK14*$F12/4 -> 294174.72 | AL15: =AL14*$F12/4 -> 294174.72 | AM15: =AM14*$F12/4 -> 294174.72 | AN15: =AN14*$F12/4 -> 294174.72 | AO15: =SUM(AK15:AN15) -> 1176698.9 | AP15: =AP14*$F12/4 -> 353009.66 | AQ15: =AQ14*$F12/4 -> 353009.66 | AR15: =AR14*$F12/4 -> 353009.66 | AS15: =AS14*$F12/4 -> 353009.66 | AT15: =SUM(AP15:AS15) -> 1412038.7 | AU15: =AU14*$F12/4 -> 423611.6 | AV15: =AV14*$F12/4 -> 423611.6 | AW15: =AW14*$F12/4 -> 423611.6 | AX15: =AX14*$F12/4 -> 423611.6 | AY15: =SUM(AU15:AX15) -> 1694446.4 | AZ15: =AZ14*$F12/4 -> 508333.92 | BA15: =BA14*$F12/4 -> 508333.92 | BB15: =BB14*$F12/4 -> 508333.92 | BC15: =BC14*$F12/4 -> 508333.92 | BD15: =SUM(AZ15:BC15) -> 2033335.7 | BE15: =BE14*$F12/4 -> 610000.7 | BF15: =BF14*$F12/4 -> 610000.7 | BG15: =BG14*$F12/4 -> 610000.7 | BH15: =BH14*$F12/4 -> 610000.7 | BI15: =SUM(BE15:BH15) -> 2440002.8 | BJ15: =BJ14*$F12/4 -> 732000.84 | BK15: =BK14*$F12/4 -> 732000.84 | BL15: =BL14*$F12/4 -> 732000.84 | BM15: =BM14*$F12/4 -> 732000.84 | BN15: =SUM(BJ15:BM15) -> 2928003.4
A16: R&D Subcontractors (input) | G16: 0 | H16: 0 | I16: 0 | J16: 0 | K16: =SUM(G16:J16) -> 0 | L16: 0 | M16: 0 | N16: 0 | O16: 0 | P16: =SUM(L16:O16) -> 0 | Q16: 0 | R16: 0 | S16: 0 | T16: 0 | U16: =SUM(Q16:T16) -> 0 | V16: 0 | W16: 0 | X16: 0 | Y16: 0 | Z16: =SUM(V16:Y16) -> 0 | AA16: 0 | AB16: 0 | AC16: 0 | AD16: 0 | AE16: =SUM(AA16:AD16) -> 0 | AF16: 0 | AG16: 0 | AH16: 0 | AI16: 0 | AJ16: =SUM(AF16:AI16) -> 0 | AK16: 0 | AL16: 0 | AM16: 0 | AN16: 0 | AO16: =SUM(AK16:AN16) -> 0 | AP16: 0 | AQ16: 0 | AR16: 0 | AS16: 0 | AT16: =SUM(AP16:AS16) -> 0 | AU16: 0 | AV16: 0 | AW16: 0 | AX16: 0 | AY16: =SUM(AU16:AX16) -> 0 | AZ16: 0 | BA16: 0 | BB16: 0 | BC16: 0 | BD16: =SUM(AZ16:BC16) -> 0 | BE16: 0 | BF16: 0 | BG16: 0 | BH16: 0 | BI16: =SUM(BE16:BH16) -> 0 | BJ16: 0 | BK16: 0 | BL16: 0 | BM16: 0 | BN16: =SUM(BJ16:BM16) -> 0
A17: R&D Other Variable Costs (input) | G17: 0 | H17: 0 | I17: 0 | J17: 0 | K17: =SUM(G17:J17) -> 0 | L17: 0 | M17: 0 | N17: 0 | O17: 0 | P17: =SUM(L17:O17) -> 0 | Q17: 0 | R17: 0 | S17: 0 | T17: 0 | U17: =SUM(Q17:T17) -> 0 | V17: 0 | W17: 0 | X17: 0 | Y17: 0 | Z17: =SUM(V17:Y17) -> 0 | AA17: 0 | AB17: 0 | AC17: 0 | AD17: 0 | AE17: =SUM(AA17:AD17) -> 0 | AF17: 0 | AG17: 0 | AH17: 0 | AI17: 0 | AJ17: =SUM(AF17:AI17) -> 0 | AK17: 0 | AL17: 0 | AM17: 0 | AN17: 0 | AO17: =SUM(AK17:AN17) -> 0 | AP17: 0 | AQ17: 0 | AR17: 0 | AS17: 0 | AT17: =SUM(AP17:AS17) -> 0 | AU17: 0 | AV17: 0 | AW17: 0 | AX17: 0 | AY17: =SUM(AU17:AX17) -> 0 | AZ17: 0 | BA17: 0 | BB17: 0 | BC17: 0 | BD17: =SUM(AZ17:BC17) -> 0 | BE17: 0 | BF17: 0 | BG17: 0 | BH17: 0 | BI17: =SUM(BE17:BH17) -> 0 | BJ17: 0 | BK17: 0 | BL17: 0 | BM17: 0 | BN17: =SUM(BJ17:BM17) -> 0
A18: Total R&D OPEX | G18: =G15+G16+G17 -> 75000 | H18: =H15+H16+H17 -> 75000 | I18: =I15+I16+I17 -> 75000 | J18: =J15+J16+J17 -> 75000 | K18: =K15+K16+K17 -> 300000 | L18: =L15+L16+L17 -> 100000 | M18: =M15+M16+M17 -> 100000 | N18: =N15+N16+N17 -> 100000 | ... BN18: =BN15+BN16+BN17 -> 2928003.4
A21: S&M — Operating Expenses
A22: Selected Stage | F22: ='Customer''s Questionnaire'!I9 -> Round C | G22: =G7 -> Round C | L22: =L7 -> Series C | Q22: =Q7 -> Series C | V22: =V7 -> Series D/E | AA22: =AA7 -> Pre-IPO | AF22: =AF7 -> Pre-IPO | AK22: =AK7 -> Pre-IPO | AP22: =AP7 -> Pre-IPO | AU22: =AU7 -> Pre-IPO | AZ22: =AZ7 -> Pre-IPO | BE22: =BE7 -> Pre-IPO | BJ22: =BJ7 -> Pre-IPO
A23: Selected Sector | F23: ='Customer''s Questionnaire'!I8 -> Food-Tech / Ag-Tech | G23: =G8 -> Food-Tech / Ag-Tech | L23: =L8 -> Food-Tech / Ag-Tech | Q23: =Q8 -> Food-Tech / Ag-Tech | V23: =V8 -> Food-Tech / Ag-Tech | AA23: =AA8 -> Food-Tech / Ag-Tech | AF23: =AF8 -> Food-Tech / Ag-Tech | AK23: =AK8 -> Food-Tech / Ag-Tech | AP23: =AP8 -> Food-Tech / Ag-Tech | AU23: =AU8 -> Food-Tech / Ag-Tech | AZ23: =AZ8 -> Food-Tech / Ag-Tech | BE23: =BE8 -> Food-Tech / Ag-Tech | BJ23: =BJ8 -> Food-Tech / Ag-Tech
A24: Avg_Years_Since_Founding | F24: ='Customer''s Questionnaire'!$I$11 -> 7 | G24: =G9 -> 7 | L24: =L9 -> 8 | Q24: =Q9 -> 9 | V24: =V9 -> 10 | AA24: =AA9 -> 11 | AF24: =AF9 -> 12 | AK24: =AK9 -> 13 | AP24: =AP9 -> 14 | AU24: =AU9 -> 15 | AZ24: =AZ9 -> 16 | BE24: =BE9 -> 17 | BJ24: =BJ9 -> 18
A25: OPEX Benchmark | F25: ='Customer''s Questionnaire'!$J$10 -> Too High | G25: =G10 -> Too High | L25: =L10 -> Too High | Q25: =Q10 -> Too High | V25: =V10 -> Too High | AA25: =AA10 -> Too High | AF25: =AF10 -> Too High | AK25: =AK10 -> Too High | AP25: =AP10 -> Too High | AU25: =AU10 -> Too High | AZ25: =AZ10 -> Too High | BE25: =BE10 -> Too High | BJ25: =BJ10 -> Too High
